Workbook
Name ETE: #REF!
Name GN: #REF!
Name GR: #REF!
Name MANC: #REF!
Name MUN: #REF!
Name NG: #REF!

Sheet IT PEI
A1: Año | B1: N G 1 | C1: N G 2 | D1: Fecha de recepción | E1: Periodo PEI | F1: Vigencia | G1: Tipo de PEI | H1: Estado_PEI | I1: Responsable Institucional | J1: Cantidad de revisiones | K1: Fecha de derivación | L1: Etapas de revisión | M1: Comentario adicional/ Emisor de I.T | N1: Articulación | O1: Expediente | P1: Fecha de I.T | Q1: Número de I.T | R1: Fecha Oficio | S1: Número Oficio | T1: Id_Sector | U1: nombre_sector | V1: Id_Pliego | W1: Nombre_pliego | X1: Id_UE | Y1: Nombre_unidad_ejecutora | Z1: Id_Departamento | AA1: nombre_departamento | AB1: Id_Provincia | AC1: nombre_provincia | AD1: Id_4Distrito | AE1: nombre_distrito | AF1: id_registro | AG1: last_updated | AH1: updated_by
A2: 2016 | B2: GN | C2: GN | D2: 42713 | E2: 2017-2019 | F2: NO | G2: FORMULADO | H2: EMITIDO | P2: 42713 | Q2: 024-2016-CEPLAN/DNCP-FI | T2: 1 | U2: PRESIDENCIA CONSEJO MINISTROS | V2: 23 | W2: AUTORIDAD NACIONAL DEL SERVICIO CIVIL | X2: 1314 | Y2: AUTORIDAD NACIONAL DE SERVICIO CIVIL | Z2: 15 | AA2: LIMA | AB2: 1 | AC2: LIMA | AD2: 13 | AE2: JESUS MARIA
A3: 2016 | B3: GN | C3: GN | D3: 42730 | E3: 2017-2019 | F3: NO | G3: FORMULADO | H3: EMITIDO | P3: 42730 | Q3: 042-2016-CEPLAN/DNCP-FI | T3: 9 | U3: ECONOMIA Y FINANZAS | V3: 96 | W3: CENTRAL DE COMPRAS PÚBLICAS - PERÚ COMPRAS | X3: 1650 | Y3: CENTRAL DE COMPRAS PUBLICAS - PERU COMPRAS | Z3: 15 | AA3: LIMA | AB3: 1 | AC3: LIMA | AD3: 31 | AE3: SAN ISIDRO
A4: 2016 | B4: GN | C4: GN | D4: 42731 | E4: 2017-2019 | F4: NO | G4: FORMULADO | H4: EMITIDO | P4: 42731 | Q4: 046-2016-CEPLAN/DNCP-FI | T4: 26 | U4: DEFENSA | V4: 25 | W4: CENTRO NACIONAL DE ESTIMACION, PREVENCION Y REDUCCION DEL RIESGO DE DESASTRES - CENEPRED | X4: 1410 | Y4: CENTRO NAC. DE ESTIMACION, PREVENCION Y REDUCCION DE RIESGOS DE DESASTRES- CENEPRED | Z4: 15 | AA4: LIMA | AB4: 1 | AC4: LIMA | AD4: 31 | AE4: SAN ISIDRO
A5: 2016 | B5: GN | C5: GN | D5: 42733 | E5: 2017-2019 | F5: NO | G5: FORMULADO | H5: EMITIDO | P5: 42733 | Q5: 055-2016-CEPLAN/DNCP-FI | T5: 1 | U5: PRESIDENCIA CONSEJO MINISTROS | V5: 12 | W5: COMISION NACIONAL PARA EL DESARROLLO Y VIDA SIN DROGAS - DEVIDA | X5: 1064 | Y5: COMISION NAC. PARA EL DESARROLLO Y VIDA SIN DROGAS - DEVIDA | Z5: 15 | AA5: LIMA | AB5: 1 | AC5: LIMA | AD5: 1 | AE5: LIMA
A6: 2016 | B6: GN | C6: GN | D6: 42591 | E6: 2016-2018 | F6: NO | G6: FORMULADO | H6: EMITIDO | P6: 42591 | Q6: 018-2016-CEPLAN/DNCP-FI | T6: 38 | U6: PRODUCCION | V6: 59 | W6: FONDO NACIONAL DE DESARROLLO PESQUERO - FONDEPES | X6: 192 | Y6: FONDO NACIONAL DE DESARROLLO PESQUERO-FONDEPES | Z6: 15 | AA6: LIMA | AB6: 1 | AC6: LIMA | AD6: 1 | AE6: LIMA
A7: 2016 | B7: GR | C7: GR | D7: 42725 | E7: 2017-2019 | F7: NO | G7: FORMULADO | H7: EMITIDO | P7: 42725 | Q7: 038-2016-CEPLAN/DNCP-FI | T7: 99 | U7: GOBIERNOS REGIONALES | V7: 440 | W7: GOBIERNO REGIONAL DEL DEPARTAMENTO DE AMAZONAS | X7: 721 | Y7: REGION AMAZONAS-SEDE CENTRAL | Z7: 1 | AA7: AMAZONAS | AB7: 1 | AC7: CHACHAPOYAS | AD7: 1 | AE7: CHACHAPOYAS
A8: 2016 | B8: GR | C8: GR | D8: 42731 | E8: 2017-2019 | F8: NO | G8: FORMULADO | H8: EMITIDO | P8: 42731 | Q8: 048-2016-CEPLAN/DNCP-FI | T8: 99 | U8: GOBIERNOS REGIONALES | V8: 441 | W8: GOBIERNO REGIONAL DEL DEPARTAMENTO DE ANCASH | X8: 726 | Y8: REGION ANCASH SEDE CENTRAL | Z8: 2 | AA8: ANCASH | AB8: 1 | AC8: HUARAZ | AD8: 1 | AE8: HUARAZ
A9: 2016 | B9: GR | C9: GR | D9: 42444 | E9: 2016-2018 | F9: NO | G9: FORMULADO | H9: EMITIDO | P9: 42444 | Q9: 007-2016-CEPLAN/DNCP-FI | T9: 99 | U9: GOBIERNOS REGIONALES | V9: 444 | W9: GOBIERNO REGIONAL DEL DEPARTAMENTO DE AYACUCHO | X9: 770 | Y9: REGION AYACUCHO-SEDE CENTRAL | Z9: 5 | AA9: AYACUCHO | AB9: 1 | AC9: HUAMANGA | AD9: 1 | AE9: AYACUCHO
A10: 2016 | B10: GR | C10: GR | D10: 42383 | E10: 2015-2017 | F10: NO | G10: FORMULADO | H10: EMITIDO | P10: 42383 | Q10: 002-2016-CEPLAN/DNCP-DHC | T10: 99 | U10: GOBIERNOS REGIONALES | V10: 450 | W10: GOBIERNO REGIONAL DEL DEPARTAMENTO DE JUNIN | X10: 818 | Y10: REGION JUNIN-SEDE CENTRAL | Z10: 12 | AA10: JUNIN | AB10: 1 | AC10: HUANCAYO | AD10: 1 | AE10: HUANCAYO
A11: 2016 | B11: GR | C11: GR | D11: 42384 | E11: 2016-2018 | F11: NO | G11: FORMULADO | H11: EMITIDO | P11: 42384 | Q11: 003-2016-CEPLAN/DNCP-DHC | T11: 99 | U11: GOBIERNOS REGIONALES | V11: 453 | W11: GOBIERNO REGIONAL DEL DEPARTAMENTO DE LORETO | X11: 861 | Y11: REGION LORETO-SEDE CENTRAL | Z11: 16 | AA11: LORETO | AB11: 1 | AC11: MAYNAS | AD11: 12 | AE11: BELEN
A12: 2016 | B12: GR | C12: GR | D12: 42604 | E12: 2015-2017 | F12: NO | G12: FORMULADO | H12: EMITIDO | P12: 42604 | Q12: 019-2016-CEPLAN/DNCP-FI | T12: 99 | U12: GOBIERNOS REGIONALES | V12: 455 | W12: GOBIERNO REGIONAL DEL DEPARTAMENTO DE MOQUEGUA | X12: 880 | Y12: REGION MOQUEGUA-SEDE CENTRAL | Z12: 18 | AA12: MOQUEGUA | AB12: 1 | AC12: MARISCAL NIETO | AD12: 1 | AE12: MOQUEGUA
A13: 2016 | B13: GR | C13: GR | D13: 42734 | E13: 2017-2019 | F13: NO | G13: FORMULADO | H13: EMITIDO | P13: 42734 | Q13: 057-2016-CEPLAN/DNCP-FI | T13: 99 | U13: GOBIERNOS REGIONALES | V13: 456 | W13: GOBIERNO REGIONAL DEL DEPARTAMENTO DE PASCO | X13: 885 | Y13: REGION PASCO-SEDE CENTRAL | Z13: 19 | AA13: PASCO | AB13: 1 | AC13: PASCO | AD13: 13 | AE13: YANACANCHA
... A181: 2018 | B181: GN | C181: GN | D181: 43181 | E181: 2018-2021 | F181: NO | G181: FORMULADO | H181: EMITIDO | P181: 43181 | Q181: 016-2018-CEPLAN/DNCP-PEI | T181: 5 | U181: AMBIENTAL | V181: 5 | W181: M. DEL AMBIENTE | X181: 1293 | Y181: MINISTERIO DEL AMBIENTE - ADMINISTRACION GENERAL | Z181: 15 | AA181: LIMA | AB181: 1 | AC181: LIMA | AD181: 31 | AE181: SAN ISIDRO
A182: 2018 | B182: MANC | C182: MANC | D182: 43159 | E182: 2019-2022 | F182: NO | G182: FORMULADO | H182: EMITIDO | P182: 43159 | Q182: 144-2018-CEPLAN/DNCP-PEI | T182: #N/A | U182: #N/A | V182: #N/A | W182: MANCOMUNIDAD NORVRAEM | X182: #N/D | Y182: MANCOMUNIDAD NORVRAEM | Z182: #N/D | AA182: #N/D | AB182: ## | AC182: #N/D | AD182: #N/D | AE182: #N/D
A183: 2018 | B183: MANC | C183: MANC | D183: 43157 | E183: 2018-2021 | F183: NO | G183: FORMULADO | H183: EMITIDO | P183: 43157 | Q183: 010-2018-CEPLAN/DNCP-PEI | T183: 98 | U183: Mancomunidades Regionales | V183: 360001 | W183: MANCOMUNIDAD REGIONAL DE LOS ANDES | X183: 360001 | Y183: MANCOMUNIDAD REGIONAL DE LOS ANDES | Z183: #N/D | AA183: #N/D | AB183: ## | AC183: #N/D | AD183: #N/D | AE183: #N/D
A184: 2018 | B184: GN | C184: GN | D184: 43465 | E184: 2019-2022 | F184: NO | G184: FORMULADO | H184: EMITIDO | P184: 43465 | Q184: 138-2018-CEPLAN/DNCP-PEI | T184: 39 | U184: MUJER Y POBLACIONES VULNERABLES | V184: 39 | W184: MINISTERIO DE LA MUJER Y POBLACIONES VULNERABLES | X184: 1087 | Y184: MINISTERIO DE LA MUJER Y POBLACIONES VULNERABLES- ADM. NIVEL CENTRAL | Z184: 15 | AA184: LIMA | AB184: 1 | AC184: LIMA | AD184: 1 | AE184: LIMA
A185: 2018 | B185: GN | C185: GN | D185: 43462 | E185: 2018-2021 | F185: NO | G185: FORMULADO | H185: EMITIDO | P185: 43462 | Q185: 134-2018-CEPLANIDNCP-PEI | T185: 36 | U185: TRANSPORTES Y COMUNICACIONES | V185: 36 | W185: MINISTERIO DE TRANSPORTES Y COMUNICACIONES | X185: 1072 | Y185: MINISTERIO DE TRANSPORTES Y COMUNICACIONES-ADMINISTRACION GENERAL | Z185: 15 | AA185: LIMA | AB185: 1 | AC185: LIMA | AD185: 1 | AE185: LIMA
A186: 2018 | B186: MUN | C186: MD | D186: 43434 | E186: 2019-2022 | F186: NO | G186: FORMULADO | H186: EMITIDO | P186: 43434 | Q186: 092-2018-CEPLAN/DNCP-PEI | T186: 0 | U186: FICTICIO | V186: 300679 | W186: MUNICIPALIDAD DISTRITAL DE CARMEN DE LA LEGUA REYNOSO | X186: 300679 | Y186: MUNICIPALIDAD DISTRITAL DE CARMEN DE LA LEGUA REYNOSO | Z186: 7 | AA186: PROVINCIA CONSTITUCIONAL DEL CALLAO | AB186: 1 | AC186: PROV. CALLAO | AD186: 3 | AE186: CARMEN DE LA LEGUA REYNOSO
A187: 2018 | B187: MUN | C187: MD | D187: 43390 | E187: 2019-2022 | F187: NO | G187: FORMULADO | H187: EMITIDO | P187: 43390 | Q187: 077-2018-CEPLAN/DNCP-PEI | T187: 0 | U187: FICTICIO | V187: 300332 | W187: MUNICIPALIDAD DISTRITAL DE ALTO SELVA ALEGRE | X187: 300332 | Y187: MUNICIPALIDAD DISTRITAL DE ALTO SELVA ALEGRE | Z187: 4 | AA187: AREQUIPA | AB187: 1 | AC187: AREQUIPA | AD187: 2 | AE187: ALTO SELVA ALEGRE
A188: 2018 | B188: MUN | C188: MD | D188: 43236 | E188: 2018-2020 | F188: NO | G188: FORMULADO | H188: EMITIDO | P188: 43236 | Q188: 027-2018-CEPLAN/DNCP-PEI | T188: 0 | U188: FICTICIO | V188: 300786 | W188: MUNICIPALIDAD DISTRITAL DE CHINCHERO | X188: 300786 | Y188: MUNICIPALIDAD DISTRITAL DE CHINCHERO | Z188: 8 | AA188: CUSCO | AB188: 13 | AC188: URUBAMBA | AD188: 2 | AE188: CHINCHERO
A189: 2018 | B189: MUN | C189: MD | D189: 43453 | E189: 2019-2022 | F189: NO | G189: FORMULADO | H189: EMITIDO | P189: 43453 | Q189: 119-2018-CEPLAN/DNCP-PEI | T189: 0 | U189: FICTICIO | V189: 301258 | W189: MUNICIPALIDAD DISTRITAL DE CIENEGUILLA | X189: 301258 | Y189: MUNICIPALIDAD DISTRITAL DE CIENEGUILLA | Z189: 15 | AA189: LIMA | AB189: 1 | AC189: LIMA | AD189: 9 | AE189: CIENEGUILLA
A190: 2018 | B190: MUN | C190: MD | D190: 43416 | E190: 2019-2022 | F190: NO | G190: FORMULADO | H190: EMITIDO | P190: 43416 | Q190: 085-2018-CEPLAN/DNCP-PEI | T190: 0 | U190: FICTICIO | V190: 300749 | W190: MUNICIPALIDAD DISTRITAL DE ECHARATI | X190: 300749 | Y190: MUNICIPALIDAD DISTRITAL DE ECHARATI | Z190: 8 | AA190: CUSCO | AB190: 9 | AC190: LA CONVENCION | AD190: 2 | AE190: ECHARATI
A191: 2018 | B191: MUN | C191: MD | D191: 43225 | E191: 2018-2021 | F191: NO | G191: FORMULADO | H191: EMITIDO | P191: 43225 | Q191: 025-2018-CEPLAN/DNCP-PEI | T191: 0 | U191: FICTICIO | V191: 300874 | W191: MUNICIPALIDAD DISTRITAL DE HUACHOCOLPA | X191: 300874 | Y191: MUNICIPALIDAD DISTRITAL DE HUACHOCOLPA | Z191: 9 | AA191: HUANCAVELICA | AB191: 7 | AC191: TAYACAJA | AD191: 7 | AE191: HUACHOCOLPA
A192: 2018 | B192: MUN | C192: MD | D192: 43398 | E192: 2019-2022 | F192: NO | G192: FORMULADO | H192: EMITIDO | P192: 43398 | Q192: 082-2018-CEPLAN/DNCP-PEI | T192: 0 | U192: FICTICIO | V192: 301524 | W192: MUNICIPALIDAD DISTRITAL DE HUANCABAMBA | X192: 301524 | Y192: MUNICIPALIDAD DISTRITAL DE HUANCABAMBA | Z192: 19 | AA192: PASCO | AB192: 3 | AC192: OXAPAMPA | AD192: 3 | AE192: HUANCABAMBA
A193: 2018 | B193: MUN | C193: MD | D193: 43383 | E193: 2019-2021 | F193: NO | G193: FORMULADO | H193: EMITIDO | P193: 43383 | Q193: 073-2018-CEPLAN/DNCP-PEI | T193: 0 | U193: FICTICIO | V193: 300754 | W193: MUNICIPALIDAD DISTRITAL DE QUIMBIRI | X193: 300754 | Y193: MUNICIPALIDAD DISTRITAL DE QUIMBIRI | Z193: 8 | AA193: CUSCO | AB193: 9 | AC193: LA CONVENCION | AD193: 7 | AE193: QUIMBIRI
A194: 2018 | B194: MUN | C194: MD | D194: 43105 | E194: 2018-2020 | F194: NO | G194: FORMULADO | H194: EMITIDO | P194: 43105 | Q194: 002-2018-CEPLAN/DNCP-PEI | T194: 0 | U194: FICTICIO | V194: 301263 | W194: MUNICIPALIDAD DISTRITAL DE LA MOLINA | X194: 301263 | Y194: MUNICIPALIDAD DISTRITAL DE LA MOLINA | Z194: 15 | AA194: LIMA | AB194: 1 | AC194: LIMA | AD194: 14 | AE194: LA MOLINA
A195: 2018 | B195: MUN | C195: MD | D195: 43461 | E195: 2019-2021 | F195: NO | G195: FORMULADO | H195: EMITIDO | P195: 43461 | Q195: 132-2018-CEPLAN/DNCP-PEI | T195: 0 | U195: FICTICIO | V195: 300680 | W195: MUNICIPALIDAD DISTRITAL DE LA PERLA | X195: 300680 | Y195: MUNICIPALIDAD DISTRITAL DE LA PERLA | Z195: 7 | AA195: PROVINCIA CONSTITUCIONAL DEL CALLAO | AB195: 1 | AC195: PROV. CALLAO | AD195: 4 | AE195: LA PERLA
... A220: 2018 | B220: MUN | C220: MP | D220: 43440 | E220: 2019-2023 | F220: NO | G220: FORMULADO | H220: EMITIDO | P220: 43440 | Q220: 095-2018-CEPLAN/DNCP-PEI | T220: 0 | U220: FICTICIO | V220: 300022 | W220: MUNICIPALIDAD PROVINCIAL DE BAGUA | X220: 300022 | Y220: MUNICIPALIDAD PROVINCIAL DE BAGUA | Z220: 1 | AA220: AMAZONAS | AB220: 2 | AC220: BAGUA | AD220: 1 | AE220: BAGUA
A221: 2018 | B221: MUN | C221: MP | D221: 43341 | E221: 2019-2021 | F221: NO | G221: FORMULADO | H221: EMITIDO | I221: Filemon Sulca | P221: 43341 | Q221: 061-2018-CEPLAN/DNCP-PEI | T221: 0 | U221: FICTICIO | V221: 300724 | W221: MUNICIPALIDAD PROVINCIAL DE CANCHIS - SICUANI | X221: 300724 | Y221: MUNICIPALIDAD PROVINCIAL DE CANCHIS - SICUANI | Z221: 8 | AA221: CUSCO | AB221: 6 | AC221: CANCHIS | AD221: 1 | AE221: SICUANI
A222: 2018 | B222: MUN | C222: MP | D222: 43460 | E222: 2019-2022 | F222: NO | G222: FORMULADO | H222: EMITIDO | P222: 43460 | Q222: 123-2018-CEPLAN/DNCP-PEI | T222: 0 | U222: FICTICIO | V222: 301623 | W222: MUNICIPALIDAD PROVINCIAL DE CARABAYA - MACUSANI | X222: 301623 | Y222: MUNICIPALIDAD PROVINCIAL DE CARABAYA - MACUSANI | Z222: 21 | AA222: PUNO | AB222: 3 | AC222: CARABAYA | AD222: 1 | AE222: MACUSANI
A223: 2018 | B223: MUN | C223: MP | D223: 43215 | E223: 2019-2021 | F223: NO | G223: FORMULADO | H223: EMITIDO | P223: 43215 | Q223: 023-2018-CEPLAN/DNCP-PEI | T223: 0 | U223: FICTICIO | V223: 300125 | W223: MUNICIPALIDAD PROVINCIAL DE CARHUAZ | X223: 300125 | Y223: MUNICIPALIDAD PROVINCIAL DE CARHUAZ | Z223: 2 | AA223: ANCASH | AB223: 6 | AC223: CARHUAZ | AD223: 1 | AE223: CARHUAZ
A224: 2018 | B224: MUN | C224: MP | D224: 43357 | E224: 2019-2021 | F224: NO | G224: FORMULADO | H224: EMITIDO | P224: 43357 | Q224: 067-2018-CEPLAN/DNCP-PEI | T224: 0 | U224: FICTICIO | V224: 300829 | W224: MUNICIPALIDAD PROVINCIAL DE CASTROVIRREYNA | X224: 300829 | Y224: MUNICIPALIDAD PROVINCIAL DE CASTROVIRREYNA | Z224: 9 | AA224: HUANCAVELICA | AB224: 4 | AC224: CASTROVIRREYNA | AD224: 1 | AE224: CASTROVIRREYNA
A225: 2018 | B225: MUN | C225: MP | D225: 43263 | E225: 2019-2021 | F225: NO | G225: FORMULADO | H225: EMITIDO | P225: 43263 | Q225: 040-2018-CEPLAN/DNCP-PEI | T225: 0 | U225: FICTICIO | V225: 300001 | W225: MUNICIPALIDAD PROVINCIAL DE CHACHAPOYAS | X225: 300001 | Y225: MUNICIPALIDAD PROVINCIAL DE CHACHAPOYAS | Z225: 1 | AA225: AMAZONAS | AB225: 1 | AC225: CHACHAPOYAS | AD225: 1 | AE225: CHACHAPOYAS
A226: 2018 | B226: MUN | C226: MP | D226: 43430 | E226: 2019-2021 | F226: NO | G226: FORMULADO | H226: EMITIDO | P226: 43430 | Q226: 091-2018-CEPLAN/DNCP-PEI | T226: 0 | U226: FICTICIO | V226: 300842 | W226: MUNICIPALIDAD PROVINCIAL DE CHURCAMPA | X226: 300842 | Y226: MUNICIPALIDAD PROVINCIAL DE CHURCAMPA | Z226: 9 | AA226: HUANCAVELICA | AB226: 5 | AC226: CHURCAMPA | AD226: 1 | AE226: CHURCAMPA
A227: 2018 | B227: MUN | C227: MP | D227: 43461 | E227: 2019-2022 | F227: NO | G227: FORMULADO | H227: EMITIDO | P227: 43461 | Q227: 129-2018-CEPLAN/DNCP-PEI | T227: 0 | U227: FICTICIO | V227: 300040 | W227: MUNICIPALIDAD PROVINCIAL DE CONDORCANQUI - NIEVA | X227: 300040 | Y227: MUNICIPALIDAD PROVINCIAL DE CONDORCANQUI - NIEVA | Z227: 1 | AA227: AMAZONAS | AB227: 4 | AC227: CONDORCANQUI | AD227: 1 | AE227: NIEVA
A228: 2018 | B228: MUN | C228: MP | D228: 43391 | E228: 2019-2021 | F228: NO | G228: FORMULADO | H228: EMITIDO | P228: 43391 | Q228: 078-2018-CEPLAN/DNCP-PEI | T228: 0 | U228: FICTICIO | V228: 300740 | W228: MUNICIPALIDAD PROVINCIAL DE ESPINAR | X228: 300740 | Y228: MUNICIPALIDAD PROVINCIAL DE ESPINAR | Z228: 8 | AA228: CUSCO | AB228: 8 | AC228: ESPINAR | AD228: 1 | AE228: ESPINAR
A229: 2018 | B229: MUN | C229: MP | D229: 43301 | E229: 2019-2021 | F229: NO | G229: FORMULADO | H229: EMITIDO | P229: 43301 | Q229: 049-2018-CEPLAN/DNCP-PEI | T229: 0 | U229: FICTICIO | V229: 301232 | W229: MUNICIPALIDAD PROVINCIAL DE FERREÑAFE | X229: 301232 | Y229: MUNICIPALIDAD PROVINCIAL DE FERREÑAFE | Z229: 14 | AA229: LAMBAYEQUE | AB229: 2 | AC229: FERRENAFE | AD229: 1 | AE229: FERRENAFE
A230: 2018 | B230: MUN | C230: MP | D230: 43453 | E230: 2019-2022 | F230: NO | G230: FORMULADO | H230: EMITIDO | I230: Leidy Cayotopa / Ivan PNUD | P230: 43453 | Q230: 116-2018-CEPLAN/DNCP-PEI | T230: 0 | U230: FICTICIO | V230: 300916 | W230: MUNICIPALIDAD PROVINCIAL DE HUAMALIES - LLATA | X230: 300916 | Y230: MUNICIPALIDAD PROVINCIAL DE HUAMALIES - LLATA | Z230: 10 | AA230: HUANUCO | AB230: 5 | AC230: HUAMALIES | AD230: 1 | AE230: LLATA
A231: 2018 | B231: MUN | C231: MP | D231: 43311 | E231: 2019-2021 | F231: NO | G231: FORMULADO | H231: EMITIDO | P231: 43311 | Q231: 056-2018-CEPLAN/DNCP-PEI | T231: 0 | U231: FICTICIO | V231: 300460 | W231: MUNICIPALIDAD PROVINCIAL DE HUANCA SANCOS - SANCOS | X231: 300460 | Y231: MUNICIPALIDAD PROVINCIAL DE HUANCA SANCOS - SANCOS | Z231: 5 | AA231: AYACUCHO | AB231: 3 | AC231: HUANCA SANCOS | AD231: 1 | AE231: SANCOS
A232: 2018 | B232: MUN | C232: MP | D232: 43465 | E232: 2019-2022 | F232: NO | G232: FORMULADO | H232: EMITIDO | P232: 43465 | Q232: 143-2018-CEPLAN/DNCP-PEI | T232: 0 | U232: FICTICIO | V232: 301548 | W232: MUNICIPALIDAD PROVINCIAL DE HUANCABAMBA | X232: 301548 | Y232: MUNICIPALIDAD PROVINCIAL DE HUANCABAMBA | Z232: 20 | AA232: PIURA | AB232: 3 | AC232: HUANCABAMBA | AD232: 1 | AE232: HUANCABAMBA
A233: 2018 | B233: MUN | C233: MP | D233: 43451 | E233: 2019-2022 | F233: NO | G233: FORMULADO | H233: EMITIDO | P233: 43451 | Q233: 107-2018-CEPLAN/DNCP-PEI | T233: 0 | U233: FICTICIO | V233: 300885 | W233: MUNICIPALIDAD PROVINCIAL DE HUANUCO | X233: 300885 | Y233: MUNICIPALIDAD PROVINCIAL DE HUANUCO | Z233: 10 | AA233: HUANUCO | AB233: 1 | AC233: HUANUCO | AD233: 1 | AE233: HUANUCO
A234: 2018 | B234: MUN | C234: MP | D234: 43461 | E234: 2019-2022 | F234: NO | G234: FORMULADO | H234: EMITIDO | P234: 43461 | Q234: 130-2018-CEPLAN/DNCP-PEI | T234: 0 | U234: FICTICIO | V234: 301371 | W234: MUNICIPALIDAD PROVINCIAL DE HUAURA | X234: 301371 | Y234: MUNICIPALIDAD PROVINCIAL DE HUAURA | Z234: 15 | AA234: LIMA | AB234: 8 | AC234: HUAURA | AD234: 1 | AE234: HUACHO
A235: 2018 | B235: MUN | C235: MP | D235: 43437 | E235: 2019-2021 | F235: NO | G235: FORMULADO | H235: EMITIDO | I235: Vilma Celestino | P235: 43437 | Q235: 093-2018-CEPLAN/DNCP-PEI | T235: 0 | U235: FICTICIO | V235: 300171 | W235: MUNICIPALIDAD PROVINCIAL DE HUAYLAS - CARAZ | X235: 300171 | Y235: MUNICIPALIDAD PROVINCIAL DE HUAYLAS - CARAZ | Z235: 2 | AA235: ANCASH | AB235: 12 | AC235: HUAYLAS | AD235: 1 | AE235: CARAZ
A236: 2018 | B236: MUN | C236: MP | D236: 43460 | E236: 2019-2022 | F236: NO | G236: FORMULADO | H236: EMITIDO | P236: 43460 | Q236: 122-2018-CEPLAN/DNCP-PEI | T236: 0 | U236: FICTICIO | V236: 300960 | W236: MUNICIPALIDAD PROVINCIAL DE ICA | X236: 300960 | Y236: MUNICIPALIDAD PROVINCIAL DE ICA | Z236: 11 | AA236: ICA | AB236: 1 | AC236: ICA | AD236: 1 | AE236: ICA
A237: 2018 | B237: MUN | C237: MP | D237: 43104 | E237: 2018-2020 | F237: NO | G237: FORMULADO | H237: EMITIDO | P237: 43104 | Q237: 001-2018-CEPLAN/DNCP-PEI | T237: 0 | U237: FICTICIO | V237: 301498 | W237: MUNICIPALIDAD PROVINCIAL DE ILO | X237: 301498 | Y237: MUNICIPALIDAD PROVINCIAL DE ILO | Z237: 18 | AA237: MOQUEGUA | AB237: 3 | AC237: ILO | AD237: 1 | AE237: ILO
A238: 2018 | B238: MUN | C238: MP | D238: 43389 | E238: 2019-2022 | F238: NO | G238: FORMULADO | H238: EMITIDO | P238: 43389 | Q238: 076-2018-CEPLAN/DNCP-PEI | T238: 0 | U238: FICTICIO | V238: 300623 | W238: MUNICIPALIDAD PROVINCIAL DE JAEN | X238: 300623 | Y238: MUNICIPALIDAD PROVINCIAL DE JAEN | Z238: 6 | AA238: CAJAMARCA | AB238: 8 | AC238: JAEN | AD238: 1 | AE238: JAEN
A239: 2018 | B239: MUN | C239: MP | D239: 43395 | E239: 2019-2021 | F239: NO | G239: FORMULADO | H239: EMITIDO | P239: 43395 | Q239: 080-2018-CEPLAN/DNCP-PEI | T239: 0 | U239: FICTICIO | V239: 301294 | W239: MUNICIPALIDAD PROVINCIAL DE BARRANCA | X239: 301294 | Y239: MUNICIPALIDAD PROVINCIAL DE BARRANCA | Z239: 15 | AA239: LIMA | AB239: 2 | AC239: BARRANCA | AD239: 1 | AE239: BARRANCA
A240: 2018 | B240: MUN | C240: MP | D240: 43399 | E240: 2019-2021 | F240: NO | G240: FORMULADO | H240: EMITIDO | P240: 43399 | Q240: 083-2018-CEPLAN/DNCP-PEI | T240: 0 | U240: FICTICIO | V240: 301046 | W240: MUNICIPALIDAD PROVINCIAL DE CHANCHAMAYO | X240: 301046 | Y240: MUNICIPALIDAD PROVINCIAL DE CHANCHAMAYO | Z240: 12 | AA240: JUNIN | AB240: 3 | AC240: CHANCHAMAYO | AD240: 1 | AE240: CHANCHAMAYO
A241: 2018 | B241: MUN | C241: MP | D241: 43395 | E241: 2019-2022 | F241: NO | G241: FORMULADO | H241: EMITIDO | P241: 43395 | Q241: 079-2018-CEPLAN/DNCP-PEI | T241: 0 | U241: FICTICIO | V241: 300748 | W241: MUNICIPALIDAD PROVINCIAL DE LA CONVENCION - SANTA ANA | X241: 300748 | Y241: MUNICIPALIDAD PROVINCIAL DE LA CONVENCION - SANTA ANA | Z241: 8 | AA241: CUSCO | AB241: 9 | AC241: LA CONVENCION | AD241: 1 | AE241: SANTA ANA
A242: 2018 | B242: MUN | C242: MP | D242: 43398 | E242: 2019-2022 | F242: NO | G242: FORMULADO | H242: EMITIDO | P242: 43398 | Q242: 081-2018-CEPLAN/DNCP-PEI | T242: 0 | U242: FICTICIO | V242: 300464 | W242: MUNICIPALIDAD PROVINCIAL DE HUANTA | X242: 300464 | Y242: MUNICIPALIDAD PROVINCIAL DE HUANTA | Z242: 5 | AA242: AYACUCHO | AB242: 4 | AC242: HUANTA | AD242: 1 | AE242: HUANTA
A243: 2018 | B243: MUN | C243: MP | D243: 43432 | E243: 2019-2022 | F243: NO | G243: FORMULADO | H243: EMITIDO | P243: 43432 | Q243: 090-2018-CEPLAN/DNCP-PEI | T243: 0 | U243: FICTICIO | V243: 300471 | W243: MUNICIPALIDAD PROVINCIAL DE LA MAR - SAN MIGUEL | X243: 300471 | Y243: MUNICIPALIDAD PROVINCIAL DE LA MAR - SAN MIGUEL | Z243: 5 | AA243: AYACUCHO | AB243: 5 | AC243: LA MAR | AD243: 1 | AE243: SAN MIGUEL
A244: 2018 | B244: MUN | C244: MP | D244: 43243 | E244: 2018-2021 | F244: NO | G244: FORMULADO | H244: EMITIDO | P244: 43243 | Q244: 029-2018-CEPLAN/DNCP-PEI | T244: 0 | U244: FICTICIO | V244: 301481 | W244: MUNICIPALIDAD PROVINCIAL DE MARISCAL NIETO - MOQUEGUA | X244: 301481 | Y244: MUNICIPALIDAD PROVINCIAL DE MARISCAL NIETO - MOQUEGUA | Z244: 18 | AA244: MOQUEGUA | AB244: 1 | AC244: MARISCAL NIETO | AD244: 1 | AE244: MOQUEGUA
A245: 2018 | B245: MUN | C245: MP | D245: 43441 | E245: 2019-2022 | F245: NO | G245: FORMULADO | H245: EMITIDO | P245: 43441 | Q245: 097-2018-CEPLAN/DNCP-PEI | T245: 0 | U245: FICTICIO | V245: 301663 | W245: MUNICIPALIDAD PROVINCIAL DE MELGAR - AYAVIRI | X245: 301663 | Y245: MUNICIPALIDAD PROVINCIAL DE MELGAR - AYAVIRI | Z245: 21 | AA245: PUNO | AB245: 8 | AC245: MELGAR | AD245: 1 | AE245: AYAVIRI
A246: 2018 | B246: MUN | C246: MP | D246: 43346 | E246: 2018-2021 | F246: NO | G246: FORMULADO | H246: EMITIDO | P246: 43346 | Q246: 063-2018-CEPLAN/DNCP-PEI | T246: 0 | U246: FICTICIO | V246: 301522 | W246: MUNICIPALIDAD PROVINCIAL DE OXAPAMPA | X246: 301522 | Y246: MUNICIPALIDAD PROVINCIAL DE OXAPAMPA | Z246: 19 | AA246: PASCO | AB246: 3 | AC246: OXAPAMPA | AD246: 1 | AE246: OXAPAMPA
A247: 2018 | B247: MUN | C247: MP | D247: 43451 | E247: 2019-2022 | F247: NO | G247: FORMULADO | H247: EMITIDO | P247: 43451 | Q247: 110-2018-CEPLAN/DNCP-PEI | T247: 0 | U247: FICTICIO | V247: 301826 | W247: MUNICIPALIDAD PROVINCIAL DE PADRE ABAD - AGUAITIA | X247: 301826 | Y247: MUNICIPALIDAD PROVINCIAL DE PADRE ABAD - AGUAITIA | Z247: 25 | AA247: UCAYALI | AB247: 3 | AC247: PADRE ABAD | AD247: 1 | AE247: PADRE ABAD
... A275: 2018 | B275: GN | C275: OCA | D275: 43319 | E275: 2018-2020 | F275: NO | G275: FORMULADO | H275: EMITIDO | P275: 43319 | Q275: 060-2018-CEPLAN/DNCP-PEI | T275: 33 | U275: REGISTRO NACIONAL DE IDENTIFICACION Y ESTADO CIVIL | V275: 33 | W275: REGISTRO NACIONAL DE IDENTIFICACION Y ESTADO CIVIL | X275: 480 | Y275: REGISTRO NACIONAL DE IDENTIFICACION Y ESTADO CIVIL | Z275: 15 | AA275: LIMA | AB275: 1 | AC275: LIMA | AD275: 1 | AE275: LIMA
A276: 2018 | B276: ETE | C276: ETE | D276: 43418 | E276: 2018-2022 | F276: NO | G276: FORMULADO | H276: EMITIDO | L276: I.T emitido | P276: 43418 | Q276: 087-2018-CEPLAN/DNCP-PEI | T276: 0 | U276: FICTICIO | V276: 500134 | W276: ENTIDAD PRESTADORA DE SERVICIOS DE SANEAMIENTO SEDAM HUANCAYO S.A. | X276: 500134 | Y276: ENTIDAD PRESTADORA DE SERVICIOS DE SANEAMIENTO SEDAM HUANCAYO S.A. | Z276: 12 | AA276: JUNIN | AB276: 1 | AC276: HUANCAYO | AD276: 1 | AE276: HUANCAYO
A277: 2018 | B277: GN | C277: GN | D277: 43364 | E277: 2018-2020 | F277: NO | G277: FORMULADO | H277: EMITIDO | P277: 43364 | Q277: 068-2018-CEPLAN/DNCP-PEI | T277: 5 | U277: AMBIENTAL | V277: 52 | W277: SERVICIO NACIONAL DE CERTIFICACION AMBIENTAL PARA LAS INVERSIONES SOSTENIBLES -SENACE | X277: 1534 | Y277: ADMINISTRACION - SENACE | Z277: 15 | AA277: LIMA | AB277: 1 | AC277: LIMA | AD277: 30 | AE277: SAN BORJA
A278: 2018 | B278: GN | C278: GN | D278: 43462 | E278: 2019-2022 | F278: NO | G278: FORMULADO | H278: EMITIDO | P278: 43462 | Q278: 136-2018-CEPLAN/DNCP-PEI | T278: 13 | U278: AGRICULTURA | V278: 165 | W278: SERVICIO NACIONAL FORESTAL Y DE FAUNA SILVESTRE - SERFOR | X278: 1503 | Y278: SERVICIO NAC. FORESTAL Y DE FAUNA SILVESTRE-SERFOR - SEDE CENTRAL | Z278: 15 | AA278: LIMA | AB278: 1 | AC278: LIMA | AD278: 31 | AE278: SAN ISIDRO
A279: 2018 | B279: GN | C279: GN | D279: 43185 | E279: 2018-2020 | F279: NO | G279: FORMULADO | H279: EMITIDO | P279: 43185 | Q279: 017-2018-CEPLANIDNCP-PEI | T279: 37 | U279: VIVIENDA CONSTRUCCION Y SANEAMIENTO | V279: 56 | W279: SUPERINTENDENCIA NACIONAL DE BIENES ESTATALES | X279: 204 | Y279: SUPERINTENDENCIA NACIONAL DE BIENES ESTATALES | Z279: 15 | AA279: LIMA | AB279: 1 | AC279: LIMA | AD279: 14 | AE279: LA MOLINA
A280: 2018 | B280: GN | C280: GN | D280: 43311 | E280: 2019-2021 | F280: NO | G280: FORMULADO | H280: EMITIDO | P280: 43311 | Q280: 055-2018-CEPLAN/DNCP-PEI | T280: 7 | U280: INTERIOR | V280: 72 | W280: SUPERINTENDENCIA NACIONAL DE CONTROL DE SERVICIOS DE SEGURIDAD, ARMAS, MUNICIONES Y EXPLOSIVOS DE USO CIVIL | X280: 1519 | Y280: SUPERINTENDENCIA NACIONAL DE CONTROL DE SERVICIOS DE SEGURIDAD, ARMAS, MUNICIONES Y EXPLOSIVOS DE USO CIVIL- SUCAMEC | Z280: 15 | AA280: LIMA | AB280: 1 | AC280: LIMA | AD280: 20 | AE280: MAGDALENA DEL MAR
A281: 2018 | B281: GN | C281: GN | D281: 43185 | E281: 2018-2020 | F281: NO | G281: FORMULADO | H281: EMITIDO | P281: 43185 | Q281: 019-2018-CEPLAN/DNCP-PEI | T281: 12 | U281: TRABAJO Y PROMOCION DEL EMPLEO | V281: 121 | W281: SUPERINTENDENCIA NACIONAL DE FISCALIZACION LABORAL | X281: 1510 | Y281: SUPERINTENDENCIA NACIONAL DE FISCALIZACION LABORAL - SUNAFIL | Z281: 15 | AA281: LIMA | AB281: 1 | AC281: LIMA | AD281: 13 | AE281: JESUS MARIA
A282: 2018 | B282: GN | C282: GN | D282: 43465 | E282: 2019-2022 | F282: NO | G282: FORMULADO | H282: EMITIDO | P282: 43465 | Q282: 140-2018-CEPLAN/DNCP-PEI | T282: 6 | U282: JUSTICIA | V282: 67 | W282: SUPERINTENDENCIA NACIONAL DE LOS REGISTROS PUBLICOS | X282: 24 | Y282: SUNARP - SEDE CENTRAL | Z282: 15 | AA282: LIMA | AB282: 1 | AC282: LIMA | AD282: 40 | AE282: SANTIAGO DE SURCO
A283: 2018 | B283: GN | C283: GN | D283: 43445 | E283: 2019-2021 | F283: NO | G283: FORMULADO | H283: EMITIDO | P283: 43445 | Q283: 103-2018-CEPLAN/DNCP-PEI | T283: 11 | U283: SALUD | V283: 134 | W283: SUPERINTENDENCIA NACIONAL DE SALUD | X283: 515 | Y283: SUPERINTENDENCIA NACIONAL DE SALUD | Z283: 15 | AA283: LIMA | AB283: 1 | AC283: LIMA | AD283: 40 | AE283: SANTIAGO DE SURCO
A284: 2018 | B284: GN | C284: OCA | D284: 43300 | E284: 2019-2021 | F284: NO | G284: FORMULADO | H284: EMITIDO | P284: 43300 | Q284: 047-2018-CEPLAN/DNCP-PEI | T284: 24 | U284: TRIBUNAL CONSTITUCIONAL | V284: 24 | W284: TRIBUNAL CONSTITUCIONAL | X284: 201 | Y284: TRIBUNAL CONSTITUCIONAL | Z284: 15 | AA284: LIMA | AB284: 1 | AC284: LIMA | AD284: 1 | AE284: LIMA
A285: 2018 | B285: GN | C285: UN | D285: 43311 | E285: 2019-2021 | F285: NO | G285: FORMULADO | H285: EMITIDO | P285: 43311 | Q285: 052-2018-CEPLAN/DNCP-PEI | T285: 10 | U285: EDUCACION | V285: 526 | W285: U.N. AGRARIA DE LA SELVA | X285: 104 | Y285: UNIVERSIDAD NACIONAL AGRARIA DE LA SELVA | Z285: 10 | AA285: HUANUCO | AB285: 6 | AC285: LEONCIO PRADO | AD285: 1 | AE285: RUPA-RUPA
A286: 2018 | B286: GN | C286: UN | D286: 43301 | E286: 2019-2021 | F286: NO | G286: FORMULADO | H286: EMITIDO | P286: 43301 | Q286: 050-2018-CEPLAN/DNCP-PEI | T286: 10 | U286: EDUCACION | V286: 557 | W286: U.N. AUTÓNOMA DE ALTO AMAZONAS | X286: 1591 | Y286: UNIV. NACIONAL AUTONOMA DE ALTO AMAZONAS | Z286: 16 | AA286: LORETO | AB286: 2 | AC286: ALTO AMAZONAS | AD286: 1 | AE286: YURIMAGUAS
A287: 2018 | B287: GN | C287: UN | D287: 43223 | E287: 2019-2021 | F287: NO | G287: FORMULADO | H287: EMITIDO | P287: 43223 | Q287: 024-2018-CEPLAN/DNCP-PEI | T287: 10 | U287: EDUCACION | V287: 527 | W287: U.N. DANIEL ALCIDES CARRION | X287: 105 | Y287: UNIVERSIDAD NACIONAL DANIEL ALCIDES CARRION | Z287: 19 | AA287: PASCO | AB287: 1 | AC287: PASCO | AD287: 13 | AE287: YANACANCHA
A288: 2018 | B288: GN | C288: UN | D288: 43161 | E288: 2018-2020 | F288: NO | G288: FORMULADO | H288: EMITIDO | P288: 43161 | Q288: 012-2018-CEPLAN/DNCP-PEI | T288: 10 | U288: EDUCACION | V288: 547 | W288: U.N. DE CAÑETE | X288: 1372 | Y288: UNIVERSIDAD NACIONAL DE CAÑETE | Z288: 15 | AA288: LIMA | AB288: 5 | AC288: CANETE | AD288: 1 | AE288: SAN VICENTE DE CANETE
... A297: 2018 | B297: GN | C297: UN | D297: 43465 | E297: 2019-2022 | F297: NO | G297: FORMULADO | H297: EMITIDO | P297: 43465 | Q297: 142-2018-CEPLAN/DNCP-PEI | T297: 10 | U297: EDUCACION | V297: 516 | W297: U.N. SAN CRISTOBAL DE HUAMANGA | X297: 94 | Y297: UNIVERSIDAD NACIONAL SAN CRISTOBAL DE HUAMANGA | Z297: 5 | AA297: AYACUCHO | AB297: 1 | AC297: HUAMANGA | AD297: 1 | AE297: AYACUCHO
A298: 2019 | B298: MUN | C298: MD | D298: 43563 | E298: 2017-2021 | F298: NO | G298: AMPLIADO | H298: EMITIDO | O298: 2019-0000551 | P298: 43563 | Q298: 000079-2019-DNCPPEI | T298: 0 | U298: FICTICIO | V298: 301289 | W298: MUNICIPALIDAD DISTRITAL DE SANTIAGO DE SURCO | X298: 301289 | Y298: MUNICIPALIDAD DISTRITAL DE SANTIAGO DE SURCO | Z298: 15 | AA298: LIMA | AB298: 1 | AC298: LIMA | AD298: 40 | AE298: SANTIAGO DE SURCO
A299: 2019 | B299: GN | C299: GN | D299: 43657 | E299: 2019-2022 | F299: NO | G299: FORMULADO | H299: EMITIDO | O299: 2019-0001291 | P299: 43657 | Q299: 000185-2019-DNCPPEI | T299: 11 | U299: SALUD | V299: 131 | W299: INSTITUTO NACIONAL DE SALUD | X299: 151 | Y299: INSTITUTO NACIONAL DE SALUD | Z299: 15 | AA299: LIMA | AB299: 1 | AC299: LIMA | AD299: 8 | AE299: CHORRILLOS
A300: 2019 | B300: MUN | C300: MD | D300: 43550 | E300: 2019-2022 | F300: NO | G300: FORMULADO | H300: EMITIDO | O300: 2019-0000615 | P300: 43550 | Q300: 000072-2019-DNCPPEI | T300: 0 | U300: FICTICIO | V300: 301260 | W300: MUNICIPALIDAD DISTRITAL DE EL AGUSTINO | X300: 301260 | Y300: MUNICIPALIDAD DISTRITAL DE EL AGUSTINO | Z300: 15 | AA300: LIMA | AB300: 1 | AC300: LIMA | AD300: 11 | AE300: EL AGUSTINO
A301: 2019 | B301: MUN | C301: MP | D301: 43552 | E301: 2019-2022 | F301: NO | G301: FORMULADO | H301: EMITIDO | O301: 2019-0000630 | P301: 43552 | Q301: 000074-2019-DNCPPEI | T301: 0 | U301: FICTICIO | V301: 301003 | W301: MUNICIPALIDAD PROVINCIAL DE HUANCAYO | X301: 301003 | Y301: MUNICIPALIDAD PROVINCIAL DE HUANCAYO | Z301: 12 | AA301: JUNIN | AB301: 1 | AC301: HUANCAYO | AD301: 1 | AE301: HUANCAYO
A302: 2019 | B302: GN | C302: UN | D302: 43642 | E302: 2020-2022 | F302: NO | G302: FORMULADO | H302: EMITIDO | O302: 2019-0001257 | P302: 43642 | Q302: 000183-2019-DNCPPEI | T302: 10 | U302: EDUCACION | V302: 512 | W302: U.N. DE TRUJILLO | X302: 90 | Y302: UNIVERSIDAD NACIONAL DE TRUJILLO | Z302: 13 | AA302: LA LIBERTAD | AB302: 1 | AC302: TRUJILLO | AD302: 1 | AE302: TRUJILLO
A303: 2019 | B303: MUN | C303: MP | D303: 43594 | E303: 2019-2022 | F303: NO | G303: FORMULADO | H303: EMITIDO | O303: 2019-0000745 | P303: 43594 | Q303: 000154-2019-DNCPPEI | T303: 0 | U303: FICTICIO | V303: 300692 | W303: MUNICIPALIDAD PROVINCIAL DE ACOMAYO | X303: 300692 | Y303: MUNICIPALIDAD PROVINCIAL DE ACOMAYO | Z303: 8 | AA303: CUSCO | AB303: 2 | AC303: ACOMAYO | AD303: 1 | AE303: ACOMAYO
A304: 2019 | B304: GN | C304: UN | D304: 43643 | E304: 2019-2022 | F304: NO | G304: FORMULADO | H304: EMITIDO | O304: 2019-0001236 | P304: 43643 | Q304: 000184-2019-DNCPPEI | T304: 10 | U304: EDUCACION | V304: 553 | W304: U.N. AUTÓNOMA ALTOANDINA DE TARMA | X304: 1529 | Y304: U. N. AUTÓNOMA ALTOANADINA DE TARMA - UNAAT | Z304: 12 | AA304: JUNIN | AB304: 7 | AC304: TARMA | AD304: 1 | AE304: TARMA
A305: 2019 | B305: GN | C305: GN | D305: 43825 | E305: 2020-2023 | F305: NO | G305: FORMULADO | H305: EMITIDO | O305: 2019-0002466 | P305: 43825 | Q305: 000239-2019-DNCPPEI | T305: 5 | U305: AMBIENTAL | V305: 331 | W305: SERVICIO NACIONAL DE METEOROLOGIA E HIDROLOGIA | X305: 474 | Y305: SERVICIO NACIONAL DE METEOROLOGIA E HIDROLOGIA-SENAMHI | Z305: 15 | AA305: LIMA | AB305: 1 | AC305: LIMA | AD305: 13 | AE305: JESUS MARIA
A306: 2019 | B306: MUN | C306: MD | D306: 43546 | E306: 2018-2022 | F306: NO | G306: AMPLIADO | H306: EMITIDO | O306: 2019-0000002 | P306: 43546 | Q306: 000054-2019-DNCPPEI | T306: 0 | U306: FICTICIO | V306: 301280 | W306: MUNICIPALIDAD DISTRITAL DE SAN ISIDRO | X306: 301280 | Y306: MUNICIPALIDAD DISTRITAL DE SAN ISIDRO | Z306: 15 | AA306: LIMA | AB306: 1 | AC306: LIMA | AD306: 31 | AE306: SAN ISIDRO
A307: 2019 | B307: GR | C307: GR | D307: 43550 | E307: 2018-2022 | F307: NO | G307: AMPLIADO | H307: EMITIDO | O307: 2019-0000520 | P307: 43550 | Q307: 000070-2019-DNCPPEI | T307: 99 | U307: GOBIERNOS REGIONALES | V307: 442 | W307: GOBIERNO REGIONAL DEL DEPARTAMENTO DE APURIMAC | X307: 747 | Y307: REGION APURIMAC-SEDE CENTRAL | Z307: 3 | AA307: APURIMAC | AB307: 1 | AC307: ABANCAY | AD307: 1 | AE307: ABANCAY
A308: 2019 | B308: MUN | C308: MP | D308: 43543 | E308: 2019-2023 | F308: NO | G308: AMPLIADO | H308: EMITIDO | O308: 2019-0000529 | P308: 43543 | Q308: 000035-2019-DNCPPEI | T308: 0 | U308: FICTICIO | V308: 300001 | W308: MUNICIPALIDAD PROVINCIAL DE CHACHAPOYAS | X308: 300001 | Y308: MUNICIPALIDAD PROVINCIAL DE CHACHAPOYAS | Z308: 1 | AA308: AMAZONAS | AB308: 1 | AC308: CHACHAPOYAS | AD308: 1 | AE308: CHACHAPOYAS
A309: 2019 | B309: GN | C309: GN | D309: 43549 | E309: 2017-2022 | F309: NO | G309: AMPLIADO | H309: EMITIDO | O309: 2019-0000553 | P309: 43549 | Q309: 000055-2019-DNCPPEI | T309: 7 | U309: INTERIOR | V309: 7 | W309: M. DEL INTERIOR | X309: 25 | Y309: MINISTERIO DEL INTERIOR-OFICINA GENERAL DE ADMINISTRACION | Z309: 15 | AA309: LIMA | AB309: 1 | AC309: LIMA | AD309: 31 | AE309: SAN ISIDRO
... A538: 2019 | B538: MUN | C538: MD | D538: 43809 | E538: 2020-2023 | F538: NO | G538: FORMULADO | H538: EMITIDO | O538: 2019-0002195 | P538: 43809 | Q538: 000226-2019-DNCPPEI | T538: 0 | U538: FICTICIO | V538: 301292 | W538: MUNICIPALIDAD DISTRITAL DE VILLA MARIA DEL TRIUNFO | X538: 301292 | Y538: MUNICIPALIDAD DISTRITAL DE VILLA MARIA DEL TRIUNFO | Z538: 15 | AA538: LIMA | AB538: 1 | AC538: LIMA | AD538: 43 | AE538: VILLA MARIA DEL TRIUNFO
A539: 2020 | B539: GN | C539: GN | D539: 43964 | E539: 2021-2024 | F539: NO | G539: AMPLIADO | H539: EMITIDO | I539: SILVA PIÑA SANDY KATHERYN | O539: 2020-0000625 | P539: 43964 | Q539: 000066-2020-DNCPPEI | T539: 13 | U539: AGRICULTURA | V539: 160 | W539: SERVICIO NACIONAL DE SANIDAD AGRARIA - SENASA | X539: 157 | Y539: SERVICIO NACIONAL DE SANIDAD AGRARIA-SENASA | Z539: 15 | AA539: LIMA | AB539: 1 | AC539: LIMA | AD539: 13 | AE539: JESUS MARIA
A540: 2020 | B540: GN | C540: GN | D540: 44155 | E540: 2017-2023 | F540: NO | G540: AMPLIADO | H540: EMITIDO | I540: SILVA PIÑA SANDY KATHERYN | O540: 2020-0001501 | P540: 44155 | Q540: 000237-2020-DNCPPEI | T540: 1 | U540: PRESIDENCIA CONSEJO MINISTROS | V540: 12 | W540: COMISION NACIONAL PARA EL DESARROLLO Y VIDA SIN DROGAS - DEVIDA | X540: 1064 | Y540: COMISION NAC. PARA EL DESARROLLO Y VIDA SIN DROGAS - DEVIDA | Z540: 15 | AA540: LIMA | AB540: 1 | AC540: LIMA | AD540: 1 | AE540: LIMA
A541: 2020 | B541: MUN | C541: MD | D541: 44009 | E541: 2017-2023 | F541: NO | G541: AMPLIADO | H541: EMITIDO | I541: SILVA PIÑA SANDY KATHERYN | O541: 2020-0000746 | P541: 44009 | Q541: 000123-2020-DNCPPEI | T541: 0 | U541: FICTICIO | V541: 301255 | W541: MUNICIPALIDAD DISTRITAL DE CARABAYLLO | X541: 301255 | Y541: MUNICIPALIDAD DISTRITAL DE CARABAYLLO | Z541: 15 | AA541: LIMA | AB541: 1 | AC541: LIMA | AD541: 6 | AE541: CARABAYLLO
A542: 2020 | B542: GN | C542: GN | D542: 44001 | E542: 2017-2023 | F542: NO | G542: AMPLIADO | H542: EMITIDO | I542: SILVA PIÑA SANDY KATHERYN | O542: 2020-0000763 | P542: 44001 | Q542: 000102-2020-DNCPPEI | T542: 9 | U542: ECONOMIA Y FINANZAS | V542: 58 | W542: SUPERINTENDENCIA DEL MERCADO DE VALORES | X542: 1274 | Y542: SUPERINTENDECIA DEL MERCADO DE VALORES - SMV | Z542: 15 | AA542: LIMA | AB542: 1 | AC542: LIMA | AD542: 22 | AE542: MIRAFLORES
A543: 2020 | B543: GN | C543: GN | D543: 44011 | E543: 2017-2023 | F543: NO | G543: AMPLIADO | H543: EMITIDO | I543: SILVA PIÑA SANDY KATHERYN | O543: 2020-0000809 | P543: 44011 | Q543: 000150-2020-DNCPPEI | T543: 1 | U543: PRESIDENCIA CONSEJO MINISTROS | V543: 114 | W543: CONSEJO NACIONAL DE CIENCIA, TECNOLOGIA E INNOVACION TECNOLOGICA | X543: 86 | Y543: CONSEJO NACIONAL DE CIENCIA, TECNOLOGIA E INNOVACION TECNOLOGICA - CONCYTEC | Z543: 15 | AA543: LIMA | AB543: 1 | AC543: LIMA | AD543: 30 | AE543: SAN BORJA
A544: 2020 | B544: GN | C544: GN | D544: 44006 | E544: 2017-2023 | F544: NO | G544: AMPLIADO | H544: EMITIDO | I544: SILVA PIÑA SANDY KATHERYN | O544: 2020-0000792 | P544: 44006 | Q544: 000113-2020-DNCPPEI | T544: 1 | U544: PRESIDENCIA CONSEJO MINISTROS | V544: 2 | W544: INSTITUTO NACIONAL DE ESTADISTICA E INFORMATICA | X544: 5 | Y544: INSTITUTO NACIONAL DE ESTADISTICA E INFORMATICA- INEI | Z544: 15 | AA544: LIMA | AB544: 1 | AC544: LIMA | AD544: 13 | AE544: JESUS MARIA
A545: 2020 | B545: GN | C545: GN | D545: 43993 | E545: 2017-2023 | F545: NO | G545: AMPLIADO | H545: EMITIDO | I545: SILVA PIÑA SANDY KATHERYN | O545: 2020-0000700 | P545: 43993 | Q545: 000086-2020-DNCPPEI | T545: 3 | U545: CULTURA | V545: 116 | W545: INSTITUTO NACIONAL DE RADIO Y TELEVISION DEL PERU - IRTP | X545: 513 | Y545: INSTITUTO NACIONAL DE RADIO Y TELEVISION DEL PERU - IRTP | Z545: 15 | AA545: LIMA | AB545: 1 | AC545: LIMA | AD545: 15 | AE545: LA VICTORIA
A546: 2020 | B546: GN | C546: GN | D546: 43899 | E546: 2017-2023 | F546: NO | G546: AMPLIADO | H546: EMITIDO | I546: SILVA PIÑA SANDY KATHERYN | O546: 2020-0000495 | P546: 43899 | Q546: 000035-2020-DNCPPEI | T546: 9 | U546: ECONOMIA Y FINANZAS | V546: 9 | W546: M. DE ECONOMIA Y FINANZAS | X546: 46 | Y546: MEF-ADMINISTRACION GENERAL | Z546: 15 | AA546: LIMA | AB546: 1 | AC546: LIMA | AD546: 1 | AE546: LIMA
A547: 2020 | B547: GN | C547: GN | D547: 44008 | E547: 2017-2023 | F547: NO | G547: AMPLIADO | H547: EMITIDO | I547: SILVA PIÑA SANDY KATHERYN | O547: 2020-0000805 | P547: 44008 | Q547: 000121-2020-DNCPPEI | T547: 12 | U547: TRABAJO Y PROMOCION DEL EMPLEO | V547: 12 | W547: M. DE TRABAJO Y PROMOCION DEL EMPLEO | X547: 154 | Y547: MINISTERIO DE TRABAJO-OFICINA GENERAL DE ADMINISTRACION | Z547: 15 | AA547: LIMA | AB547: 1 | AC547: LIMA | AD547: 13 | AE547: JESUS MARIA
A548: 2020 | B548: MUN | C548: MD | D548: 44010 | E548: 2017-2023 | F548: NO | G548: AMPLIADO | H548: EMITIDO | I548: SILVA PIÑA SANDY KATHERYN | O548: 2020-0000748 | P548: 44010 | Q548: 000135-2020-DNCPPEI | T548: 0 | U548: FICTICIO | V548: 301259 | W548: MUNICIPALIDAD DISTRITAL DE COMAS | X548: 301259 | Y548: MUNICIPALIDAD DISTRITAL DE COMAS | Z548: 15 | AA548: LIMA | AB548: 1 | AC548: LIMA | AD548: 10 | AE548: COMAS
A549: 2020 | B549: GN | C549: GN | D549: 44168 | E549: 2017-2024 | F549: NO | G549: AMPLIADO | H549: EMITIDO | I549: SILVA PIÑA SANDY KATHERYN | O549: 2020-0001542 | P549: 44168 | Q549: 000239-2020-DNCPPEI | T549: 9 | U549: ECONOMIA Y FINANZAS | V549: 9 | W549: M. DE ECONOMIA Y FINANZAS | X549: 46 | Y549: MEF-ADMINISTRACION GENERAL | Z549: 15 | AA549: LIMA | AB549: 1 | AC549: LIMA | AD549: 1 | AE549: LIMA
A550: 2020 | B550: GN | C550: UN | D550: 44000 | E550: 2017-2023 | F550: NO | G550: AMPLIADO | H550: EMITIDO | I550: SILVA PIÑA SANDY KATHERYN | O550: 2020-0000757 | P550: 44000 | Q550: 000100-2020-DNCPPEI | T550: 10 | U550: EDUCACION | V550: 530 | W550: U.N. JOSE FAUSTINO SANCHEZ CARRION | X550: 108 | Y550: UNIVERSIDAD NACIONAL FAUSTINO SANCHEZ CARRION | Z550: 15 | AA550: LIMA | AB550: 8 | AC550: HUAURA | AD550: 1 | AE550: HUACHO
... A680: 2020 | B680: MUN | C680: MD | D680: 44069 | E680: 2021-2024 | F680: NO | G680: FORMULADO | H680: EMITIDO | I680: SILVA PIÑA SANDY KATHERYN | O680: 2020-0001048 | P680: 44069 | Q680: 000192-2020-DNCPPEI | T680: 0 | U680: FICTICIO | V680: 300207 | W680: MUNICIPALIDAD DISTRITAL DE PAMPAS | X680: 300207 | Y680: MUNICIPALIDAD DISTRITAL DE PAMPAS | Z680: 2 | AA680: ANCASH | AB680: 15 | AC680: PALLASCA | AD680: 9 | AE680: PAMPAS
A681: 2020 | B681: MUN | C681: MP | D681: 44175 | E681: 2021-2024 | F681: NO | G681: FORMULADO | H681: EMITIDO | I681: Vilma Celestino | O681: 2020-0001563 | P681: 44175 | Q681: 000245-2020-DNCPPEI | T681: 0 | U681: FICTICIO | V681: 300102 | W681: MUNICIPALIDAD PROVINCIAL DE ANTONIO RAYMONDI - LLAMELLIN | X681: 300102 | Y681: MUNICIPALIDAD PROVINCIAL DE ANTONIO RAIMONDI - LLAMELLIN | Z681: 2 | AA681: ANCASH | AB681: 3 | AC681: ANTONIO RAIMONDI | AD681: 1 | AE681: LLAMELLIN
A682: 2020 | B682: MUN | C682: MP | D682: 44009 | E682: 2021-2024 | F682: NO | G682: FORMULADO | H682: EMITIDO | I682: SILVA PIÑA SANDY KATHERYN | O682: 2020-0000819 | P682: 44009 | Q682: 000131-2020-DNCPPEI | T682: 0 | U682: FICTICIO | V682: 300464 | W682: MUNICIPALIDAD PROVINCIAL DE HUANTA | X682: 300464 | Y682: MUNICIPALIDAD PROVINCIAL DE HUANTA | Z682: 5 | AA682: AYACUCHO | AB682: 4 | AC682: HUANTA | AD682: 1 | AE682: HUANTA
A683: 2020 | B683: MUN | C683: MP | D683: 44095 | E683: 2021-2024 | F683: NO | G683: FORMULADO | H683: EMITIDO | I683: SILVA PIÑA SANDY KATHERYN | O683: 2020-0001199 | P683: 44095 | Q683: 000204-2020-DNCPPEI | T683: 0 | U683: FICTICIO | V683: 301501 | W683: MUNICIPALIDAD PROVINCIAL DE PASCO - CHAUPIMARCA | X683: 301501 | Y683: MUNICIPALIDAD PROVINCIAL DE PASCO - CHAUPIMARCA | Z683: 19 | AA683: PASCO | AB683: 1 | AC683: PASCO | AD683: 1 | AE683: CHAUPIMARCA
...

Sheet Data_UEs
A1: NG | B1: NG1 | C1: NivelGobierno | D1: Id_Sector | E1: nombre_sector | F1: Id_Pliego | G1: nombre_pliego | H1: Id_UE | I1: Nombre_unidad_ejecutora | J1: Id_Departamento | K1: nombre_departamento | L1: Id_Provincia | M1: nombre_provincia | N1: Id_4Distrito | O1: nombre_distrito | P1: TipoDistrito | Q1: PEI | R1: POI | S1: PESEM | T1: PDC | U1: Universidad? | V1: OtroTipoEntidad | W1: c/ PEI | X1: Ult.PEI | Y1: Tipo PEI | Z1: PEI_vigente? | AA1: Estado_PEI | AB1: Expediente | AC1: Fecha de Informe Técnico | AD1: Nro de Informe Técnico | AE1: PEI al 2030? | AF1: Vigente 2030 | AG1: No vigente al 2030 | AH1: EnProceso-Vigente 2030 | AI1: ¿ACTIVO? | AJ1: Responsable Institucional | AK1: Correo electrónico | AL1: Operador planeamiento_UE | AM1: Cargo (Según ROF) | AN1: Número de contacto | AO1: Correo electrónico | AP1: POI 2022 (Seguimiento) | AQ1: POI 2023-2025 (Aprobado) | AR1: POI 2024-2026 (Elaborado) | AS1: POI 2024-2026 (Aprobado) | AT1: POI 2024-2026 (Ajustado) | AU1: POI 2024-2026 (Consistenciado) | AV1: POI 2024-2026 (Estado Cons) | AW1: POI 2024 (Seguimiento ) | AX1: POI 2025-2027 (Elaborado) | AY1: POI 2025-2027 (Aprobado) | AZ1: POI 2025-2027 (Ajustado) | BA1: POI 2025-2027 (Consistenciado) | BB1: POI 2025-2027 (Estado Consistenciado) | BC1: POI 2025-2027 (Estado Seguimiento) | BD1: POI 2026-2028 (Elab) | BE1: POI 2026-2028 (Aprob) | BF1: POI 2026-2028 (Ajustado) | BG1: POI 2026-2028 (Consistenciado) | BH1: POI 2026-2028 (Estado Consistenciado) | BI1: POI 2026 (Seguimiento) | BJ1: POI 2027-2029 (Elab) | BK1: POI 2027-2029 (Aprob) | BL1: SUMA_APROBADO_2026 | BM1: SUMA_ELABORACION_2027 | BN1: SUMA_APROBADO_2027 | BO1: SUMA_ELABORACION_2028 | BP1: SUMA_APROBADO_2028 | BQ1: Tiene_PDC? | BR1: Periodo PDC | BS1: PDC_Aprobado? | BT1: PDC_vigente?
A2: Gobierno nacional | B2: OCA | C2: E | D2: 4 | E2: PODER JUDICIAL | F2: 40 | G2: ACADEMIA DE LA MAGISTRATURA | H2: 14 | I2: ACADEMIA DE LA MAGISTRATURA | J2: 15 | K2: LIMA | L2: 1 | M2: LIMA | N2: 1 | O2: LIMA | Q2: S | R2: S | V2: OCA | W2: =IFERROR(VLOOKUP(H2,'IT PEI'!$X$2:$X$5647,1,0),"...") -> 14 | X2: =_xlfn.XLOOKUP(H2,'IT PEI'!X$2:X$5647,'IT PEI'!E$2:E$5647,"...",2,-1) -> 2024-2030 | Y2: =_xlfn.XLOOKUP(H2,'IT PEI'!X$2:X$5647,'IT PEI'!G$2:G$5647,"...",2,-1) -> FORMULADO | Z2: =_xlfn.XLOOKUP(H2,'IT PEI'!X$2:X$5647,'IT PEI'!F$2:F$5647,"...",2,-1) -> SI | AA2: =_xlfn.XLOOKUP(H2,'IT PEI'!X$2:X$5647,'IT PEI'!H$2:H$5647,"...",2,-1) -> EMITIDO | AB2: =_xlfn.XLOOKUP(H2,'IT PEI'!X$2:X$5647,'IT PEI'!O$2:O$5647,"...",2,-1) -> 2024-0000196 | AC2: =_xlfn.XLOOKUP(H2,'IT PEI'!X$2:X$5647,'IT PEI'!P$2:P$5647,"...",2,-1) -> 45310 | AD2: =_xlfn.XLOOKUP(H2,'IT PEI'!X$2:X$5647,'IT PEI'!Q$2:Q$5647,"...",2,-1) -> 000009-2024-CEPLAN-DNCPPEI | AE2: =IF(COUNTIF(X2, "*" & "2030" & "*")>0, "SI", "No" ) -> SI | AF2: =IF(COUNTIF(X2, "*" & "2030" & "*")>0, 1, 0 ) -> 1 | AG2: =IF(COUNTIF(X2, "*" & "2030" & "*")>0, 0, 1 ) -> 0 | AH2: =IF(AND(AA2="En Proceso",AE2="Si"),1,0) -> 0 | AI2: ACTIVO | AJ2: Addy López Peña | AK2: alopez@ceplan.gob.pe | AL2: =IFERROR(VLOOKUP(tbl_ues[[#This Row],[Id_UE]],'[1]Directorio v.02'!$H$3:$U$3089,11,FALSE),"") -> Miguel Angel Dávila Servat | AM2: =IFERROR(VLOOKUP(tbl_ues[[#This Row],[Id_UE]],'[1]Directorio v.02'!$H$3:$U$3089,12,FALSE),"") -> Jefe de la Oficina de Planificación y Presupuesto | AN2: =IFERROR(VLOOKUP(tbl_ues[[#This Row],[Id_UE]],'[1]Directorio v.02'!$H$3:$U$3089,13,FALSE),"") -> 4280300 anx 524 | AO2: =IFERROR(VLOOKUP(tbl_ues[[#This Row],[Id_UE]],'[1]Directorio v.02'!$H$3:$U$3089,14,FALSE),"") -> mdavila@amag.edu.pe | AP2: =VLOOKUP(H2,#REF!,7,0) -> #REF! | AQ2: =VLOOKUP(H2,#REF!,9,0) -> #REF! | AR2: =VLOOKUP(H2,#REF!,15,0) -> #REF! | AS2: =VLOOKUP(H2,#REF!,16,0) -> #REF! | AT2: =VLOOKUP(H2,#REF!,17,0) -> #REF! | AU2: =VLOOKUP(H2,#REF!,18,0) -> #REF! | AV2: =VLOOKUP(H2,#REF!,19,0) -> #REF! | AW2: =VLOOKUP(H2,#REF!,20,0) -> #REF! | AX2: =VLOOKUP(H2,#REF!,22,0) -> #REF! | AY2: =VLOOKUP(H2,#REF!,23,0) -> #REF! | AZ2: =VLOOKUP(H2,#REF!,24,0) -> #REF! | BA2: =VLOOKUP(H2,#REF!,25,0) -> #REF! | BB2: =VLOOKUP(H2,#REF!,26,0) -> #REF! | BC2: =VLOOKUP(H2,#REF!,27,0) -> #REF! | BD2: =VLOOKUP(H2,#REF!,29,0) -> #REF! | BE2: =VLOOKUP(H2,#REF!,30,0) -> #REF! | BF2: =VLOOKUP(H2,#REF!,31,0) -> #REF! | BG2: =VLOOKUP(H2,#REF!,32,0) -> #REF! | BH2: =VLOOKUP(H2,#REF!,33,0) -> #REF! | BI2: =VLOOKUP(H2,#REF!,34,0) -> #REF! | BJ2: =VLOOKUP(H2,#REF!,36,0) -> #REF! | BK2: =VLOOKUP(H2,#REF!,37,0) -> #REF! | BL2: =VLOOKUP(H2,#REF!,44,0) -> #REF! | BM2: =VLOOKUP(H2,#REF!,45,0) -> #REF! | BN2: =VLOOKUP(H2,#REF!,46,0) -> #REF! | BO2: =VLOOKUP(H2,#REF!,47,0) -> #REF! | BP2: =VLOOKUP(H2,#REF!,48,0) -> #REF!
A3: Gobierno nacional | B3: Poder Ejecutivo | C3: E | D3: 26 | E3: DEFENSA | F3: 335 | G3: AGENCIA DE COMPRAS DE LAS FUERZAS ARMADAS | H3: 1545 | I3: AGENCIA DE COMPRAS DE LAS FUERZAS ARMADAS | J3: 15 | K3: LIMA | L3: 1 | M3: LIMA | N3: 1 | O3: LIMA | Q3: S | R3: S | W3: =IFERROR(VLOOKUP(H3,'IT PEI'!$X$2:$X$5647,1,0),"...") -> 1545 | X3: =_xlfn.XLOOKUP(H3,'IT PEI'!X$2:X$5647,'IT PEI'!E$2:E$5647,"...",2,-1) -> 2025-2030 | Y3: =_xlfn.XLOOKUP(H3,'IT PEI'!X$2:X$5647,'IT PEI'!G$2:G$5647,"...",2,-1) -> FORMULADO | Z3: =_xlfn.XLOOKUP(H3,'IT PEI'!X$2:X$5647,'IT PEI'!F$2:F$5647,"...",2,-1) -> SI | AA3: =_xlfn.XLOOKUP(H3,'IT PEI'!X$2:X$5647,'IT PEI'!H$2:H$5647,"...",2,-1) -> EMITIDO | AB3: =_xlfn.XLOOKUP(H3,'IT PEI'!X$2:X$5647,'IT PEI'!O$2:O$5647,"...",2,-1) -> 2025-000382 | AC3: =_xlfn.XLOOKUP(H3,'IT PEI'!X$2:X$5647,'IT PEI'!P$2:P$5647,"...",2,-1) -> 45688 | AD3: =_xlfn.XLOOKUP(H3,'IT PEI'!X$2:X$5647,'IT PEI'!Q$2:Q$5647,"...",2,-1) -> 000039-2025-CEPLAN-DNCPPEI | AE3: =IF(COUNTIF(X3, "*" & "2030" & "*")>0, "SI", "No" ) -> SI | AF3: =IF(COUNTIF(X3, "*" & "2030" & "*")>0, 1, 0 ) -> 1 | AG3: =IF(COUNTIF(X3, "*" & "2030" & "*")>0, 0, 1 ) -> 0 | AH3: =IF(AND(AA3="En Proceso",AE3="Si"),1,0) -> 0 | AI3: ACTIVO | AJ3: Leidy Cayotopa Mesones | AK3: leidy.cayotopa.ceplan@gmail.com | AL3: =IFERROR(VLOOKUP(tbl_ues[[#This Row],[Id_UE]],'[1]Directorio v.02'!$H$3:$U$3089,11,FALSE),"") -> Francisco José Ríos Lituma | AM3: =IFERROR(VLOOKUP(tbl_ues[[#This Row],[Id_UE]],'[1]Directorio v.02'!$H$3:$U$3089,12,FALSE),"") -> Jefe de la Oficina de Planeamiento y Presupuesto | AN3: =IFERROR(VLOOKUP(tbl_ues[[#This Row],[Id_UE]],'[1]Directorio v.02'!$H$3:$U$3089,13,FALSE),"") -> 206-0100 Anexo 2140 | AO3: =IFERROR(VLOOKUP(tbl_ues[[#This Row],[Id_UE]],'[1]Directorio v.02'!$H$3:$U$3089,14,FALSE),"") -> francisco.rios@acffaa.gob.pe | AP3: =VLOOKUP(H3,#REF!,7,0) -> #REF! | AQ3: =VLOOKUP(H3,#REF!,9,0) -> #REF! | AR3: =VLOOKUP(H3,#REF!,15,0) -> #REF! | AS3: =VLOOKUP(H3,#REF!,16,0) -> #REF! | AT3: =VLOOKUP(H3,#REF!,17,0) -> #REF! | AU3: =VLOOKUP(H3,#REF!,18,0) -> #REF! | AV3: =VLOOKUP(H3,#REF!,19,0) -> #REF! | AW3: =VLOOKUP(H3,#REF!,20,0) -> #REF! | AX3: =VLOOKUP(H3,#REF!,22,0) -> #REF! | AY3: =VLOOKUP(H3,#REF!,23,0) -> #REF! | AZ3: =VLOOKUP(H3,#REF!,24,0) -> #REF! | BA3: =VLOOKUP(H3,#REF!,25,0) -> #REF! | BB3: =VLOOKUP(H3,#REF!,26,0) -> #REF! | BC3: =VLOOKUP(H3,#REF!,27,0) -> #REF! | BD3: =VLOOKUP(H3,#REF!,29,0) -> #REF! | BE3: =VLOOKUP(H3,#REF!,30,0) -> #REF! | BF3: =VLOOKUP(H3,#REF!,31,0) -> #REF! | BG3: =VLOOKUP(H3,#REF!,32,0) -> #REF! | BH3: =VLOOKUP(H3,#REF!,33,0) -> #REF! | BI3: =VLOOKUP(H3,#REF!,34,0) -> #REF! | BJ3: =VLOOKUP(H3,#REF!,36,0) -> #REF! | BK3: =VLOOKUP(H3,#REF!,37,0) -> #REF! | BL3: =VLOOKUP(H3,#REF!,44,0) -> #REF! | BM3: =VLOOKUP(H3,#REF!,45,0) -> #REF! | BN3: =VLOOKUP(H3,#REF!,46,0) -> #REF! | BO3: =VLOOKUP(H3,#REF!,47,0) -> #REF! | BP3: =VLOOKUP(H3,#REF!,48,0) -> #REF!
A4: Gobierno nacional | B4: Poder Ejecutivo | C4: E | D4: 9 | E4: ECONOMIA Y FINANZAS | F4: 55 | G4: AGENCIA DE PROMOCION DE LA INVERSION PRIVADA | H4: 1231 | I4: AGENCIA DE PROMOCION DE LA INVERSION PRIVADA - PROINVERSION | J4: 15 | K4: LIMA | L4: 1 | M4: LIMA | N4: 31 | O4: SAN ISIDRO | Q4: S | R4: S | W4: =IFERROR(VLOOKUP(H4,'IT PEI'!$X$2:$X$5647,1,0),"...") -> 1231 | X4: =_xlfn.XLOOKUP(H4,'IT PEI'!X$2:X$5647,'IT PEI'!E$2:E$5647,"...",2,-1) -> 2024-2030 | Y4: =_xlfn.XLOOKUP(H4,'IT PEI'!X$2:X$5647,'IT PEI'!G$2:G$5647,"...",2,-1) -> FORMULADO | Z4: =_xlfn.XLOOKUP(H4,'IT PEI'!X$2:X$5647,'IT PEI'!F$2:F$5647,"...",2,-1) -> SI | AA4: =_xlfn.XLOOKUP(H4,'IT PEI'!X$2:X$5647,'IT PEI'!H$2:H$5647,"...",2,-1) -> EMITIDO | AB4: =_xlfn.XLOOKUP(H4,'IT PEI'!X$2:X$5647,'IT PEI'!O$2:O$5647,"...",2,-1) -> 2024-0001603 | AC4: =_xlfn.XLOOKUP(H4,'IT PEI'!X$2:X$5647,'IT PEI'!P$2:P$5647,"...",2,-1) -> 45433 | AD4: =_xlfn.XLOOKUP(H4,'IT PEI'!X$2:X$5647,'IT PEI'!Q$2:Q$5647,"...",2,-1) -> 000238-2024-CEPLAN-DNCPPEI | AE4: =IF(COUNTIF(X4, "*" & "2030" & "*")>0, "SI", "No" ) -> SI | AF4: =IF(COUNTIF(X4, "*" & "2030" & "*")>0, 1, 0 ) -> 1 | AG4: =IF(COUNTIF(X4, "*" & "2030" & "*")>0, 0, 1 ) -> 0 | AH4: =IF(AND(AA4="En Proceso",AE4="Si"),1,0) -> 0 | AI4: ACTIVO | AJ4: Fatima Amoretti Arteaga | AK4: fatima.amoretti.ceplan@gmail.com | AL4: =IFERROR(VLOOKUP(tbl_ues[[#This Row],[Id_UE]],'[1]Directorio v.02'!$H$3:$U$3089,11,FALSE),"") -> Apolinar Madrid Escobar | AM4: =IFERROR(VLOOKUP(tbl_ues[[#This Row],[Id_UE]],'[1]Directorio v.02'!$H$3:$U$3089,12,FALSE),"") -> Jefe de la Oficina de Planeamiento y Presupuesto € | AN4: =IFERROR(VLOOKUP(tbl_ues[[#This Row],[Id_UE]],'[1]Directorio v.02'!$H$3:$U$3089,13,FALSE),"") -> 2001200 A.1353 | AO4: =IFERROR(VLOOKUP(tbl_ues[[#This Row],[Id_UE]],'[1]Directorio v.02'!$H$3:$U$3089,14,FALSE),"") -> amadrid@proinversion.gob.pe | AP4: =VLOOKUP(H4,#REF!,7,0) -> #REF! | AQ4: =VLOOKUP(H4,#REF!,9,0) -> #REF! | AR4: =VLOOKUP(H4,#REF!,15,0) -> #REF! | AS4: =VLOOKUP(H4,#REF!,16,0) -> #REF! | AT4: =VLOOKUP(H4,#REF!,17,0) -> #REF! | AU4: =VLOOKUP(H4,#REF!,18,0) -> #REF! | AV4: =VLOOKUP(H4,#REF!,19,0) -> #REF! | AW4: =VLOOKUP(H4,#REF!,20,0) -> #REF! | AX4: =VLOOKUP(H4,#REF!,22,0) -> #REF! | AY4: =VLOOKUP(H4,#REF!,23,0) -> #REF! | AZ4: =VLOOKUP(H4,#REF!,24,0) -> #REF! | BA4: =VLOOKUP(H4,#REF!,25,0) -> #REF! | BB4: =VLOOKUP(H4,#REF!,26,0) -> #REF! | BC4: =VLOOKUP(H4,#REF!,27,0) -> #REF! | BD4: =VLOOKUP(H4,#REF!,29,0) -> #REF! | BE4: =VLOOKUP(H4,#REF!,30,0) -> #REF! | BF4: =VLOOKUP(H4,#REF!,31,0) -> #REF! | BG4: =VLOOKUP(H4,#REF!,32,0) -> #REF! | BH4: =VLOOKUP(H4,#REF!,33,0) -> #REF! | BI4: =VLOOKUP(H4,#REF!,34,0) -> #REF! | BJ4: =VLOOKUP(H4,#REF!,36,0) -> #REF! | BK4: =VLOOKUP(H4,#REF!,37,0) -> #REF! | BL4: =VLOOKUP(H4,#REF!,44,0) -> #REF! | BM4: =VLOOKUP(H4,#REF!,45,0) -> #REF! | BN4: =VLOOKUP(H4,#REF!,46,0) -> #REF! | BO4: =VLOOKUP(H4,#REF!,47,0) -> #REF! | BP4: =VLOOKUP(H4,#REF!,48,0) -> #REF!
A5: Gobierno nacional | B5: Poder Ejecutivo | C5: E | D5: 8 | E5: RELACIONES EXTERIORES | F5: 80 | G5: AGENCIA PERUANA DE COOPERACION INTERNACIONAL - APCI | H5: 1089 | I5: AGENCIA PERUANA DE COOPERACION INTERNACIONAL - APCI | J5: 15 | K5: LIMA | L5: 1 | M5: LIMA | N5: 22 | O5: MIRAFLORES | Q5: S | R5: S | W5: =IFERROR(VLOOKUP(H5,'IT PEI'!$X$2:$X$5647,1,0),"...") -> 1089 | X5: =_xlfn.XLOOKUP(H5,'IT PEI'!X$2:X$5647,'IT PEI'!E$2:E$5647,"...",2,-1) -> 2025-2030 | Y5: =_xlfn.XLOOKUP(H5,'IT PEI'!X$2:X$5647,'IT PEI'!G$2:G$5647,"...",2,-1) -> MODIFICADO | Z5: =_xlfn.XLOOKUP(H5,'IT PEI'!X$2:X$5647,'IT PEI'!F$2:F$5647,"...",2,-1) -> SI | AA5: =_xlfn.XLOOKUP(H5,'IT PEI'!X$2:X$5647,'IT PEI'!H$2:H$5647,"...",2,-1) -> EN PROCESO | AB5: =_xlfn.XLOOKUP(H5,'IT PEI'!X$2:X$5647,'IT PEI'!O$2:O$5647,"...",2,-1) -> 0 | AC5: =_xlfn.XLOOKUP(H5,'IT PEI'!X$2:X$5647,'IT PEI'!P$2:P$5647,"...",2,-1) -> 0 | AD5: =_xlfn.XLOOKUP(H5,'IT PEI'!X$2:X$5647,'IT PEI'!Q$2:Q$5647,"...",2,-1) -> 0 | AE5: =IF(COUNTIF(X5, "*" & "2030" & "*")>0, "SI", "No" ) -> SI | AF5: =IF(COUNTIF(X5, "*" & "2030" & "*")>0, 1, 0 ) -> 1 | AG5: =IF(COUNTIF(X5, "*" & "2030" & "*")>0, 0, 1 ) -> 0 | AH5: =IF(AND(AA5="En Proceso",AE5="Si"),1,0) -> 1 | AI5: ACTIVO | AJ5: Vilma Celestino Villafana | AK5: vcelestinov@gmail.com | AL5: =IFERROR(VLOOKUP(tbl_ues[[#This Row],[Id_UE]],'[1]Directorio v.02'!$H$3:$U$3089,11,FALSE),"") -> Ing. Cesar Eduardo Díaz Díaz | AM5: =IFERROR(VLOOKUP(tbl_ues[[#This Row],[Id_UE]],'[1]Directorio v.02'!$H$3:$U$3089,12,FALSE),"") -> Jefe de la Oficina de Planeamiento y Presupuesto | AN5: =IFERROR(VLOOKUP(tbl_ues[[#This Row],[Id_UE]],'[1]Directorio v.02'!$H$3:$U$3089,13,FALSE),"") -> 944 266 341 | AO5: =IFERROR(VLOOKUP(tbl_ues[[#This Row],[Id_UE]],'[1]Directorio v.02'!$H$3:$U$3089,14,FALSE),"") -> cdiaz@apci.gob.pe | AP5: =VLOOKUP(H5,#REF!,7,0) -> #REF! | AQ5: =VLOOKUP(H5,#REF!,9,0) -> #REF! | AR5: =VLOOKUP(H5,#REF!,15,0) -> #REF! | AS5: =VLOOKUP(H5,#REF!,16,0) -> #REF! | AT5: =VLOOKUP(H5,#REF!,17,0) -> #REF! | AU5: =VLOOKUP(H5,#REF!,18,0) -> #REF! | AV5: =VLOOKUP(H5,#REF!,19,0) -> #REF! | AW5: =VLOOKUP(H5,#REF!,20,0) -> #REF! | AX5: =VLOOKUP(H5,#REF!,22,0) -> #REF! | AY5: =VLOOKUP(H5,#REF!,23,0) -> #REF! | AZ5: =VLOOKUP(H5,#REF!,24,0) -> #REF! | BA5: =VLOOKUP(H5,#REF!,25,0) -> #REF! | BB5: =VLOOKUP(H5,#REF!,26,0) -> #REF! | BC5: =VLOOKUP(H5,#REF!,27,0) -> #REF! | BD5: =VLOOKUP(H5,#REF!,29,0) -> #REF! | BE5: =VLOOKUP(H5,#REF!,30,0) -> #REF! | BF5: =VLOOKUP(H5,#REF!,31,0) -> #REF! | BG5: =VLOOKUP(H5,#REF!,32,0) -> #REF! | BH5: =VLOOKUP(H5,#REF!,33,0) -> #REF! | BI5: =VLOOKUP(H5,#REF!,34,0) -> #REF! | BJ5: =VLOOKUP(H5,#REF!,36,0) -> #REF! | BK5: =VLOOKUP(H5,#REF!,37,0) -> #REF! | BL5: =VLOOKUP(H5,#REF!,44,0) -> #REF! | BM5: =VLOOKUP(H5,#REF!,45,0) -> #REF! | BN5: =VLOOKUP(H5,#REF!,46,0) -> #REF! | BO5: =VLOOKUP(H5,#REF!,47,0) -> #REF! | BP5: =VLOOKUP(H5,#REF!,48,0) -> #REF!
A6: Gobierno nacional | B6: Poder Ejecutivo | C6: E | D6: 3 | E6: CULTURA | F6: 60 | G6: ARCHIVO GENERAL DE LA NACION | H6: 16 | I6: OFICINA TECNICA ADMINISTRATIVA-ARCHIVO GENERAL DE LA NACION | J6: 15 | K6: LIMA | L6: 1 | M6: LIMA | N6: 1 | O6: LIMA | Q6: S | R6: S | W6: =IFERROR(VLOOKUP(H6,'IT PEI'!$X$2:$X$5647,1,0),"...") -> 16 | X6: =_xlfn.XLOOKUP(H6,'IT PEI'!X$2:X$5647,'IT PEI'!E$2:E$5647,"...",2,-1) -> 2025-2030 | Y6: =_xlfn.XLOOKUP(H6,'IT PEI'!X$2:X$5647,'IT PEI'!G$2:G$5647,"...",2,-1) -> FORMULADO | Z6: =_xlfn.XLOOKUP(H6,'IT PEI'!X$2:X$5647,'IT PEI'!F$2:F$5647,"...",2,-1) -> SI | AA6: =_xlfn.XLOOKUP(H6,'IT PEI'!X$2:X$5647,'IT PEI'!H$2:H$5647,"...",2,-1) -> EMITIDO | AB6: =_xlfn.XLOOKUP(H6,'IT PEI'!X$2:X$5647,'IT PEI'!O$2:O$5647,"...",2,-1) -> 2025-0000332 | AC6: =_xlfn.XLOOKUP(H6,'IT PEI'!X$2:X$5647,'IT PEI'!P$2:P$5647,"...",2,-1) -> 45687 | AD6: =_xlfn.XLOOKUP(H6,'IT PEI'!X$2:X$5647,'IT PEI'!Q$2:Q$5647,"...",2,-1) -> 000032-2025-CEPLAN-DNCPPEI | AE6: =IF(COUNTIF(X6, "*" & "2030" & "*")>0, "SI", "No" ) -> SI | AF6: =IF(COUNTIF(X6, "*" & "2030" & "*")>0, 1, 0 ) -> 1 | AG6: =IF(COUNTIF(X6, "*" & "2030" & "*")>0, 0, 1 ) -> 0 | AH6: =IF(AND(AA6="En Proceso",AE6="Si"),1,0) -> 0 | AI6: ACTIVO | AJ6: Lourdes Gutierrez Aguado | AK6: lgutierrez@ceplan.gob.pe | AL6: =IFERROR(VLOOKUP(tbl_ues[[#This Row],[Id_UE]],'[1]Directorio v.02'!$H$3:$U$3089,11,FALSE),"") -> Carlos Ricardo Velazco Bonzano | AM6: =IFERROR(VLOOKUP(tbl_ues[[#This Row],[Id_UE]],'[1]Directorio v.02'!$H$3:$U$3089,12,FALSE),"") -> Jefe de la Oficina de Planeamiento y Presupuesto | AN6: =IFERROR(VLOOKUP(tbl_ues[[#This Row],[Id_UE]],'[1]Directorio v.02'!$H$3:$U$3089,13,FALSE),"") -> 426-7221 - Anexo: 222 | AO6: =IFERROR(VLOOKUP(tbl_ues[[#This Row],[Id_UE]],'[1]Directorio v.02'!$H$3:$U$3089,14,FALSE),"") -> cvelazco@agn.gob.pe | AP6: =VLOOKUP(H6,#REF!,7,0) -> #REF! | AQ6: =VLOOKUP(H6,#REF!,9,0) -> #REF! | AR6: =VLOOKUP(H6,#REF!,15,0) -> #REF! | AS6: =VLOOKUP(H6,#REF!,16,0) -> #REF! | AT6: =VLOOKUP(H6,#REF!,17,0) -> #REF! | AU6: =VLOOKUP(H6,#REF!,18,0) -> #REF! | AV6: =VLOOKUP(H6,#REF!,19,0) -> #REF! | AW6: =VLOOKUP(H6,#REF!,20,0) -> #REF! | AX6: =VLOOKUP(H6,#REF!,22,0) -> #REF! | AY6: =VLOOKUP(H6,#REF!,23,0) -> #REF! | AZ6: =VLOOKUP(H6,#REF!,24,0) -> #REF! | BA6: =VLOOKUP(H6,#REF!,25,0) -> #REF! | BB6: =VLOOKUP(H6,#REF!,26,0) -> #REF! | BC6: =VLOOKUP(H6,#REF!,27,0) -> #REF! | BD6: =VLOOKUP(H6,#REF!,29,0) -> #REF! | BE6: =VLOOKUP(H6,#REF!,30,0) -> #REF! | BF6: =VLOOKUP(H6,#REF!,31,0) -> #REF! | BG6: =VLOOKUP(H6,#REF!,32,0) -> #REF! | BH6: =VLOOKUP(H6,#REF!,33,0) -> #REF! | BI6: =VLOOKUP(H6,#REF!,34,0) -> #REF! | BJ6: =VLOOKUP(H6,#REF!,36,0) -> #REF! | BK6: =VLOOKUP(H6,#REF!,37,0) -> #REF! | BL6: =VLOOKUP(H6,#REF!,44,0) -> #REF! | BM6: =VLOOKUP(H6,#REF!,45,0) -> #REF! | BN6: =VLOOKUP(H6,#REF!,46,0) -> #REF! | BO6: =VLOOKUP(H6,#REF!,47,0) -> #REF! | BP6: =VLOOKUP(H6,#REF!,48,0) -> #REF!
A7: Gobierno nacional | B7: Poder Ejecutivo | C7: E | D7: 36 | E7: TRANSPORTES Y COMUNICACIONES | F7: 203 | G7: AUTORIDAD DE TRANSPORTE URBANO PARA LIMA Y CALLAO - ATU | H7: 1717 | I7: AUTORIDAD DE TRANSPORTE URBANO PARA LIMA Y CALLAO - ATU | J7: 15 | K7: LIMA | L7: 1 | M7: LIMA | N7: 22 | O7: MIRAFLORES | Q7: S | R7: S | W7: =IFERROR(VLOOKUP(H7,'IT PEI'!$X$2:$X$5647,1,0),"...") -> 1717 | X7: =_xlfn.XLOOKUP(H7,'IT PEI'!X$2:X$5647,'IT PEI'!E$2:E$5647,"...",2,-1) -> 2024-2030 | Y7: =_xlfn.XLOOKUP(H7,'IT PEI'!X$2:X$5647,'IT PEI'!G$2:G$5647,"...",2,-1) -> ACTUALIZADO | Z7: =_xlfn.XLOOKUP(H7,'IT PEI'!X$2:X$5647,'IT PEI'!F$2:F$5647,"...",2,-1) -> SI | AA7: =_xlfn.XLOOKUP(H7,'IT PEI'!X$2:X$5647,'IT PEI'!H$2:H$5647,"...",2,-1) -> EMITIDO | AB7: =_xlfn.XLOOKUP(H7,'IT PEI'!X$2:X$5647,'IT PEI'!O$2:O$5647,"...",2,-1) -> 2026-0001605 | AC7: =_xlfn.XLOOKUP(H7,'IT PEI'!X$2:X$5647,'IT PEI'!P$2:P$5647,"...",2,-1) -> 46126 | AD7: =_xlfn.XLOOKUP(H7,'IT PEI'!X$2:X$5647,'IT PEI'!Q$2:Q$5647,"...",2,-1) -> 000264-2026-CEPLAN-DNCPPEI | AE7: =IF(COUNTIF(X7, "*" & "2030" & "*")>0, "SI", "No" ) -> SI | AF7: =IF(COUNTIF(X7, "*" & "2030" & "*")>0, 1, 0 ) -> 1 | AG7: =IF(COUNTIF(X7, "*" & "2030" & "*")>0, 0, 1 ) -> 0 | AH7: =IF(AND(AA7="En Proceso",AE7="Si"),1,0) -> 0 | AI7: ACTIVO | AJ7: Leidy Cayotopa Mesones | AK7: leidy.cayotopa.ceplan@gmail.com | AL7: =IFERROR(VLOOKUP(tbl_ues[[#This Row],[Id_UE]],'[1]Directorio v.02'!$H$3:$U$3089,11,FALSE),"") -> Alexandro Fabricio Estremadoyro Koc | AM7: =IFERROR(VLOOKUP(tbl_ues[[#This Row],[Id_UE]],'[1]Directorio v.02'!$H$3:$U$3089,12,FALSE),"") -> Jefe de la Unidad de Planeamiento y Organización | AN7: =IFERROR(VLOOKUP(tbl_ues[[#This Row],[Id_UE]],'[1]Directorio v.02'!$H$3:$U$3089,13,FALSE),"") -> (01)224 2444/ Anexo 1335 | AO7: =IFERROR(VLOOKUP(tbl_ues[[#This Row],[Id_UE]],'[1]Directorio v.02'!$H$3:$U$3089,14,FALSE),"") -> aestremadoyro@atu.gob.pe | AP7: =VLOOKUP(H7,#REF!,7,0) -> #REF! | AQ7: =VLOOKUP(H7,#REF!,9,0) -> #REF! | AR7: =VLOOKUP(H7,#REF!,15,0) -> #REF! | AS7: =VLOOKUP(H7,#REF!,16,0) -> #REF! | AT7: =VLOOKUP(H7,#REF!,17,0) -> #REF! | AU7: =VLOOKUP(H7,#REF!,18,0) -> #REF! | AV7: =VLOOKUP(H7,#REF!,19,0) -> #REF! | AW7: =VLOOKUP(H7,#REF!,20,0) -> #REF! | AX7: =VLOOKUP(H7,#REF!,22,0) -> #REF! | AY7: =VLOOKUP(H7,#REF!,23,0) -> #REF! | AZ7: =VLOOKUP(H7,#REF!,24,0) -> #REF! | BA7: =VLOOKUP(H7,#REF!,25,0) -> #REF! | BB7: =VLOOKUP(H7,#REF!,26,0) -> #REF! | BC7: =VLOOKUP(H7,#REF!,27,0) -> #REF! | BD7: =VLOOKUP(H7,#REF!,29,0) -> #REF! | BE7: =VLOOKUP(H7,#REF!,30,0) -> #REF! | BF7: =VLOOKUP(H7,#REF!,31,0) -> #REF! | BG7: =VLOOKUP(H7,#REF!,32,0) -> #REF! | BH7: =VLOOKUP(H7,#REF!,33,0) -> #REF! | BI7: =VLOOKUP(H7,#REF!,34,0) -> #REF! | BJ7: =VLOOKUP(H7,#REF!,36,0) -> #REF! | BK7: =VLOOKUP(H7,#REF!,37,0) -> #REF! | BL7: =VLOOKUP(H7,#REF!,44,0) -> #REF! | BM7: =VLOOKUP(H7,#REF!,45,0) -> #REF! | BN7: =VLOOKUP(H7,#REF!,46,0) -> #REF! | BO7: =VLOOKUP(H7,#REF!,47,0) -> #REF! | BP7: =VLOOKUP(H7,#REF!,48,0) -> #REF!
A8: Gobierno nacional | B8: Poder Ejecutivo | C8: E | D8: 1 | E8: PRESIDENCIA CONSEJO MINISTROS | F8: 29 | G8: AUTORIDAD NACIONAL DE INFRAESTRUCTURA | H8: 1750 | I8: AUTORIDAD NACIONAL DE INFRAESTRUCTURA | J8: 15 | K8: LIMA | L8: 1 | M8: LIMA | N8: 1 | O8: LIMA | Q8: S | R8: S | W8: =IFERROR(VLOOKUP(H8,'IT PEI'!$X$2:$X$5647,1,0),"...") -> 1750 | X8: =_xlfn.XLOOKUP(H8,'IT PEI'!X$2:X$5647,'IT PEI'!E$2:E$5647,"...",2,-1) -> 2025-2030 | Y8: =_xlfn.XLOOKUP(H8,'IT PEI'!X$2:X$5647,'IT PEI'!G$2:G$5647,"...",2,-1) -> FORMULADO | Z8: =_xlfn.XLOOKUP(H8,'IT PEI'!X$2:X$5647,'IT PEI'!F$2:F$5647,"...",2,-1) -> SI | AA8: =_xlfn.XLOOKUP(H8,'IT PEI'!X$2:X$5647,'IT PEI'!H$2:H$5647,"...",2,-1) -> EMITIDO | AB8: =_xlfn.XLOOKUP(H8,'IT PEI'!X$2:X$5647,'IT PEI'!O$2:O$5647,"...",2,-1) -> 2024-0001068 | AC8: =_xlfn.XLOOKUP(H8,'IT PEI'!X$2:X$5647,'IT PEI'!P$2:P$5647,"...",2,-1) -> 45656 | AD8: =_xlfn.XLOOKUP(H8,'IT PEI'!X$2:X$5647,'IT PEI'!Q$2:Q$5647,"...",2,-1) -> 000487-2024-CEPLAN-DNCPPEI | AE8: =IF(COUNTIF(X8, "*" & "2030" & "*")>0, "SI", "No" ) -> SI | AF8: =IF(COUNTIF(X8, "*" & "2030" & "*")>0, 1, 0 ) -> 1 | AG8: =IF(COUNTIF(X8, "*" & "2030" & "*")>0, 0, 1 ) -> 0 | AH8: =IF(AND(AA8="En Proceso",AE8="Si"),1,0) -> 0 | AI8: ACTIVO | AJ8: Claudia Melendez Mauricio | AK8: claudia.melendez.ceplan@gmail.com | AL8: =IFERROR(VLOOKUP(tbl_ues[[#This Row],[Id_UE]],'[1]Directorio v.02'!$H$3:$U$3089,11,FALSE),"") -> Carlos Chunga | AM8: =IFERROR(VLOOKUP(tbl_ues[[#This Row],[Id_UE]],'[1]Directorio v.02'!$H$3:$U$3089,12,FALSE),"") -> Jefe de la unidad de Planeamiento | AN8: =IFERROR(VLOOKUP(tbl_ues[[#This Row],[Id_UE]],'[1]Directorio v.02'!$H$3:$U$3089,13,FALSE),"") -> 993392829 | AO8: =IFERROR(VLOOKUP(tbl_ues[[#This Row],[Id_UE]],'[1]Directorio v.02'!$H$3:$U$3089,14,FALSE),"") -> cchunga@anin.gob.pe | AP8: =VLOOKUP(H8,#REF!,7,0) -> #REF! | AQ8: =VLOOKUP(H8,#REF!,9,0) -> #REF! | AR8: =VLOOKUP(H8,#REF!,15,0) -> #REF! | AS8: =VLOOKUP(H8,#REF!,16,0) -> #REF! | AT8: =VLOOKUP(H8,#REF!,17,0) -> #REF! | AU8: =VLOOKUP(H8,#REF!,18,0) -> #REF! | AV8: =VLOOKUP(H8,#REF!,19,0) -> #REF! | AW8: =VLOOKUP(H8,#REF!,20,0) -> #REF! | AX8: =VLOOKUP(H8,#REF!,22,0) -> #REF! | AY8: =VLOOKUP(H8,#REF!,23,0) -> #REF! | AZ8: =VLOOKUP(H8,#REF!,24,0) -> #REF! | BA8: =VLOOKUP(H8,#REF!,25,0) -> #REF! | BB8: =VLOOKUP(H8,#REF!,26,0) -> #REF! | BC8: =VLOOKUP(H8,#REF!,27,0) -> #REF! | BD8: =VLOOKUP(H8,#REF!,29,0) -> #REF! | BE8: =VLOOKUP(H8,#REF!,30,0) -> #REF! | BF8: =VLOOKUP(H8,#REF!,31,0) -> #REF! | BG8: =VLOOKUP(H8,#REF!,32,0) -> #REF! | BH8: =VLOOKUP(H8,#REF!,33,0) -> #REF! | BI8: =VLOOKUP(H8,#REF!,34,0) -> #REF! | BJ8: =VLOOKUP(H8,#REF!,36,0) -> #REF! | BK8: =VLOOKUP(H8,#REF!,37,0) -> #REF! | BL8: =VLOOKUP(H8,#REF!,44,0) -> #REF! | BM8: =VLOOKUP(H8,#REF!,45,0) -> #REF! | BN8: =VLOOKUP(H8,#REF!,46,0) -> #REF! | BO8: =VLOOKUP(H8,#REF!,47,0) -> #REF! | BP8: =VLOOKUP(H8,#REF!,48,0) -> #REF!
A9: Gobierno nacional | B9: Poder Ejecutivo | C9: E | D9: 13 | E9: AGRARIO Y DE RIEGO | F9: 164 | G9: AUTORIDAD NACIONAL DEL AGUA - ANA | H9: 1358 | I9: MODERNIZACION DE LA GESTION DE LOS RECURSOS HIDRICOS | J9: 15 | K9: LIMA | L9: 1 | M9: LIMA | N9: 30 | O9: SAN BORJA | R9: S | W9: =IFERROR(VLOOKUP(H9,'IT PEI'!$X$2:$X$5647,1,0),"...") -> ... | X9: =_xlfn.XLOOKUP(H9,'IT PEI'!X$2:X$5647,'IT PEI'!E$2:E$5647,"...",2,-1) -> ... | Y9: =_xlfn.XLOOKUP(H9,'IT PEI'!X$2:X$5647,'IT PEI'!G$2:G$5647,"...",2,-1) -> ... | Z9: =_xlfn.XLOOKUP(H9,'IT PEI'!X$2:X$5647,'IT PEI'!F$2:F$5647,"...",2,-1) -> ... | AA9: =_xlfn.XLOOKUP(H9,'IT PEI'!X$2:X$5647,'IT PEI'!H$2:H$5647,"...",2,-1) -> ... | AB9: =_xlfn.XLOOKUP(H9,'IT PEI'!X$2:X$5647,'IT PEI'!O$2:O$5647,"...",2,-1) -> ... | AC9: =_xlfn.XLOOKUP(H9,'IT PEI'!X$2:X$5647,'IT PEI'!P$2:P$5647,"...",2,-1) -> ... | AD9: =_xlfn.XLOOKUP(H9,'IT PEI'!X$2:X$5647,'IT PEI'!Q$2:Q$5647,"...",2,-1) -> ... | AE9: =IF(COUNTIF(X9, "*" & "2030" & "*")>0, "SI", "No" ) -> No | AF9: =IF(COUNTIF(X9, "*" & "2030" & "*")>0, 1, 0 ) -> 0 | AG9: =IF(COUNTIF(X9, "*" & "2030" & "*")>0, 0, 1 ) -> 1 | AH9: =IF(AND(AA9="En Proceso",AE9="Si"),1,0) -> 0 | AI9: INACTIVO | AJ9: Fatima Amoretti Arteaga | AK9: fatima.amoretti.ceplan@gmail.com | AL9: =IFERROR(VLOOKUP(tbl_ues[[#This Row],[Id_UE]],'[1]Directorio v.02'!$H$3:$U$3089,11,FALSE),"") | AM9: =IFERROR(VLOOKUP(tbl_ues[[#This Row],[Id_UE]],'[1]Directorio v.02'!$H$3:$U$3089,12,FALSE),"") | AN9: =IFERROR(VLOOKUP(tbl_ues[[#This Row],[Id_UE]],'[1]Directorio v.02'!$H$3:$U$3089,13,FALSE),"") | AO9: =IFERROR(VLOOKUP(tbl_ues[[#This Row],[Id_UE]],'[1]Directorio v.02'!$H$3:$U$3089,14,FALSE),"") | AP9: =VLOOKUP(H9,#REF!,7,0) -> #REF! | AQ9: =VLOOKUP(H9,#REF!,9,0) -> #REF! | AR9: =VLOOKUP(H9,#REF!,15,0) -> #REF! | AS9: =VLOOKUP(H9,#REF!,16,0) -> #REF! | AT9: =VLOOKUP(H9,#REF!,17,0) -> #REF! | AU9: =VLOOKUP(H9,#REF!,18,0) -> #REF! | AV9: =VLOOKUP(H9,#REF!,19,0) -> #REF! | AW9: =VLOOKUP(H9,#REF!,20,0) -> #REF! | AX9: =VLOOKUP(H9,#REF!,22,0) -> #REF! | AY9: =VLOOKUP(H9,#REF!,23,0) -> #REF! | AZ9: =VLOOKUP(H9,#REF!,24,0) -> #REF! | BA9: =VLOOKUP(H9,#REF!,25,0) -> #REF! | BB9: =VLOOKUP(H9,#REF!,26,0) -> #REF! | BC9: =VLOOKUP(H9,#REF!,27,0) -> #REF! | BD9: =VLOOKUP(H9,#REF!,29,0) -> #REF! | BE9: =VLOOKUP(H9,#REF!,30,0) -> #REF! | BF9: =VLOOKUP(H9,#REF!,31,0) -> #REF! | BG9: =VLOOKUP(H9,#REF!,32,0) -> #REF! | BH9: =VLOOKUP(H9,#REF!,33,0) -> #REF! | BI9: =VLOOKUP(H9,#REF!,34,0) -> #REF! | BJ9: =VLOOKUP(H9,#REF!,36,0) -> #REF! | BK9: =VLOOKUP(H9,#REF!,37,0) -> #REF! | BL9: =VLOOKUP(H9,#REF!,44,0) -> #REF! | BM9: =VLOOKUP(H9,#REF!,45,0) -> #REF! | BN9: =VLOOKUP(H9,#REF!,46,0) -> #REF! | BO9: =VLOOKUP(H9,#REF!,47,0) -> #REF! | BP9: =VLOOKUP(H9,#REF!,48,0) -> #REF!
A10: Gobierno nacional | B10: Poder Ejecutivo | C10: E | D10: 13 | E10: AGRARIO Y DE RIEGO | F10: 164 | G10: AUTORIDAD NACIONAL DEL AGUA - ANA | H10: 1299 | I10: AUTORIDAD NACIONAL DE AGUA - SEDE CENTRAL | J10: 15 | K10: LIMA | L10: 1 | M10: LIMA | N10: 31 | O10: SAN ISIDRO | Q10: S | R10: S | W10: =IFERROR(VLOOKUP(H10,'IT PEI'!$X$2:$X$5647,1,0),"...") -> 1299 | X10: =_xlfn.XLOOKUP(H10,'IT PEI'!X$2:X$5647,'IT PEI'!E$2:E$5647,"...",2,-1) -> 2025-2030 | Y10: =_xlfn.XLOOKUP(H10,'IT PEI'!X$2:X$5647,'IT PEI'!G$2:G$5647,"...",2,-1) -> FORMULADO | Z10: =_xlfn.XLOOKUP(H10,'IT PEI'!X$2:X$5647,'IT PEI'!F$2:F$5647,"...",2,-1) -> SI | AA10: =_xlfn.XLOOKUP(H10,'IT PEI'!X$2:X$5647,'IT PEI'!H$2:H$5647,"...",2,-1) -> EMITIDO | AB10: =_xlfn.XLOOKUP(H10,'IT PEI'!X$2:X$5647,'IT PEI'!O$2:O$5647,"...",2,-1) -> 2024-0003569 | AC10: =_xlfn.XLOOKUP(H10,'IT PEI'!X$2:X$5647,'IT PEI'!P$2:P$5647,"...",2,-1) -> 45628 | AD10: =_xlfn.XLOOKUP(H10,'IT PEI'!X$2:X$5647,'IT PEI'!Q$2:Q$5647,"...",2,-1) -> 000404-2024-CEPLAN-DNCPPEI | AE10: =IF(COUNTIF(X10, "*" & "2030" & "*")>0, "SI", "No" ) -> SI | AF10: =IF(COUNTIF(X10, "*" & "2030" & "*")>0, 1, 0 ) -> 1 | AG10: =IF(COUNTIF(X10, "*" & "2030" & "*")>0, 0, 1 ) -> 0 | AH10: =IF(AND(AA10="En Proceso",AE10="Si"),1,0) -> 0 | AI10: ACTIVO | AJ10: Fatima Amoretti Arteaga | AK10: fatima.amoretti.ceplan@gmail.com | AL10: =IFERROR(VLOOKUP(tbl_ues[[#This Row],[Id_UE]],'[1]Directorio v.02'!$H$3:$U$3089,11,FALSE),"") -> Cpcc. Johnny César Cayo Saravia | AM10: =IFERROR(VLOOKUP(tbl_ues[[#This Row],[Id_UE]],'[1]Directorio v.02'!$H$3:$U$3089,12,FALSE),"") -> Director Oficina de Planeamiento y Presupuesto | AN10: =IFERROR(VLOOKUP(tbl_ues[[#This Row],[Id_UE]],'[1]Directorio v.02'!$H$3:$U$3089,13,FALSE),"") -> 224-3298 A. 1409 | AO10: =IFERROR(VLOOKUP(tbl_ues[[#This Row],[Id_UE]],'[1]Directorio v.02'!$H$3:$U$3089,14,FALSE),"") -> ccayo@ana.gob.pe | AP10: =VLOOKUP(H10,#REF!,7,0) -> #REF! | AQ10: =VLOOKUP(H10,#REF!,9,0) -> #REF! | AR10: =VLOOKUP(H10,#REF!,15,0) -> #REF! | AS10: =VLOOKUP(H10,#REF!,16,0) -> #REF! | AT10: =VLOOKUP(H10,#REF!,17,0) -> #REF! | AU10: =VLOOKUP(H10,#REF!,18,0) -> #REF! | AV10: =VLOOKUP(H10,#REF!,19,0) -> #REF! | AW10: =VLOOKUP(H10,#REF!,20,0) -> #REF! | AX10: =VLOOKUP(H10,#REF!,22,0) -> #REF! | AY10: =VLOOKUP(H10,#REF!,23,0) -> #REF! | AZ10: =VLOOKUP(H10,#REF!,24,0) -> #REF! | BA10: =VLOOKUP(H10,#REF!,25,0) -> #REF! | BB10: =VLOOKUP(H10,#REF!,26,0) -> #REF! | BC10: =VLOOKUP(H10,#REF!,27,0) -> #REF! | BD10: =VLOOKUP(H10,#REF!,29,0) -> #REF! | BE10: =VLOOKUP(H10,#REF!,30,0) -> #REF! | BF10: =VLOOKUP(H10,#REF!,31,0) -> #REF! | BG10: =VLOOKUP(H10,#REF!,32,0) -> #REF! | BH10: =VLOOKUP(H10,#REF!,33,0) -> #REF! | BI10: =VLOOKUP(H10,#REF!,34,0) -> #REF! | BJ10: =VLOOKUP(H10,#REF!,36,0) -> #REF! | BK10: =VLOOKUP(H10,#REF!,37,0) -> #REF! | BL10: =VLOOKUP(H10,#REF!,44,0) -> #REF! | BM10: =VLOOKUP(H10,#REF!,45,0) -> #REF! | BN10: =VLOOKUP(H10,#REF!,46,0) -> #REF! | BO10: =VLOOKUP(H10,#REF!,47,0) -> #REF! | BP10: =VLOOKUP(H10,#REF!,48,0) -> #REF!
A11: Gobierno nacional | B11: Poder Ejecutivo | C11: E | D11: 1 | E11: PRESIDENCIA CONSEJO MINISTROS | F11: 23 | G11: AUTORIDAD NACIONAL DEL SERVICIO CIVIL | H11: 1314 | I11: AUTORIDAD NACIONAL DE SERVICIO CIVIL | J11: 15 | K11: LIMA | L11: 1 | M11: LIMA | N11: 13 | O11: JESUS MARIA | Q11: S | R11: S | W11: =IFERROR(VLOOKUP(H11,'IT PEI'!$X$2:$X$5647,1,0),"...") -> 1314 | X11: =_xlfn.XLOOKUP(H11,'IT PEI'!X$2:X$5647,'IT PEI'!E$2:E$5647,"...",2,-1) -> 2025-2030 | Y11: =_xlfn.XLOOKUP(H11,'IT PEI'!X$2:X$5647,'IT PEI'!G$2:G$5647,"...",2,-1) -> FORMULADO | Z11: =_xlfn.XLOOKUP(H11,'IT PEI'!X$2:X$5647,'IT PEI'!F$2:F$5647,"...",2,-1) -> SI | AA11: =_xlfn.XLOOKUP(H11,'IT PEI'!X$2:X$5647,'IT PEI'!H$2:H$5647,"...",2,-1) -> EMITIDO | AB11: =_xlfn.XLOOKUP(H11,'IT PEI'!X$2:X$5647,'IT PEI'!O$2:O$5647,"...",2,-1) -> 2024-0003871 | AC11: =_xlfn.XLOOKUP(H11,'IT PEI'!X$2:X$5647,'IT PEI'!P$2:P$5647,"...",2,-1) -> 45645 | AD11: =_xlfn.XLOOKUP(H11,'IT PEI'!X$2:X$5647,'IT PEI'!Q$2:Q$5647,"...",2,-1) -> 000448-2024-CEPLAN-DNCPPEI | AE11: =IF(COUNTIF(X11, "*" & "2030" & "*")>0, "SI", "No" ) -> SI | AF11: =IF(COUNTIF(X11, "*" & "2030" & "*")>0, 1, 0 ) -> 1 | AG11: =IF(COUNTIF(X11, "*" & "2030" & "*")>0, 0, 1 ) -> 0 | AH11: =IF(AND(AA11="En Proceso",AE11="Si"),1,0) -> 0 | AI11: ACTIVO | AJ11: Claudia Melendez Mauricio | AK11: claudia.melendez.ceplan@gmail.com | AL11: =IFERROR(VLOOKUP(tbl_ues[[#This Row],[Id_UE]],'[1]Directorio v.02'!$H$3:$U$3089,11,FALSE),"") -> Irwing Aspajo Grandez | AM11: =IFERROR(VLOOKUP(tbl_ues[[#This Row],[Id_UE]],'[1]Directorio v.02'!$H$3:$U$3089,12,FALSE),"") -> Jefe de la Oficina de Planeamiento y Presupuesto | AN11: =IFERROR(VLOOKUP(tbl_ues[[#This Row],[Id_UE]],'[1]Directorio v.02'!$H$3:$U$3089,13,FALSE),"") -> 964419164 | AO11: =IFERROR(VLOOKUP(tbl_ues[[#This Row],[Id_UE]],'[1]Directorio v.02'!$H$3:$U$3089,14,FALSE),"") -> iaspajo@servir.gob.pe | AP11: =VLOOKUP(H11,#REF!,7,0) -> #REF! | AQ11: =VLOOKUP(H11,#REF!,9,0) -> #REF! | AR11: =VLOOKUP(H11,#REF!,15,0) -> #REF! | AS11: =VLOOKUP(H11,#REF!,16,0) -> #REF! | AT11: =VLOOKUP(H11,#REF!,17,0) -> #REF! | AU11: =VLOOKUP(H11,#REF!,18,0) -> #REF! | AV11: =VLOOKUP(H11,#REF!,19,0) -> #REF! | AW11: =VLOOKUP(H11,#REF!,20,0) -> #REF! | AX11: =VLOOKUP(H11,#REF!,22,0) -> #REF! | AY11: =VLOOKUP(H11,#REF!,23,0) -> #REF! | AZ11: =VLOOKUP(H11,#REF!,24,0) -> #REF! | BA11: =VLOOKUP(H11,#REF!,25,0) -> #REF! | BB11: =VLOOKUP(H11,#REF!,26,0) -> #REF! | BC11: =VLOOKUP(H11,#REF!,27,0) -> #REF! | BD11: =VLOOKUP(H11,#REF!,29,0) -> #REF! | BE11: =VLOOKUP(H11,#REF!,30,0) -> #REF! | BF11: =VLOOKUP(H11,#REF!,31,0) -> #REF! | BG11: =VLOOKUP(H11,#REF!,32,0) -> #REF! | BH11: =VLOOKUP(H11,#REF!,33,0) -> #REF! | BI11: =VLOOKUP(H11,#REF!,34,0) -> #REF! | BJ11: =VLOOKUP(H11,#REF!,36,0) -> #REF! | BK11: =VLOOKUP(H11,#REF!,37,0) -> #REF! | BL11: =VLOOKUP(H11,#REF!,44,0) -> #REF! | BM11: =VLOOKUP(H11,#REF!,45,0) -> #REF! | BN11: =VLOOKUP(H11,#REF!,46,0) -> #REF! | BO11: =VLOOKUP(H11,#REF!,47,0) -> #REF! | BP11: =VLOOKUP(H11,#REF!,48,0) -> #REF!
A12: Gobierno nacional | B12: Poder Ejecutivo | C12: E | D12: 36 | E12: TRANSPORTES Y COMUNICACIONES | F12: 214 | G12: AUTORIDAD PORTUARIA NACIONAL | H12: 1205 | I12: AUTORIDAD PORTUARIA NACIONAL | J12: 07 | K12: PROVINCIA CONSTITUCIONAL DEL CALLAO | L12: 1 | M12: CALLAO | N12: 4 | O12: LA PERLA | Q12: S | R12: S | W12: =IFERROR(VLOOKUP(H12,'IT PEI'!$X$2:$X$5647,1,0),"...") -> 1205 | X12: =_xlfn.XLOOKUP(H12,'IT PEI'!X$2:X$5647,'IT PEI'!E$2:E$5647,"...",2,-1) -> 2024-2030 | Y12: =_xlfn.XLOOKUP(H12,'IT PEI'!X$2:X$5647,'IT PEI'!G$2:G$5647,"...",2,-1) -> FORMULADO | Z12: =_xlfn.XLOOKUP(H12,'IT PEI'!X$2:X$5647,'IT PEI'!F$2:F$5647,"...",2,-1) -> SI | AA12: =_xlfn.XLOOKUP(H12,'IT PEI'!X$2:X$5647,'IT PEI'!H$2:H$5647,"...",2,-1) -> EMITIDO | AB12: =_xlfn.XLOOKUP(H12,'IT PEI'!X$2:X$5647,'IT PEI'!O$2:O$5647,"...",2,-1) -> 2024-000236 | AC12: =_xlfn.XLOOKUP(H12,'IT PEI'!X$2:X$5647,'IT PEI'!P$2:P$5647,"...",2,-1) -> 45379 | AD12: =_xlfn.XLOOKUP(H12,'IT PEI'!X$2:X$5647,'IT PEI'!Q$2:Q$5647,"...",2,-1) -> 000145-2024-CEPLAN-DNCPPEI | AE12: =IF(COUNTIF(X12, "*" & "2030" & "*")>0, "SI", "No" ) -> SI | AF12: =IF(COUNTIF(X12, "*" & "2030" & "*")>0, 1, 0 ) -> 1 | AG12: =IF(COUNTIF(X12, "*" & "2030" & "*")>0, 0, 1 ) -> 0 | AH12: =IF(AND(AA12="En Proceso",AE12="Si"),1,0) -> 0 | AI12: ACTIVO | AJ12: Leidy Cayotopa Mesones | AK12: leidy.cayotopa.ceplan@gmail.com | AL12: =IFERROR(VLOOKUP(tbl_ues[[#This Row],[Id_UE]],'[1]Directorio v.02'!$H$3:$U$3089,11,FALSE),"") -> Ricardo Javier Guimaray Hernández | AM12: =IFERROR(VLOOKUP(tbl_ues[[#This Row],[Id_UE]],'[1]Directorio v.02'!$H$3:$U$3089,12,FALSE),"") -> Director de Planeamiento y Estudios Económicos | AN12: =IFERROR(VLOOKUP(tbl_ues[[#This Row],[Id_UE]],'[1]Directorio v.02'!$H$3:$U$3089,13,FALSE),"") -> 630 9600 Anx. 1706 | AO12: =IFERROR(VLOOKUP(tbl_ues[[#This Row],[Id_UE]],'[1]Directorio v.02'!$H$3:$U$3089,14,FALSE),"") -> rguimaray@apn.gob.pe | AP12: =VLOOKUP(H12,#REF!,7,0) -> #REF! | AQ12: =VLOOKUP(H12,#REF!,9,0) -> #REF! | AR12: =VLOOKUP(H12,#REF!,15,0) -> #REF! | AS12: =VLOOKUP(H12,#REF!,16,0) -> #REF! | AT12: =VLOOKUP(H12,#REF!,17,0) -> #REF! | AU12: =VLOOKUP(H12,#REF!,18,0) -> #REF! | AV12: =VLOOKUP(H12,#REF!,19,0) -> #REF! | AW12: =VLOOKUP(H12,#REF!,20,0) -> #REF! | AX12: =VLOOKUP(H12,#REF!,22,0) -> #REF! | AY12: =VLOOKUP(H12,#REF!,23,0) -> #REF! | AZ12: =VLOOKUP(H12,#REF!,24,0) -> #REF! | BA12: =VLOOKUP(H12,#REF!,25,0) -> #REF! | BB12: =VLOOKUP(H12,#REF!,26,0) -> #REF! | BC12: =VLOOKUP(H12,#REF!,27,0) -> #REF! | BD12: =VLOOKUP(H12,#REF!,29,0) -> #REF! | BE12: =VLOOKUP(H12,#REF!,30,0) -> #REF! | BF12: =VLOOKUP(H12,#REF!,31,0) -> #REF! | BG12: =VLOOKUP(H12,#REF!,32,0) -> #REF! | BH12: =VLOOKUP(H12,#REF!,33,0) -> #REF! | BI12: =VLOOKUP(H12,#REF!,34,0) -> #REF! | BJ12: =VLOOKUP(H12,#REF!,36,0) -> #REF! | BK12: =VLOOKUP(H12,#REF!,37,0) -> #REF! | BL12: =VLOOKUP(H12,#REF!,44,0) -> #REF! | BM12: =VLOOKUP(H12,#REF!,45,0) -> #REF! | BN12: =VLOOKUP(H12,#REF!,46,0) -> #REF! | BO12: =VLOOKUP(H12,#REF!,47,0) -> #REF! | BP12: =VLOOKUP(H12,#REF!,48,0) -> #REF!
A13: Gobierno nacional | B13: Poder Ejecutivo | C13: E | D13: 3 | E13: CULTURA | F13: 113 | G13: BIBLIOTECA NACIONAL DEL PERU | H13: 85 | I13: BIBLIOTECA NACIONAL DEL PERU | J13: 15 | K13: LIMA | L13: 1 | M13: LIMA | N13: 1 | O13: LIMA | Q13: S | R13: S | W13: =IFERROR(VLOOKUP(H13,'IT PEI'!$X$2:$X$5647,1,0),"...") -> 85 | X13: =_xlfn.XLOOKUP(H13,'IT PEI'!X$2:X$5647,'IT PEI'!E$2:E$5647,"...",2,-1) -> 2023-2030 | Y13: =_xlfn.XLOOKUP(H13,'IT PEI'!X$2:X$5647,'IT PEI'!G$2:G$5647,"...",2,-1) -> MODIFICADO | Z13: =_xlfn.XLOOKUP(H13,'IT PEI'!X$2:X$5647,'IT PEI'!F$2:F$5647,"...",2,-1) -> SI | AA13: =_xlfn.XLOOKUP(H13,'IT PEI'!X$2:X$5647,'IT PEI'!H$2:H$5647,"...",2,-1) -> EMITIDO | AB13: =_xlfn.XLOOKUP(H13,'IT PEI'!X$2:X$5647,'IT PEI'!O$2:O$5647,"...",2,-1) -> 2024-0000981 | AC13: =_xlfn.XLOOKUP(H13,'IT PEI'!X$2:X$5647,'IT PEI'!P$2:P$5647,"...",2,-1) -> 45377 | AD13: =_xlfn.XLOOKUP(H13,'IT PEI'!X$2:X$5647,'IT PEI'!Q$2:Q$5647,"...",2,-1) -> 000123-2024-CEPLAN-DNCPPEI | AE13: =IF(COUNTIF(X13, "*" & "2030" & "*")>0, "SI", "No" ) -> SI | AF13: =IF(COUNTIF(X13, "*" & "2030" & "*")>0, 1, 0 ) -> 1 | AG13: =IF(COUNTIF(X13, "*" & "2030" & "*")>0, 0, 1 ) -> 0 | AH13: =IF(AND(AA13="En Proceso",AE13="Si"),1,0) -> 0 | AI13: ACTIVO | AJ13: Lourdes Gutierrez Aguado | AK13: lgutierrez@ceplan.gob.pe | AL13: =IFERROR(VLOOKUP(tbl_ues[[#This Row],[Id_UE]],'[1]Directorio v.02'!$H$3:$U$3089,11,FALSE),"") -> Erika Romero Estela | AM13: =IFERROR(VLOOKUP(tbl_ues[[#This Row],[Id_UE]],'[1]Directorio v.02'!$H$3:$U$3089,12,FALSE),"") -> Jefe de la Oficina de Planeamiento y Presupuesto | AN13: =IFERROR(VLOOKUP(tbl_ues[[#This Row],[Id_UE]],'[1]Directorio v.02'!$H$3:$U$3089,13,FALSE),"") -> 513-6900 - Anexo 7400 | AO13: =IFERROR(VLOOKUP(tbl_ues[[#This Row],[Id_UE]],'[1]Directorio v.02'!$H$3:$U$3089,14,FALSE),"") -> erika.romero@bnp.gob.pe | AP13: =VLOOKUP(H13,#REF!,7,0) -> #REF! | AQ13: =VLOOKUP(H13,#REF!,9,0) -> #REF! | AR13: =VLOOKUP(H13,#REF!,15,0) -> #REF! | AS13: =VLOOKUP(H13,#REF!,16,0) -> #REF! | AT13: =VLOOKUP(H13,#REF!,17,0) -> #REF! | AU13: =VLOOKUP(H13,#REF!,18,0) -> #REF! | AV13: =VLOOKUP(H13,#REF!,19,0) -> #REF! | AW13: =VLOOKUP(H13,#REF!,20,0) -> #REF! | AX13: =VLOOKUP(H13,#REF!,22,0) -> #REF! | AY13: =VLOOKUP(H13,#REF!,23,0) -> #REF! | AZ13: =VLOOKUP(H13,#REF!,24,0) -> #REF! | BA13: =VLOOKUP(H13,#REF!,25,0) -> #REF! | BB13: =VLOOKUP(H13,#REF!,26,0) -> #REF! | BC13: =VLOOKUP(H13,#REF!,27,0) -> #REF! | BD13: =VLOOKUP(H13,#REF!,29,0) -> #REF! | BE13: =VLOOKUP(H13,#REF!,30,0) -> #REF! | BF13: =VLOOKUP(H13,#REF!,31,0) -> #REF! | BG13: =VLOOKUP(H13,#REF!,32,0) -> #REF! | BH13: =VLOOKUP(H13,#REF!,33,0) -> #REF! | BI13: =VLOOKUP(H13,#REF!,34,0) -> #REF! | BJ13: =VLOOKUP(H13,#REF!,36,0) -> #REF! | BK13: =VLOOKUP(H13,#REF!,37,0) -> #REF! | BL13: =VLOOKUP(H13,#REF!,44,0) -> #REF! | BM13: =VLOOKUP(H13,#REF!,45,0) -> #REF! | BN13: =VLOOKUP(H13,#REF!,46,0) -> #REF! | BO13: =VLOOKUP(H13,#REF!,47,0) -> #REF! | BP13: =VLOOKUP(H13,#REF!,48,0) -> #REF!
A14: Gobierno nacional | B14: Poder Ejecutivo | C14: E | D14: 9 | E14: ECONOMIA Y FINANZAS | F14: 96 | G14: CENTRAL DE COMPRAS PÚBLICAS - PERÚ COMPRAS | H14: 1650 | I14: CENTRAL DE COMPRAS PUBLICAS - PERU COMPRAS | J14: 15 | K14: LIMA | L14: 1 | M14: LIMA | N14: 31 | O14: SAN ISIDRO | Q14: S | R14: S | W14: =IFERROR(VLOOKUP(H14,'IT PEI'!$X$2:$X$5647,1,0),"...") -> 1650 | X14: =_xlfn.XLOOKUP(H14,'IT PEI'!X$2:X$5647,'IT PEI'!E$2:E$5647,"...",2,-1) -> 2026-2030 | Y14: =_xlfn.XLOOKUP(H14,'IT PEI'!X$2:X$5647,'IT PEI'!G$2:G$5647,"...",2,-1) -> FORMULADO | Z14: =_xlfn.XLOOKUP(H14,'IT PEI'!X$2:X$5647,'IT PEI'!F$2:F$5647,"...",2,-1) -> SI | AA14: =_xlfn.XLOOKUP(H14,'IT PEI'!X$2:X$5647,'IT PEI'!H$2:H$5647,"...",2,-1) -> EMITIDO | AB14: =_xlfn.XLOOKUP(H14,'IT PEI'!X$2:X$5647,'IT PEI'!O$2:O$5647,"...",2,-1) -> 2026-0000210 | AC14: =_xlfn.XLOOKUP(H14,'IT PEI'!X$2:X$5647,'IT PEI'!P$2:P$5647,"...",2,-1) -> 46037 | AD14: =_xlfn.XLOOKUP(H14,'IT PEI'!X$2:X$5647,'IT PEI'!Q$2:Q$5647,"...",2,-1) -> 000016-2026-CEPLAN-DNCPPEI | AE14: =IF(COUNTIF(X14, "*" & "2030" & "*")>0, "SI", "No" ) -> SI | AF14: =IF(COUNTIF(X14, "*" & "2030" & "*")>0, 1, 0 ) -> 1 | AG14: =IF(COUNTIF(X14, "*" & "2030" & "*")>0, 0, 1 ) -> 0 | AH14: =IF(AND(AA14="En Proceso",AE14="Si"),1,0) -> 0 | AI14: ACTIVO | AJ14: Fatima Amoretti Arteaga | AK14: fatima.amoretti.ceplan@gmail.com | AL14: =IFERROR(VLOOKUP(tbl_ues[[#This Row],[Id_UE]],'[1]Directorio v.02'!$H$3:$U$3089,11,FALSE),"") -> Milagros Esperanza Guerrero Barrera | AM14: =IFERROR(VLOOKUP(tbl_ues[[#This Row],[Id_UE]],'[1]Directorio v.02'!$H$3:$U$3089,12,FALSE),"") -> Jefe de la Oficina de Planeamiento y Presupuesto | AN14: =IFERROR(VLOOKUP(tbl_ues[[#This Row],[Id_UE]],'[1]Directorio v.02'!$H$3:$U$3089,13,FALSE),"") -> 962826260 | AO14: =IFERROR(VLOOKUP(tbl_ues[[#This Row],[Id_UE]],'[1]Directorio v.02'!$H$3:$U$3089,14,FALSE),"") -> milagros.guerrero@perucompras.gob.pe | AP14: =VLOOKUP(H14,#REF!,7,0) -> #REF! | AQ14: =VLOOKUP(H14,#REF!,9,0) -> #REF! | AR14: =VLOOKUP(H14,#REF!,15,0) -> #REF! | AS14: =VLOOKUP(H14,#REF!,16,0) -> #REF! | AT14: =VLOOKUP(H14,#REF!,17,0) -> #REF! | AU14: =VLOOKUP(H14,#REF!,18,0) -> #REF! | AV14: =VLOOKUP(H14,#REF!,19,0) -> #REF! | AW14: =VLOOKUP(H14,#REF!,20,0) -> #REF! | AX14: =VLOOKUP(H14,#REF!,22,0) -> #REF! | AY14: =VLOOKUP(H14,#REF!,23,0) -> #REF! | AZ14: =VLOOKUP(H14,#REF!,24,0) -> #REF! | BA14: =VLOOKUP(H14,#REF!,25,0) -> #REF! | BB14: =VLOOKUP(H14,#REF!,26,0) -> #REF! | BC14: =VLOOKUP(H14,#REF!,27,0) -> #REF! | BD14: =VLOOKUP(H14,#REF!,29,0) -> #REF! | BE14: =VLOOKUP(H14,#REF!,30,0) -> #REF! | BF14: =VLOOKUP(H14,#REF!,31,0) -> #REF! | BG14: =VLOOKUP(H14,#REF!,32,0) -> #REF! | BH14: =VLOOKUP(H14,#REF!,33,0) -> #REF! | BI14: =VLOOKUP(H14,#REF!,34,0) -> #REF! | BJ14: =VLOOKUP(H14,#REF!,36,0) -> #REF! | BK14: =VLOOKUP(H14,#REF!,37,0) -> #REF! | BL14: =VLOOKUP(H14,#REF!,44,0) -> #REF! | BM14: =VLOOKUP(H14,#REF!,45,0) -> #REF! | BN14: =VLOOKUP(H14,#REF!,46,0) -> #REF! | BO14: =VLOOKUP(H14,#REF!,47,0) -> #REF! | BP14: =VLOOKUP(H14,#REF!,48,0) -> #REF!
A15: Gobierno nacional | B15: Poder Ejecutivo | C15: E | D15: 35 | E15: COMERCIO EXTERIOR Y TURISMO | F15: 180 | G15: CENTRO DE FORMACION EN TURISMO | H15: 162 | I15: CENTRO DE FORMACION EN TURISMO | J15: 15 | K15: LIMA | L15: 1 | M15: LIMA | N15: 4 | O15: BARRANCO | Q15: S | R15: S | W15: =IFERROR(VLOOKUP(H15,'IT PEI'!$X$2:$X$5647,1,0),"...") -> 162 | X15: =_xlfn.XLOOKUP(H15,'IT PEI'!X$2:X$5647,'IT PEI'!E$2:E$5647,"...",2,-1) -> 2026-2030 | Y15: =_xlfn.XLOOKUP(H15,'IT PEI'!X$2:X$5647,'IT PEI'!G$2:G$5647,"...",2,-1) -> FORMULADO | Z15: =_xlfn.XLOOKUP(H15,'IT PEI'!X$2:X$5647,'IT PEI'!F$2:F$5647,"...",2,-1) -> SI | AA15: =_xlfn.XLOOKUP(H15,'IT PEI'!X$2:X$5647,'IT PEI'!H$2:H$5647,"...",2,-1) -> EMITIDO | AB15: =_xlfn.XLOOKUP(H15,'IT PEI'!X$2:X$5647,'IT PEI'!O$2:O$5647,"...",2,-1) -> 2026-0000087 | AC15: =_xlfn.XLOOKUP(H15,'IT PEI'!X$2:X$5647,'IT PEI'!P$2:P$5647,"...",2,-1) -> 46030 | AD15: =_xlfn.XLOOKUP(H15,'IT PEI'!X$2:X$5647,'IT PEI'!Q$2:Q$5647,"...",2,-1) -> 000004-2026-CEPLAN-DNCPPEI | AE15: =IF(COUNTIF(X15, "*" & "2030" & "*")>0, "SI", "No" ) -> SI | AF15: =IF(COUNTIF(X15, "*" & "2030" & "*")>0, 1, 0 ) -> 1 | AG15: =IF(COUNTIF(X15, "*" & "2030" & "*")>0, 0, 1 ) -> 0 | AH15: =IF(AND(AA15="En Proceso",AE15="Si"),1,0) -> 0 | AI15: ACTIVO | AJ15: Marco Condori Lozano | AK15: mcondori@ceplan.gob.pe | AL15: =IFERROR(VLOOKUP(tbl_ues[[#This Row],[Id_UE]],'[1]Directorio v.02'!$H$3:$U$3089,11,FALSE),"") -> Mijail Alva Muñoz | AM15: =IFERROR(VLOOKUP(tbl_ues[[#This Row],[Id_UE]],'[1]Directorio v.02'!$H$3:$U$3089,12,FALSE),"") -> Jefe (E ) de la Unidad de Planeamiento y Desarrollo | AN15: =IFERROR(VLOOKUP(tbl_ues[[#This Row],[Id_UE]],'[1]Directorio v.02'!$H$3:$U$3089,13,FALSE),"") -> 956-480-240 | AO15: =IFERROR(VLOOKUP(tbl_ues[[#This Row],[Id_UE]],'[1]Directorio v.02'!$H$3:$U$3089,14,FALSE),"") -> malva@cenfotur.edu.pe | AP15: =VLOOKUP(H15,#REF!,7,0) -> #REF! | AQ15: =VLOOKUP(H15,#REF!,9,0) -> #REF! | AR15: =VLOOKUP(H15,#REF!,15,0) -> #REF! | AS15: =VLOOKUP(H15,#REF!,16,0) -> #REF! | AT15: =VLOOKUP(H15,#REF!,17,0) -> #REF! | AU15: =VLOOKUP(H15,#REF!,18,0) -> #REF! | AV15: =VLOOKUP(H15,#REF!,19,0) -> #REF! | AW15: =VLOOKUP(H15,#REF!,20,0) -> #REF! | AX15: =VLOOKUP(H15,#REF!,22,0) -> #REF! | AY15: =VLOOKUP(H15,#REF!,23,0) -> #REF! | AZ15: =VLOOKUP(H15,#REF!,24,0) -> #REF! | BA15: =VLOOKUP(H15,#REF!,25,0) -> #REF! | BB15: =VLOOKUP(H15,#REF!,26,0) -> #REF! | BC15: =VLOOKUP(H15,#REF!,27,0) -> #REF! | BD15: =VLOOKUP(H15,#REF!,29,0) -> #REF! | BE15: =VLOOKUP(H15,#REF!,30,0) -> #REF! | BF15: =VLOOKUP(H15,#REF!,31,0) -> #REF! | BG15: =VLOOKUP(H15,#REF!,32,0) -> #REF! | BH15: =VLOOKUP(H15,#REF!,33,0) -> #REF! | BI15: =VLOOKUP(H15,#REF!,34,0) -> #REF! | BJ15: =VLOOKUP(H15,#REF!,36,0) -> #REF! | BK15: =VLOOKUP(H15,#REF!,37,0) -> #REF! | BL15: =VLOOKUP(H15,#REF!,44,0) -> #REF! | BM15: =VLOOKUP(H15,#REF!,45,0) -> #REF! | BN15: =VLOOKUP(H15,#REF!,46,0) -> #REF! | BO15: =VLOOKUP(H15,#REF!,47,0) -> #REF! | BP15: =VLOOKUP(H15,#REF!,48,0) -> #REF!
A16: Gobierno nacional | B16: Poder Ejecutivo | C16: E | D16: 26 | E16: DEFENSA | F16: 25 | G16: CENTRO NACIONAL DE ESTIMACION, PREVENCION Y REDUCCION DEL RIESGO DE DESASTRES - CENEPRED | H16: 1410 | I16: CENTRO NAC. DE ESTIMACION, PREVENCION Y REDUCCION DE RIESGOS DE DESASTRES- CENEPRED | J16: 15 | K16: LIMA | L16: 1 | M16: LIMA | N16: 31 | O16: SAN ISIDRO | Q16: S | R16: S | W16: =IFERROR(VLOOKUP(H16,'IT PEI'!$X$2:$X$5647,1,0),"...") -> 1410 | X16: =_xlfn.XLOOKUP(H16,'IT PEI'!X$2:X$5647,'IT PEI'!E$2:E$5647,"...",2,-1) -> 2025-2030 | Y16: =_xlfn.XLOOKUP(H16,'IT PEI'!X$2:X$5647,'IT PEI'!G$2:G$5647,"...",2,-1) -> FORMULADO | Z16: =_xlfn.XLOOKUP(H16,'IT PEI'!X$2:X$5647,'IT PEI'!F$2:F$5647,"...",2,-1) -> SI | AA16: =_xlfn.XLOOKUP(H16,'IT PEI'!X$2:X$5647,'IT PEI'!H$2:H$5647,"...",2,-1) -> EMITIDO | AB16: =_xlfn.XLOOKUP(H16,'IT PEI'!X$2:X$5647,'IT PEI'!O$2:O$5647,"...",2,-1) -> 2025-0000973 | AC16: =_xlfn.XLOOKUP(H16,'IT PEI'!X$2:X$5647,'IT PEI'!P$2:P$5647,"...",2,-1) -> 45744 | AD16: =_xlfn.XLOOKUP(H16,'IT PEI'!X$2:X$5647,'IT PEI'!Q$2:Q$5647,"...",2,-1) -> 000102-2025-DNCPPEI | AE16: =IF(COUNTIF(X16, "*" & "2030" & "*")>0, "SI", "No" ) -> SI | AF16: =IF(COUNTIF(X16, "*" & "2030" & "*")>0, 1, 0 ) -> 1 | AG16: =IF(COUNTIF(X16, "*" & "2030" & "*")>0, 0, 1 ) -> 0 | AH16: =IF(AND(AA16="En Proceso",AE16="Si"),1,0) -> 0 | AI16: ACTIVO | AJ16: Leidy Cayotopa Mesones | AK16: leidy.cayotopa.ceplan@gmail.com | AL16: =IFERROR(VLOOKUP(tbl_ues[[#This Row],[Id_UE]],'[1]Directorio v.02'!$H$3:$U$3089,11,FALSE),"") -> Miguel Angeles Chuquiruna | AM16: =IFERROR(VLOOKUP(tbl_ues[[#This Row],[Id_UE]],'[1]Directorio v.02'!$H$3:$U$3089,12,FALSE),"") -> Jefe de Planeamiento y Presupuesto | AN16: =IFERROR(VLOOKUP(tbl_ues[[#This Row],[Id_UE]],'[1]Directorio v.02'!$H$3:$U$3089,13,FALSE),"") -> 201-3550 – Anexo 155 | AO16: =IFERROR(VLOOKUP(tbl_ues[[#This Row],[Id_UE]],'[1]Directorio v.02'!$H$3:$U$3089,14,FALSE),"") -> mchuquiruna@cenepred.gob.pe | AP16: =VLOOKUP(H16,#REF!,7,0) -> #REF! | AQ16: =VLOOKUP(H16,#REF!,9,0) -> #REF! | AR16: =VLOOKUP(H16,#REF!,15,0) -> #REF! | AS16: =VLOOKUP(H16,#REF!,16,0) -> #REF! | AT16: =VLOOKUP(H16,#REF!,17,0) -> #REF! | AU16: =VLOOKUP(H16,#REF!,18,0) -> #REF! | AV16: =VLOOKUP(H16,#REF!,19,0) -> #REF! | AW16: =VLOOKUP(H16,#REF!,20,0) -> #REF! | AX16: =VLOOKUP(H16,#REF!,22,0) -> #REF! | AY16: =VLOOKUP(H16,#REF!,23,0) -> #REF! | AZ16: =VLOOKUP(H16,#REF!,24,0) -> #REF! | BA16: =VLOOKUP(H16,#REF!,25,0) -> #REF! | BB16: =VLOOKUP(H16,#REF!,26,0) -> #REF! | BC16: =VLOOKUP(H16,#REF!,27,0) -> #REF! | BD16: =VLOOKUP(H16,#REF!,29,0) -> #REF! | BE16: =VLOOKUP(H16,#REF!,30,0) -> #REF! | BF16: =VLOOKUP(H16,#REF!,31,0) -> #REF! | BG16: =VLOOKUP(H16,#REF!,32,0) -> #REF! | BH16: =VLOOKUP(H16,#REF!,33,0) -> #REF! | BI16: =VLOOKUP(H16,#REF!,34,0) -> #REF! | BJ16: =VLOOKUP(H16,#REF!,36,0) -> #REF! | BK16: =VLOOKUP(H16,#REF!,37,0) -> #REF! | BL16: =VLOOKUP(H16,#REF!,44,0) -> #REF! | BM16: =VLOOKUP(H16,#REF!,45,0) -> #REF! | BN16: =VLOOKUP(H16,#REF!,46,0) -> #REF! | BO16: =VLOOKUP(H16,#REF!,47,0) -> #REF! | BP16: =VLOOKUP(H16,#REF!,48,0) -> #REF!
A17: Gobierno nacional | B17: Poder Ejecutivo | C17: E | D17: 1 | E17: PRESIDENCIA CONSEJO MINISTROS | F17: 16 | G17: CENTRO NACIONAL DE PLANEAMIENTO ESTRATEGICO - CEPLAN | H17: 1256 | I17: CENTRO NACIONAL DE PLANEAMIENTO ESTRATEGICO- CEPLAN | J17: 15 | K17: LIMA | L17: 1 | M17: LIMA | N17: 31 | O17: SAN ISIDRO | Q17: S | R17: S | W17: =IFERROR(VLOOKUP(H17,'IT PEI'!$X$2:$X$5647,1,0),"...") -> 1256 | X17: =_xlfn.XLOOKUP(H17,'IT PEI'!X$2:X$5647,'IT PEI'!E$2:E$5647,"...",2,-1) -> 2025-2030 | Y17: =_xlfn.XLOOKUP(H17,'IT PEI'!X$2:X$5647,'IT PEI'!G$2:G$5647,"...",2,-1) -> FORMULADO | Z17: =_xlfn.XLOOKUP(H17,'IT PEI'!X$2:X$5647,'IT PEI'!F$2:F$5647,"...",2,-1) -> SI | AA17: =_xlfn.XLOOKUP(H17,'IT PEI'!X$2:X$5647,'IT PEI'!H$2:H$5647,"...",2,-1) -> EMITIDO | AB17: =_xlfn.XLOOKUP(H17,'IT PEI'!X$2:X$5647,'IT PEI'!O$2:O$5647,"...",2,-1) -> 2025-0000098 | AC17: =_xlfn.XLOOKUP(H17,'IT PEI'!X$2:X$5647,'IT PEI'!P$2:P$5647,"...",2,-1) -> 45686 | AD17: =_xlfn.XLOOKUP(H17,'IT PEI'!X$2:X$5647,'IT PEI'!Q$2:Q$5647,"...",2,-1) -> 000029-2025-CEPLAN-DNCPPEI | AE17: =IF(COUNTIF(X17, "*" & "2030" & "*")>0, "SI", "No" ) -> SI | AF17: =IF(COUNTIF(X17, "*" & "2030" & "*")>0, 1, 0 ) -> 1 | AG17: =IF(COUNTIF(X17, "*" & "2030" & "*")>0, 0, 1 ) -> 0 | AH17: =IF(AND(AA17="En Proceso",AE17="Si"),1,0) -> 0 | AI17: ACTIVO | AJ17: Claudia Melendez Mauricio | AK17: claudia.melendez.ceplan@gmail.com | AL17: =IFERROR(VLOOKUP(tbl_ues[[#This Row],[Id_UE]],'[1]Directorio v.02'!$H$3:$U$3089,11,FALSE),"") -> Antonio Mori Kuriyama | AM17: =IFERROR(VLOOKUP(tbl_ues[[#This Row],[Id_UE]],'[1]Directorio v.02'!$H$3:$U$3089,12,FALSE),"") -> Jefe de la Oficina de Planeamiento y Presupuesto | AN17: =IFERROR(VLOOKUP(tbl_ues[[#This Row],[Id_UE]],'[1]Directorio v.02'!$H$3:$U$3089,13,FALSE),"") -> 211-7800 / 1901 | AO17: =IFERROR(VLOOKUP(tbl_ues[[#This Row],[Id_UE]],'[1]Directorio v.02'!$H$3:$U$3089,14,FALSE),"") -> amori@ceplan.gob.pe | AP17: =VLOOKUP(H17,#REF!,7,0) -> #REF! | AQ17: =VLOOKUP(H17,#REF!,9,0) -> #REF! | AR17: =VLOOKUP(H17,#REF!,15,0) -> #REF! | AS17: =VLOOKUP(H17,#REF!,16,0) -> #REF! | AT17: =VLOOKUP(H17,#REF!,17,0) -> #REF! | AU17: =VLOOKUP(H17,#REF!,18,0) -> #REF! | AV17: =VLOOKUP(H17,#REF!,19,0) -> #REF! | AW17: =VLOOKUP(H17,#REF!,20,0) -> #REF! | AX17: =VLOOKUP(H17,#REF!,22,0) -> #REF! | AY17: =VLOOKUP(H17,#REF!,23,0) -> #REF! | AZ17: =VLOOKUP(H17,#REF!,24,0) -> #REF! | BA17: =VLOOKUP(H17,#REF!,25,0) -> #REF! | BB17: =VLOOKUP(H17,#REF!,26,0) -> #REF! | BC17: =VLOOKUP(H17,#REF!,27,0) -> #REF! | BD17: =VLOOKUP(H17,#REF!,29,0) -> #REF! | BE17: =VLOOKUP(H17,#REF!,30,0) -> #REF! | BF17: =VLOOKUP(H17,#REF!,31,0) -> #REF! | BG17: =VLOOKUP(H17,#REF!,32,0) -> #REF! | BH17: =VLOOKUP(H17,#REF!,33,0) -> #REF! | BI17: =VLOOKUP(H17,#REF!,34,0) -> #REF! | BJ17: =VLOOKUP(H17,#REF!,36,0) -> #REF! | BK17: =VLOOKUP(H17,#REF!,37,0) -> #REF! | BL17: =VLOOKUP(H17,#REF!,44,0) -> #REF! | BM17: =VLOOKUP(H17,#REF!,45,0) -> #REF! | BN17: =VLOOKUP(H17,#REF!,46,0) -> #REF! | BO17: =VLOOKUP(H17,#REF!,47,0) -> #REF! | BP17: =VLOOKUP(H17,#REF!,48,0) -> #REF!
A18: Gobierno nacional | B18: Poder Ejecutivo | C18: E | D18: 10 | E18: EDUCACION | F18: 111 | G18: CENTRO VACACIONAL HUAMPANI | H18: 1276 | I18: CENTRO VACACIONAL HUAMPANI | J18: 15 | K18: LIMA | L18: 1 | M18: LIMA | N18: 7 | O18: CHACLACAYO | Q18: S | R18: S | W18: =IFERROR(VLOOKUP(H18,'IT PEI'!$X$2:$X$5647,1,0),"...") -> 1276 | X18: =_xlfn.XLOOKUP(H18,'IT PEI'!X$2:X$5647,'IT PEI'!E$2:E$5647,"...",2,-1) -> 2025-2030 | Y18: =_xlfn.XLOOKUP(H18,'IT PEI'!X$2:X$5647,'IT PEI'!G$2:G$5647,"...",2,-1) -> FORMULADO | Z18: =_xlfn.XLOOKUP(H18,'IT PEI'!X$2:X$5647,'IT PEI'!F$2:F$5647,"...",2,-1) -> SI | AA18: =_xlfn.XLOOKUP(H18,'IT PEI'!X$2:X$5647,'IT PEI'!H$2:H$5647,"...",2,-1) -> EMITIDO | AB18: =_xlfn.XLOOKUP(H18,'IT PEI'!X$2:X$5647,'IT PEI'!O$2:O$5647,"...",2,-1) -> 2025-0000385 | AC18: =_xlfn.XLOOKUP(H18,'IT PEI'!X$2:X$5647,'IT PEI'!P$2:P$5647,"...",2,-1) -> 45688 | AD18: =_xlfn.XLOOKUP(H18,'IT PEI'!X$2:X$5647,'IT PEI'!Q$2:Q$5647,"...",2,-1) -> 000044-2025-CEPLAN-DNCPPEI | AE18: =IF(COUNTIF(X18, "*" & "2030" & "*")>0, "SI", "No" ) -> SI | AF18: =IF(COUNTIF(X18, "*" & "2030" & "*")>0, 1, 0 ) -> 1 | AG18: =IF(COUNTIF(X18, "*" & "2030" & "*")>0, 0, 1 ) -> 0 | AH18: =IF(AND(AA18="En Proceso",AE18="Si"),1,0) -> 0 | AI18: ACTIVO | AJ18: Vilma Celestino Villafana | AK18: vcelestinov@gmail.com | AL18: =IFERROR(VLOOKUP(tbl_ues[[#This Row],[Id_UE]],'[1]Directorio v.02'!$H$3:$U$3089,11,FALSE),"") -> Marco Antonio Ccahuana de la Cruz | AM18: =IFERROR(VLOOKUP(tbl_ues[[#This Row],[Id_UE]],'[1]Directorio v.02'!$H$3:$U$3089,12,FALSE),"") -> Jefe de la Oficina de Planeamiento Estratégico y Presupuesto | AN18: =IFERROR(VLOOKUP(tbl_ues[[#This Row],[Id_UE]],'[1]Directorio v.02'!$H$3:$U$3089,13,FALSE),"") -> 981 330 211 | AO18: =IFERROR(VLOOKUP(tbl_ues[[#This Row],[Id_UE]],'[1]Directorio v.02'!$H$3:$U$3089,14,FALSE),"") -> mccahuana@huampani.gob.pe | AP18: =VLOOKUP(H18,#REF!,7,0) -> #REF! | AQ18: =VLOOKUP(H18,#REF!,9,0) -> #REF! | AR18: =VLOOKUP(H18,#REF!,15,0) -> #REF! | AS18: =VLOOKUP(H18,#REF!,16,0) -> #REF! | AT18: =VLOOKUP(H18,#REF!,17,0) -> #REF! | AU18: =VLOOKUP(H18,#REF!,18,0) -> #REF! | AV18: =VLOOKUP(H18,#REF!,19,0) -> #REF! | AW18: =VLOOKUP(H18,#REF!,20,0) -> #REF! | AX18: =VLOOKUP(H18,#REF!,22,0) -> #REF! | AY18: =VLOOKUP(H18,#REF!,23,0) -> #REF! | AZ18: =VLOOKUP(H18,#REF!,24,0) -> #REF! | BA18: =VLOOKUP(H18,#REF!,25,0) -> #REF! | BB18: =VLOOKUP(H18,#REF!,26,0) -> #REF! | BC18: =VLOOKUP(H18,#REF!,27,0) -> #REF! | BD18: =VLOOKUP(H18,#REF!,29,0) -> #REF! | BE18: =VLOOKUP(H18,#REF!,30,0) -> #REF! | BF18: =VLOOKUP(H18,#REF!,31,0) -> #REF! | BG18: =VLOOKUP(H18,#REF!,32,0) -> #REF! | BH18: =VLOOKUP(H18,#REF!,33,0) -> #REF! | BI18: =VLOOKUP(H18,#REF!,34,0) -> #REF! | BJ18: =VLOOKUP(H18,#REF!,36,0) -> #REF! | BK18: =VLOOKUP(H18,#REF!,37,0) -> #REF! | BL18: =VLOOKUP(H18,#REF!,44,0) -> #REF! | BM18: =VLOOKUP(H18,#REF!,45,0) -> #REF! | BN18: =VLOOKUP(H18,#REF!,46,0) -> #REF! | BO18: =VLOOKUP(H18,#REF!,47,0) -> #REF! | BP18: =VLOOKUP(H18,#REF!,48,0) -> #REF!
A19: Gobierno nacional | B19: Poder Ejecutivo | C19: E | D19: 35 | E19: COMERCIO EXTERIOR Y TURISMO | F19: 8 | G19: COMISION DE PROMOCION DEL PERU PARA LA EXPORTACION Y EL TURISMO - PROMPERU | H19: 11 | I19: COMISION DE PROMOCION DEL PERU PARA LA EXPORTACION Y EL TURISMO - PROMPERU | J19: 15 | K19: LIMA | L19: 1 | M19: LIMA | N19: 31 | O19: SAN ISIDRO | Q19: S | R19: S | W19: =IFERROR(VLOOKUP(H19,'IT PEI'!$X$2:$X$5647,1,0),"...") -> 11 | X19: =_xlfn.XLOOKUP(H19,'IT PEI'!X$2:X$5647,'IT PEI'!E$2:E$5647,"...",2,-1) -> 2026-2030 | Y19: =_xlfn.XLOOKUP(H19,'IT PEI'!X$2:X$5647,'IT PEI'!G$2:G$5647,"...",2,-1) -> FORMULADO | Z19: =_xlfn.XLOOKUP(H19,'IT PEI'!X$2:X$5647,'IT PEI'!F$2:F$5647,"...",2,-1) -> SI | AA19: =_xlfn.XLOOKUP(H19,'IT PEI'!X$2:X$5647,'IT PEI'!H$2:H$5647,"...",2,-1) -> EN PROCESO | AB19: =_xlfn.XLOOKUP(H19,'IT PEI'!X$2:X$5647,'IT PEI'!O$2:O$5647,"...",2,-1) -> 0 | AC19: =_xlfn.XLOOKUP(H19,'IT PEI'!X$2:X$5647,'IT PEI'!P$2:P$5647,"...",2,-1) -> 0 | AD19: =_xlfn.XLOOKUP(H19,'IT PEI'!X$2:X$5647,'IT PEI'!Q$2:Q$5647,"...",2,-1) -> 0 | AE19: =IF(COUNTIF(X19, "*" & "2030" & "*")>0, "SI", "No" ) -> SI | AF19: =IF(COUNTIF(X19, "*" & "2030" & "*")>0, 1, 0 ) -> 1 | AG19: =IF(COUNTIF(X19, "*" & "2030" & "*")>0, 0, 1 ) -> 0 | AH19: =IF(AND(AA19="En Proceso",AE19="Si"),1,0) -> 1 | AI19: ACTIVO | AJ19: Marco Condori Lozano | AK19: mcondori@ceplan.gob.pe | AL19: =IFERROR(VLOOKUP(tbl_ues[[#This Row],[Id_UE]],'[1]Directorio v.02'!$H$3:$U$3089,11,FALSE),"") -> Ángel Wilder Navarro Díaz | AM19: =IFERROR(VLOOKUP(tbl_ues[[#This Row],[Id_UE]],'[1]Directorio v.02'!$H$3:$U$3089,12,FALSE),"") -> Jefe de la Unidad de Planeamiento y Presupuesto | AN19: =IFERROR(VLOOKUP(tbl_ues[[#This Row],[Id_UE]],'[1]Directorio v.02'!$H$3:$U$3089,13,FALSE),"") -> 616-7300 | AO19: =IFERROR(VLOOKUP(tbl_ues[[#This Row],[Id_UE]],'[1]Directorio v.02'!$H$3:$U$3089,14,FALSE),"") -> anavarro@promperu.gob.pe | AP19: =VLOOKUP(H19,#REF!,7,0) -> #REF! | AQ19: =VLOOKUP(H19,#REF!,9,0) -> #REF! | AR19: =VLOOKUP(H19,#REF!,15,0) -> #REF! | AS19: =VLOOKUP(H19,#REF!,16,0) -> #REF! | AT19: =VLOOKUP(H19,#REF!,17,0) -> #REF! | AU19: =VLOOKUP(H19,#REF!,18,0) -> #REF! | AV19: =VLOOKUP(H19,#REF!,19,0) -> #REF! | AW19: =VLOOKUP(H19,#REF!,20,0) -> #REF! | AX19: =VLOOKUP(H19,#REF!,22,0) -> #REF! | AY19: =VLOOKUP(H19,#REF!,23,0) -> #REF! | AZ19: =VLOOKUP(H19,#REF!,24,0) -> #REF! | BA19: =VLOOKUP(H19,#REF!,25,0) -> #REF! | BB19: =VLOOKUP(H19,#REF!,26,0) -> #REF! | BC19: =VLOOKUP(H19,#REF!,27,0) -> #REF! | BD19: =VLOOKUP(H19,#REF!,29,0) -> #REF! | BE19: =VLOOKUP(H19,#REF!,30,0) -> #REF! | BF19: =VLOOKUP(H19,#REF!,31,0) -> #REF! | BG19: =VLOOKUP(H19,#REF!,32,0) -> #REF! | BH19: =VLOOKUP(H19,#REF!,33,0) -> #REF! | BI19: =VLOOKUP(H19,#REF!,34,0) -> #REF! | BJ19: =VLOOKUP(H19,#REF!,36,0) -> #REF! | BK19: =VLOOKUP(H19,#REF!,37,0) -> #REF! | BL19: =VLOOKUP(H19,#REF!,44,0) -> #REF! | BM19: =VLOOKUP(H19,#REF!,45,0) -> #REF! | BN19: =VLOOKUP(H19,#REF!,46,0) -> #REF! | BO19: =VLOOKUP(H19,#REF!,47,0) -> #REF! | BP19: =VLOOKUP(H19,#REF!,48,0) -> #REF!
A20: Gobierno nacional | B20: Poder Ejecutivo | C20: E | D20: 1 | E20: PRESIDENCIA CONSEJO MINISTROS | F20: 12 | G20: COMISION NACIONAL PARA EL DESARROLLO Y VIDA SIN DROGAS - DEVIDA | H20: 1064 | I20: COMISION NAC. PARA EL DESARROLLO Y VIDA SIN DROGAS - DEVIDA | J20: 15 | K20: LIMA | L20: 1 | M20: LIMA | N20: 1 | O20: LIMA | Q20: S | R20: S | W20: =IFERROR(VLOOKUP(H20,'IT PEI'!$X$2:$X$5647,1,0),"...") -> 1064 | X20: =_xlfn.XLOOKUP(H20,'IT PEI'!X$2:X$5647,'IT PEI'!E$2:E$5647,"...",2,-1) -> 2025-2030 | Y20: =_xlfn.XLOOKUP(H20,'IT PEI'!X$2:X$5647,'IT PEI'!G$2:G$5647,"...",2,-1) -> FORMULADO | Z20: =_xlfn.XLOOKUP(H20,'IT PEI'!X$2:X$5647,'IT PEI'!F$2:F$5647,"...",2,-1) -> SI | AA20: =_xlfn.XLOOKUP(H20,'IT PEI'!X$2:X$5647,'IT PEI'!H$2:H$5647,"...",2,-1) -> EMITIDO | AB20: =_xlfn.XLOOKUP(H20,'IT PEI'!X$2:X$5647,'IT PEI'!O$2:O$5647,"...",2,-1) -> 2025-0000358 | AC20: =_xlfn.XLOOKUP(H20,'IT PEI'!X$2:X$5647,'IT PEI'!P$2:P$5647,"...",2,-1) -> 45687 | AD20: =_xlfn.XLOOKUP(H20,'IT PEI'!X$2:X$5647,'IT PEI'!Q$2:Q$5647,"...",2,-1) -> 000037-2025-CEPLAN-DNCPPEI | AE20: =IF(COUNTIF(X20, "*" & "2030" & "*")>0, "SI", "No" ) -> SI | AF20: =IF(COUNTIF(X20, "*" & "2030" & "*")>0, 1, 0 ) -> 1 | AG20: =IF(COUNTIF(X20, "*" & "2030" & "*")>0, 0, 1 ) -> 0 | AH20: =IF(AND(AA20="En Proceso",AE20="Si"),1,0) -> 0 | AI20: ACTIVO | AJ20: Claudia Melendez Mauricio | AK20: claudia.melendez.ceplan@gmail.com | AL20: =IFERROR(VLOOKUP(tbl_ues[[#This Row],[Id_UE]],'[1]Directorio v.02'!$H$3:$U$3089,11,FALSE),"") -> Edson Joel Delgado Rodríguez | AM20: =IFERROR(VLOOKUP(tbl_ues[[#This Row],[Id_UE]],'[1]Directorio v.02'!$H$3:$U$3089,12,FALSE),"") -> Jefe de la Oficina de Planeamiento y Presupuesto | AN20: =IFERROR(VLOOKUP(tbl_ues[[#This Row],[Id_UE]],'[1]Directorio v.02'!$H$3:$U$3089,13,FALSE),"") -> 924389504 | AO20: =IFERROR(VLOOKUP(tbl_ues[[#This Row],[Id_UE]],'[1]Directorio v.02'!$H$3:$U$3089,14,FALSE),"") -> edelgado@devida.gob.pe | AP20: =VLOOKUP(H20,#REF!,7,0) -> #REF! | AQ20: =VLOOKUP(H20,#REF!,9,0) -> #REF! | AR20: =VLOOKUP(H20,#REF!,15,0) -> #REF! | AS20: =VLOOKUP(H20,#REF!,16,0) -> #REF! | AT20: =VLOOKUP(H20,#REF!,17,0) -> #REF! | AU20: =VLOOKUP(H20,#REF!,18,0) -> #REF! | AV20: =VLOOKUP(H20,#REF!,19,0) -> #REF! | AW20: =VLOOKUP(H20,#REF!,20,0) -> #REF! | AX20: =VLOOKUP(H20,#REF!,22,0) -> #REF! | AY20: =VLOOKUP(H20,#REF!,23,0) -> #REF! | AZ20: =VLOOKUP(H20,#REF!,24,0) -> #REF! | BA20: =VLOOKUP(H20,#REF!,25,0) -> #REF! | BB20: =VLOOKUP(H20,#REF!,26,0) -> #REF! | BC20: =VLOOKUP(H20,#REF!,27,0) -> #REF! | BD20: =VLOOKUP(H20,#REF!,29,0) -> #REF! | BE20: =VLOOKUP(H20,#REF!,30,0) -> #REF! | BF20: =VLOOKUP(H20,#REF!,31,0) -> #REF! | BG20: =VLOOKUP(H20,#REF!,32,0) -> #REF! | BH20: =VLOOKUP(H20,#REF!,33,0) -> #REF! | BI20: =VLOOKUP(H20,#REF!,34,0) -> #REF! | BJ20: =VLOOKUP(H20,#REF!,36,0) -> #REF! | BK20: =VLOOKUP(H20,#REF!,37,0) -> #REF! | BL20: =VLOOKUP(H20,#REF!,44,0) -> #REF! | BM20: =VLOOKUP(H20,#REF!,45,0) -> #REF! | BN20: =VLOOKUP(H20,#REF!,46,0) -> #REF! | BO20: =VLOOKUP(H20,#REF!,47,0) -> #REF! | BP20: =VLOOKUP(H20,#REF!,48,0) -> #REF!
A21: Gobierno nacional | B21: Poder Ejecutivo | C21: E | D21: 1 | E21: PRESIDENCIA CONSEJO MINISTROS | F21: 12 | G21: COMISION NACIONAL PARA EL DESARROLLO Y VIDA SIN DROGAS - DEVIDA | H21: 1715 | I21: UNIDAD DE GESTION DE APOYO AL DESARROLLO SOSTENIBLE DEL VRAEM | J21: 15 | K21: LIMA | L21: 1 | M21: LIMA | N21: 1 | O21: LIMA | R21: S | W21: =IFERROR(VLOOKUP(H21,'IT PEI'!$X$2:$X$5647,1,0),"...") -> ... | X21: =_xlfn.XLOOKUP(H21,'IT PEI'!X$2:X$5647,'IT PEI'!E$2:E$5647,"...",2,-1) -> ... | Y21: =_xlfn.XLOOKUP(H21,'IT PEI'!X$2:X$5647,'IT PEI'!G$2:G$5647,"...",2,-1) -> ... | Z21: =_xlfn.XLOOKUP(H21,'IT PEI'!X$2:X$5647,'IT PEI'!F$2:F$5647,"...",2,-1) -> ... | AA21: =_xlfn.XLOOKUP(H21,'IT PEI'!X$2:X$5647,'IT PEI'!H$2:H$5647,"...",2,-1) -> ... | AB21: =_xlfn.XLOOKUP(H21,'IT PEI'!X$2:X$5647,'IT PEI'!O$2:O$5647,"...",2,-1) -> ... | AC21: =_xlfn.XLOOKUP(H21,'IT PEI'!X$2:X$5647,'IT PEI'!P$2:P$5647,"...",2,-1) -> ... | AD21: =_xlfn.XLOOKUP(H21,'IT PEI'!X$2:X$5647,'IT PEI'!Q$2:Q$5647,"...",2,-1) -> ... | AE21: =IF(COUNTIF(X21, "*" & "2030" & "*")>0, "SI", "No" ) -> No | AF21: =IF(COUNTIF(X21, "*" & "2030" & "*")>0, 1, 0 ) -> 0 | AG21: =IF(COUNTIF(X21, "*" & "2030" & "*")>0, 0, 1 ) -> 1 | AH21: =IF(AND(AA21="En Proceso",AE21="Si"),1,0) -> 0 | AI21: ACTIVO | AJ21: Claudia Melendez Mauricio | AK21: claudia.melendez.ceplan@gmail.com | AL21: =IFERROR(VLOOKUP(tbl_ues[[#This Row],[Id_UE]],'[1]Directorio v.02'!$H$3:$U$3089,11,FALSE),"") -> General Edgar Alberto Gonzales Espinoza | AM21: =IFERROR(VLOOKUP(tbl_ues[[#This Row],[Id_UE]],'[1]Directorio v.02'!$H$3:$U$3089,12,FALSE),"") -> Jefe | AN21: =IFERROR(VLOOKUP(tbl_ues[[#This Row],[Id_UE]],'[1]Directorio v.02'!$H$3:$U$3089,13,FALSE),"") -> 084 816926 | AO21: =IFERROR(VLOOKUP(tbl_ues[[#This Row],[Id_UE]],'[1]Directorio v.02'!$H$3:$U$3089,14,FALSE),"") -> fpvraem.ceopol@pnp.gob.pe | AP21: =VLOOKUP(H21,#REF!,7,0) -> #REF! | AQ21: =VLOOKUP(H21,#REF!,9,0) -> #REF! | AR21: =VLOOKUP(H21,#REF!,15,0) -> #REF! | AS21: =VLOOKUP(H21,#REF!,16,0) -> #REF! | AT21: =VLOOKUP(H21,#REF!,17,0) -> #REF! | AU21: =VLOOKUP(H21,#REF!,18,0) -> #REF! | AV21: =VLOOKUP(H21,#REF!,19,0) -> #REF! | AW21: =VLOOKUP(H21,#REF!,20,0) -> #REF! | AX21: =VLOOKUP(H21,#REF!,22,0) -> #REF! | AY21: =VLOOKUP(H21,#REF!,23,0) -> #REF! | AZ21: =VLOOKUP(H21,#REF!,24,0) -> #REF! | BA21: =VLOOKUP(H21,#REF!,25,0) -> #REF! | BB21: =VLOOKUP(H21,#REF!,26,0) -> #REF! | BC21: =VLOOKUP(H21,#REF!,27,0) -> #REF! | BD21: =VLOOKUP(H21,#REF!,29,0) -> #REF! | BE21: =VLOOKUP(H21,#REF!,30,0) -> #REF! | BF21: =VLOOKUP(H21,#REF!,31,0) -> #REF! | BG21: =VLOOKUP(H21,#REF!,32,0) -> #REF! | BH21: =VLOOKUP(H21,#REF!,33,0) -> #REF! | BI21: =VLOOKUP(H21,#REF!,34,0) -> #REF! | BJ21: =VLOOKUP(H21,#REF!,36,0) -> #REF! | BK21: =VLOOKUP(H21,#REF!,37,0) -> #REF! | BL21: =VLOOKUP(H21,#REF!,44,0) -> #REF! | BM21: =VLOOKUP(H21,#REF!,45,0) -> #REF! | BN21: =VLOOKUP(H21,#REF!,46,0) -> #REF! | BO21: =VLOOKUP(H21,#REF!,47,0) -> #REF! | BP21: =VLOOKUP(H21,#REF!,48,0) -> #REF!
A22: Gobierno nacional | B22: OCA | C22: E | D22: 28 | E22: CONGRESO DE LA REPUBLICA | F22: 28 | G22: CONGRESO DE LA REPUBLICA | H22: 477 | I22: CONGRESO DE LA REPUBLICA | J22: 15 | K22: LIMA | L22: 1 | M22: LIMA | N22: 1 | O22: LIMA | Q22: S | R22: S | V22: OCA | W22: =IFERROR(VLOOKUP(H22,'IT PEI'!$X$2:$X$5647,1,0),"...") -> 477 | X22: =_xlfn.XLOOKUP(H22,'IT PEI'!X$2:X$5647,'IT PEI'!E$2:E$5647,"...",2,-1) -> 2025-2030 | Y22: =_xlfn.XLOOKUP(H22,'IT PEI'!X$2:X$5647,'IT PEI'!G$2:G$5647,"...",2,-1) -> FORMULADO | Z22: =_xlfn.XLOOKUP(H22,'IT PEI'!X$2:X$5647,'IT PEI'!F$2:F$5647,"...",2,-1) -> SI | AA22: =_xlfn.XLOOKUP(H22,'IT PEI'!X$2:X$5647,'IT PEI'!H$2:H$5647,"...",2,-1) -> EN PROCESO | AB22: =_xlfn.XLOOKUP(H22,'IT PEI'!X$2:X$5647,'IT PEI'!O$2:O$5647,"...",2,-1) -> 0 | AC22: =_xlfn.XLOOKUP(H22,'IT PEI'!X$2:X$5647,'IT PEI'!P$2:P$5647,"...",2,-1) -> 0 | AD22: =_xlfn.XLOOKUP(H22,'IT PEI'!X$2:X$5647,'IT PEI'!Q$2:Q$5647,"...",2,-1) -> 0 | AE22: =IF(COUNTIF(X22, "*" & "2030" & "*")>0, "SI", "No" ) -> SI | AF22: =IF(COUNTIF(X22, "*" & "2030" & "*")>0, 1, 0 ) -> 1 | AG22: =IF(COUNTIF(X22, "*" & "2030" & "*")>0, 0, 1 ) -> 0 | AH22: =IF(AND(AA22="En Proceso",AE22="Si"),1,0) -> 1 | AI22: ACTIVO | AJ22: Addy López Peña | AK22: alopez@ceplan.gob.pe | AL22: =IFERROR(VLOOKUP(tbl_ues[[#This Row],[Id_UE]],'[1]Directorio v.02'!$H$3:$U$3089,11,FALSE),"") -> Hernán Landeo Cortijo | AM22: =IFERROR(VLOOKUP(tbl_ues[[#This Row],[Id_UE]],'[1]Directorio v.02'!$H$3:$U$3089,12,FALSE),"") -> Jefe del Área de Planeamiento | AN22: =IFERROR(VLOOKUP(tbl_ues[[#This Row],[Id_UE]],'[1]Directorio v.02'!$H$3:$U$3089,13,FALSE),"") -> 980677923 | AO22: =IFERROR(VLOOKUP(tbl_ues[[#This Row],[Id_UE]],'[1]Directorio v.02'!$H$3:$U$3089,14,FALSE),"") -> hlandeo@congreso.gob.pe | AP22: =VLOOKUP(H22,#REF!,7,0) -> #REF! | AQ22: =VLOOKUP(H22,#REF!,9,0) -> #REF! | AR22: =VLOOKUP(H22,#REF!,15,0) -> #REF! | AS22: =VLOOKUP(H22,#REF!,16,0) -> #REF! | AT22: =VLOOKUP(H22,#REF!,17,0) -> #REF! | AU22: =VLOOKUP(H22,#REF!,18,0) -> #REF! | AV22: =VLOOKUP(H22,#REF!,19,0) -> #REF! | AW22: =VLOOKUP(H22,#REF!,20,0) -> #REF! | AX22: =VLOOKUP(H22,#REF!,22,0) -> #REF! | AY22: =VLOOKUP(H22,#REF!,23,0) -> #REF! | AZ22: =VLOOKUP(H22,#REF!,24,0) -> #REF! | BA22: =VLOOKUP(H22,#REF!,25,0) -> #REF! | BB22: =VLOOKUP(H22,#REF!,26,0) -> #REF! | BC22: =VLOOKUP(H22,#REF!,27,0) -> #REF! | BD22: =VLOOKUP(H22,#REF!,29,0) -> #REF! | BE22: =VLOOKUP(H22,#REF!,30,0) -> #REF! | BF22: =VLOOKUP(H22,#REF!,31,0) -> #REF! | BG22: =VLOOKUP(H22,#REF!,32,0) -> #REF! | BH22: =VLOOKUP(H22,#REF!,33,0) -> #REF! | BI22: =VLOOKUP(H22,#REF!,34,0) -> #REF! | BJ22: =VLOOKUP(H22,#REF!,36,0) -> #REF! | BK22: =VLOOKUP(H22,#REF!,37,0) -> #REF! | BL22: =VLOOKUP(H22,#REF!,44,0) -> #REF! | BM22: =VLOOKUP(H22,#REF!,45,0) -> #REF! | BN22: =VLOOKUP(H22,#REF!,46,0) -> #REF! | BO22: =VLOOKUP(H22,#REF!,47,0) -> #REF! | BP22: =VLOOKUP(H22,#REF!,48,0) -> #REF!
A23: Gobierno nacional | B23: Poder Ejecutivo | C23: E | D23: 1 | E23: PRESIDENCIA CONSEJO MINISTROS | F23: 114 | G23: CONSEJO NACIONAL DE CIENCIA, TECNOLOGIA E INNOVACION TECNOLOGICA | H23: 1522 | I23: FONDO NACIONAL DE DESARROLLO CIENTIFICO, TECNOLOGICO Y DE INNOVACION TECNOLOGICA- FONDECYT | J23: 15 | K23: LIMA | L23: 1 | M23: LIMA | N23: 22 | O23: MIRAFLORES | R23: S | W23: =IFERROR(VLOOKUP(H23,'IT PEI'!$X$2:$X$5647,1,0),"...") -> ... | X23: =_xlfn.XLOOKUP(H23,'IT PEI'!X$2:X$5647,'IT PEI'!E$2:E$5647,"...",2,-1) -> ... | Y23: =_xlfn.XLOOKUP(H23,'IT PEI'!X$2:X$5647,'IT PEI'!G$2:G$5647,"...",2,-1) -> ... | Z23: =_xlfn.XLOOKUP(H23,'IT PEI'!X$2:X$5647,'IT PEI'!F$2:F$5647,"...",2,-1) -> ... | AA23: =_xlfn.XLOOKUP(H23,'IT PEI'!X$2:X$5647,'IT PEI'!H$2:H$5647,"...",2,-1) -> ... | AB23: =_xlfn.XLOOKUP(H23,'IT PEI'!X$2:X$5647,'IT PEI'!O$2:O$5647,"...",2,-1) -> ... | AC23: =_xlfn.XLOOKUP(H23,'IT PEI'!X$2:X$5647,'IT PEI'!P$2:P$5647,"...",2,-1) -> ... | AD23: =_xlfn.XLOOKUP(H23,'IT PEI'!X$2:X$5647,'IT PEI'!Q$2:Q$5647,"...",2,-1) -> ... | AE23: =IF(COUNTIF(X23, "*" & "2030" & "*")>0, "SI", "No" ) -> No | AF23: =IF(COUNTIF(X23, "*" & "2030" & "*")>0, 1, 0 ) -> 0 | AG23: =IF(COUNTIF(X23, "*" & "2030" & "*")>0, 0, 1 ) -> 1 | AH23: =IF(AND(AA23="En Proceso",AE23="Si"),1,0) -> 0 | AI23: INACTIVO | AJ23: Claudia Melendez Mauricio | AK23: claudia.melendez.ceplan@gmail.com | AL23: =IFERROR(VLOOKUP(tbl_ues[[#This Row],[Id_UE]],'[1]Directorio v.02'!$H$3:$U$3089,11,FALSE),"") | AM23: =IFERROR(VLOOKUP(tbl_ues[[#This Row],[Id_UE]],'[1]Directorio v.02'!$H$3:$U$3089,12,FALSE),"") | AN23: =IFERROR(VLOOKUP(tbl_ues[[#This Row],[Id_UE]],'[1]Directorio v.02'!$H$3:$U$3089,13,FALSE),"") | AO23: =IFERROR(VLOOKUP(tbl_ues[[#This Row],[Id_UE]],'[1]Directorio v.02'!$H$3:$U$3089,14,FALSE),"") | AP23: =VLOOKUP(H23,#REF!,7,0) -> #REF! | AQ23: =VLOOKUP(H23,#REF!,9,0) -> #REF! | AR23: =VLOOKUP(H23,#REF!,15,0) -> #REF! | AS23: =VLOOKUP(H23,#REF!,16,0) -> #REF! | AT23: =VLOOKUP(H23,#REF!,17,0) -> #REF! | AU23: =VLOOKUP(H23,#REF!,18,0) -> #REF! | AV23: =VLOOKUP(H23,#REF!,19,0) -> #REF! | AW23: =VLOOKUP(H23,#REF!,20,0) -> #REF! | AX23: =VLOOKUP(H23,#REF!,22,0) -> #REF! | AY23: =VLOOKUP(H23,#REF!,23,0) -> #REF! | AZ23: =VLOOKUP(H23,#REF!,24,0) -> #REF! | BA23: =VLOOKUP(H23,#REF!,25,0) -> #REF! | BB23: =VLOOKUP(H23,#REF!,26,0) -> #REF! | BC23: =VLOOKUP(H23,#REF!,27,0) -> #REF! | BD23: =VLOOKUP(H23,#REF!,29,0) -> #REF! | BE23: =VLOOKUP(H23,#REF!,30,0) -> #REF! | BF23: =VLOOKUP(H23,#REF!,31,0) -> #REF! | BG23: =VLOOKUP(H23,#REF!,32,0) -> #REF! | BH23: =VLOOKUP(H23,#REF!,33,0) -> #REF! | BI23: =VLOOKUP(H23,#REF!,34,0) -> #REF! | BJ23: =VLOOKUP(H23,#REF!,36,0) -> #REF! | BK23: =VLOOKUP(H23,#REF!,37,0) -> #REF! | BL23: =VLOOKUP(H23,#REF!,44,0) -> #REF! | BM23: =VLOOKUP(H23,#REF!,45,0) -> #REF! | BN23: =VLOOKUP(H23,#REF!,46,0) -> #REF! | BO23: =VLOOKUP(H23,#REF!,47,0) -> #REF! | BP23: =VLOOKUP(H23,#REF!,48,0) -> #REF!
A24: Gobierno nacional | B24: Poder Ejecutivo | C24: E | D24: 1 | E24: PRESIDENCIA CONSEJO MINISTROS | F24: 114 | G24: CONSEJO NACIONAL DE CIENCIA, TECNOLOGIA E INNOVACION TECNOLOGICA | H24: 1736 | I24: PROGRAMA NACIONAL DE INVESTIGACION CIENTIFICA Y ESTUDIOS AVANZADOS - PROCIENCIA | J24: 15 | K24: LIMA | L24: 1 | M24: LIMA | N24: 22 | O24: MIRAFLORES | R24: S | W24: =IFERROR(VLOOKUP(H24,'IT PEI'!$X$2:$X$5647,1,0),"...") -> ... | X24: =_xlfn.XLOOKUP(H24,'IT PEI'!X$2:X$5647,'IT PEI'!E$2:E$5647,"...",2,-1) -> ... | Y24: =_xlfn.XLOOKUP(H24,'IT PEI'!X$2:X$5647,'IT PEI'!G$2:G$5647,"...",2,-1) -> ... | Z24: =_xlfn.XLOOKUP(H24,'IT PEI'!X$2:X$5647,'IT PEI'!F$2:F$5647,"...",2,-1) -> ... | AA24: =_xlfn.XLOOKUP(H24,'IT PEI'!X$2:X$5647,'IT PEI'!H$2:H$5647,"...",2,-1) -> ... | AB24: =_xlfn.XLOOKUP(H24,'IT PEI'!X$2:X$5647,'IT PEI'!O$2:O$5647,"...",2,-1) -> ... | AC24: =_xlfn.XLOOKUP(H24,'IT PEI'!X$2:X$5647,'IT PEI'!P$2:P$5647,"...",2,-1) -> ... | AD24: =_xlfn.XLOOKUP(H24,'IT PEI'!X$2:X$5647,'IT PEI'!Q$2:Q$5647,"...",2,-1) -> ... | AE24: =IF(COUNTIF(X24, "*" & "2030" & "*")>0, "SI", "No" ) -> No | AF24: =IF(COUNTIF(X24, "*" & "2030" & "*")>0, 1, 0 ) -> 0 | AG24: =IF(COUNTIF(X24, "*" & "2030" & "*")>0, 0, 1 ) -> 1 | AH24: =IF(AND(AA24="En Proceso",AE24="Si"),1,0) -> 0 | AI24: ACTIVO | AJ24: Claudia Melendez Mauricio | AK24: claudia.melendez.ceplan@gmail.com | AL24: =IFERROR(VLOOKUP(tbl_ues[[#This Row],[Id_UE]],'[1]Directorio v.02'!$H$3:$U$3089,11,FALSE),"") -> Elard Bernabé Vargas | AM24: =IFERROR(VLOOKUP(tbl_ues[[#This Row],[Id_UE]],'[1]Directorio v.02'!$H$3:$U$3089,12,FALSE),"") -> Unidad de Planeamiento y Presupuesto | AN24: =IFERROR(VLOOKUP(tbl_ues[[#This Row],[Id_UE]],'[1]Directorio v.02'!$H$3:$U$3089,13,FALSE),"") -> 959180617 | AO24: =IFERROR(VLOOKUP(tbl_ues[[#This Row],[Id_UE]],'[1]Directorio v.02'!$H$3:$U$3089,14,FALSE),"") -> ebernabe@prociencia.gob.pe | AP24: =VLOOKUP(H24,#REF!,7,0) -> #REF! | AQ24: =VLOOKUP(H24,#REF!,9,0) -> #REF! | AR24: =VLOOKUP(H24,#REF!,15,0) -> #REF! | AS24: =VLOOKUP(H24,#REF!,16,0) -> #REF! | AT24: =VLOOKUP(H24,#REF!,17,0) -> #REF! | AU24: =VLOOKUP(H24,#REF!,18,0) -> #REF! | AV24: =VLOOKUP(H24,#REF!,19,0) -> #REF! | AW24: =VLOOKUP(H24,#REF!,20,0) -> #REF! | AX24: =VLOOKUP(H24,#REF!,22,0) -> #REF! | AY24: =VLOOKUP(H24,#REF!,23,0) -> #REF! | AZ24: =VLOOKUP(H24,#REF!,24,0) -> #REF! | BA24: =VLOOKUP(H24,#REF!,25,0) -> #REF! | BB24: =VLOOKUP(H24,#REF!,26,0) -> #REF! | BC24: =VLOOKUP(H24,#REF!,27,0) -> #REF! | BD24: =VLOOKUP(H24,#REF!,29,0) -> #REF! | BE24: =VLOOKUP(H24,#REF!,30,0) -> #REF! | BF24: =VLOOKUP(H24,#REF!,31,0) -> #REF! | BG24: =VLOOKUP(H24,#REF!,32,0) -> #REF! | BH24: =VLOOKUP(H24,#REF!,33,0) -> #REF! | BI24: =VLOOKUP(H24,#REF!,34,0) -> #REF! | BJ24: =VLOOKUP(H24,#REF!,36,0) -> #REF! | BK24: =VLOOKUP(H24,#REF!,37,0) -> #REF! | BL24: =VLOOKUP(H24,#REF!,44,0) -> #REF! | BM24: =VLOOKUP(H24,#REF!,45,0) -> #REF! | BN24: =VLOOKUP(H24,#REF!,46,0) -> #REF! | BO24: =VLOOKUP(H24,#REF!,47,0) -> #REF! | BP24: =VLOOKUP(H24,#REF!,48,0) -> #REF!
A25: Gobierno nacional | B25: Poder Ejecutivo | C25: E | D25: 1 | E25: PRESIDENCIA CONSEJO MINISTROS | F25: 114 | G25: CONSEJO NACIONAL DE CIENCIA, TECNOLOGIA E INNOVACION TECNOLOGICA | H25: 86 | I25: CONSEJO NACIONAL DE CIENCIA, TECNOLOGIA E INNOVACION TECNOLOGICA - CONCYTEC | J25: 15 | K25: LIMA | L25: 1 | M25: LIMA | N25: 30 | O25: SAN BORJA | Q25: S | R25: S | W25: =IFERROR(VLOOKUP(H25,'IT PEI'!$X$2:$X$5647,1,0),"...") -> 86 | X25: =_xlfn.XLOOKUP(H25,'IT PEI'!X$2:X$5647,'IT PEI'!E$2:E$5647,"...",2,-1) -> 2025-2030 | Y25: =_xlfn.XLOOKUP(H25,'IT PEI'!X$2:X$5647,'IT PEI'!G$2:G$5647,"...",2,-1) -> FORMULADO | Z25: =_xlfn.XLOOKUP(H25,'IT PEI'!X$2:X$5647,'IT PEI'!F$2:F$5647,"...",2,-1) -> SI | AA25: =_xlfn.XLOOKUP(H25,'IT PEI'!X$2:X$5647,'IT PEI'!H$2:H$5647,"...",2,-1) -> EMITIDO | AB25: =_xlfn.XLOOKUP(H25,'IT PEI'!X$2:X$5647,'IT PEI'!O$2:O$5647,"...",2,-1) -> 2025-0002549 | AC25: =_xlfn.XLOOKUP(H25,'IT PEI'!X$2:X$5647,'IT PEI'!P$2:P$5647,"...",2,-1) -> 45880 | AD25: =_xlfn.XLOOKUP(H25,'IT PEI'!X$2:X$5647,'IT PEI'!Q$2:Q$5647,"...",2,-1) -> 000289-2025-CEPLAN-DNCPPEI | AE25: =IF(COUNTIF(X25, "*" & "2030" & "*")>0, "SI", "No" ) -> SI | AF25: =IF(COUNTIF(X25, "*" & "2030" & "*")>0, 1, 0 ) -> 1 | AG25: =IF(COUNTIF(X25, "*" & "2030" & "*")>0, 0, 1 ) -> 0 | AH25: =IF(AND(AA25="En Proceso",AE25="Si"),1,0) -> 0 | AI25: ACTIVO | AJ25: Claudia Melendez Mauricio | AK25: claudia.melendez.ceplan@gmail.com | AL25: =IFERROR(VLOOKUP(tbl_ues[[#This Row],[Id_UE]],'[1]Directorio v.02'!$H$3:$U$3089,11,FALSE),"") -> Héctor Enrique Cruces Mayhua | AM25: =IFERROR(VLOOKUP(tbl_ues[[#This Row],[Id_UE]],'[1]Directorio v.02'!$H$3:$U$3089,12,FALSE),"") -> Jefe de la Oficina General de Planeamiento y Presupuesto | AN25: =IFERROR(VLOOKUP(tbl_ues[[#This Row],[Id_UE]],'[1]Directorio v.02'!$H$3:$U$3089,13,FALSE),"") -> 399-0030 Anexo 2200 | AO25: =IFERROR(VLOOKUP(tbl_ues[[#This Row],[Id_UE]],'[1]Directorio v.02'!$H$3:$U$3089,14,FALSE),"") -> hcruces@concytec.gob.pe | AP25: =VLOOKUP(H25,#REF!,7,0) -> #REF! | AQ25: =VLOOKUP(H25,#REF!,9,0) -> #REF! | AR25: =VLOOKUP(H25,#REF!,15,0) -> #REF! | AS25: =VLOOKUP(H25,#REF!,16,0) -> #REF! | AT25: =VLOOKUP(H25,#REF!,17,0) -> #REF! | AU25: =VLOOKUP(H25,#REF!,18,0) -> #REF! | AV25: =VLOOKUP(H25,#REF!,19,0) -> #REF! | AW25: =VLOOKUP(H25,#REF!,20,0) -> #REF! | AX25: =VLOOKUP(H25,#REF!,22,0) -> #REF! | AY25: =VLOOKUP(H25,#REF!,23,0) -> #REF! | AZ25: =VLOOKUP(H25,#REF!,24,0) -> #REF! | BA25: =VLOOKUP(H25,#REF!,25,0) -> #REF! | BB25: =VLOOKUP(H25,#REF!,26,0) -> #REF! | BC25: =VLOOKUP(H25,#REF!,27,0) -> #REF! | BD25: =VLOOKUP(H25,#REF!,29,0) -> #REF! | BE25: =VLOOKUP(H25,#REF!,30,0) -> #REF! | BF25: =VLOOKUP(H25,#REF!,31,0) -> #REF! | BG25: =VLOOKUP(H25,#REF!,32,0) -> #REF! | BH25: =VLOOKUP(H25,#REF!,33,0) -> #REF! | BI25: =VLOOKUP(H25,#REF!,34,0) -> #REF! | BJ25: =VLOOKUP(H25,#REF!,36,0) -> #REF! | BK25: =VLOOKUP(H25,#REF!,37,0) -> #REF! | BL25: =VLOOKUP(H25,#REF!,44,0) -> #REF! | BM25: =VLOOKUP(H25,#REF!,45,0) -> #REF! | BN25: =VLOOKUP(H25,#REF!,46,0) -> #REF! | BO25: =VLOOKUP(H25,#REF!,47,0) -> #REF! | BP25: =VLOOKUP(H25,#REF!,48,0) -> #REF!
A26: Gobierno nacional | B26: Poder Ejecutivo | C26: E | D26: 39 | E26: MUJER Y POBLACIONES VULNERABLES | F26: 345 | G26: CONSEJO NACIONAL PARA LA INTEGRACION DE LA PERSONA CON DISCAPACIDAD - CONADIS | H26: 1008 | I26: CONSEJO NAC. PARA LA INTEGRACION DE LA PERSONA CON DISCAPACIDAD- CONADIS | J26: 15 | K26: LIMA | L26: 1 | M26: LIMA | N26: 1 | O26: LIMA | Q26: S | R26: S | W26: =IFERROR(VLOOKUP(H26,'IT PEI'!$X$2:$X$5647,1,0),"...") -> 1008 | X26: =_xlfn.XLOOKUP(H26,'IT PEI'!X$2:X$5647,'IT PEI'!E$2:E$5647,"...",2,-1) -> 2025-2030 | Y26: =_xlfn.XLOOKUP(H26,'IT PEI'!X$2:X$5647,'IT PEI'!G$2:G$5647,"...",2,-1) -> FORMULADO | Z26: =_xlfn.XLOOKUP(H26,'IT PEI'!X$2:X$5647,'IT PEI'!F$2:F$5647,"...",2,-1) -> SI | AA26: =_xlfn.XLOOKUP(H26,'IT PEI'!X$2:X$5647,'IT PEI'!H$2:H$5647,"...",2,-1) -> EMITIDO | AB26: =_xlfn.XLOOKUP(H26,'IT PEI'!X$2:X$5647,'IT PEI'!O$2:O$5647,"...",2,-1) -> 2024-00003379 | AC26: =_xlfn.XLOOKUP(H26,'IT PEI'!X$2:X$5647,'IT PEI'!P$2:P$5647,"...",2,-1) -> 45608 | AD26: =_xlfn.XLOOKUP(H26,'IT PEI'!X$2:X$5647,'IT PEI'!Q$2:Q$5647,"...",2,-1) -> 000392-2024-CEPLAN-DNCPPEI | AE26: =IF(COUNTIF(X26, "*" & "2030" & "*")>0, "SI", "No" ) -> SI | AF26: =IF(COUNTIF(X26, "*" & "2030" & "*")>0, 1, 0 ) -> 1 | AG26: =IF(COUNTIF(X26, "*" & "2030" & "*")>0, 0, 1 ) -> 0 | AH26: =IF(AND(AA26="En Proceso",AE26="Si"),1,0) -> 0 | AI26: ACTIVO | AJ26: Emerson Paucar Cuipal | AK26: epaucar@ceplan.gob.pe | AL26: =IFERROR(VLOOKUP(tbl_ues[[#This Row],[Id_UE]],'[1]Directorio v.02'!$H$3:$U$3089,11,FALSE),"") -> William Jesus Cuba Arana | AM26: =IFERROR(VLOOKUP(tbl_ues[[#This Row],[Id_UE]],'[1]Directorio v.02'!$H$3:$U$3089,12,FALSE),"") -> Director II de la OFICINA DE PLANEAMIENTO, PRESUPUESTO Y MODERNIZACIÓN | AN26: =IFERROR(VLOOKUP(tbl_ues[[#This Row],[Id_UE]],'[1]Directorio v.02'!$H$3:$U$3089,13,FALSE),"") -> 995717680 | AO26: =IFERROR(VLOOKUP(tbl_ues[[#This Row],[Id_UE]],'[1]Directorio v.02'!$H$3:$U$3089,14,FALSE),"") -> mcorrea@conadisperu.gob.pe | AP26: =VLOOKUP(H26,#REF!,7,0) -> #REF! | AQ26: =VLOOKUP(H26,#REF!,9,0) -> #REF! | AR26: =VLOOKUP(H26,#REF!,15,0) -> #REF! | AS26: =VLOOKUP(H26,#REF!,16,0) -> #REF! | AT26: =VLOOKUP(H26,#REF!,17,0) -> #REF! | AU26: =VLOOKUP(H26,#REF!,18,0) -> #REF! | AV26: =VLOOKUP(H26,#REF!,19,0) -> #REF! | AW26: =VLOOKUP(H26,#REF!,20,0) -> #REF! | AX26: =VLOOKUP(H26,#REF!,22,0) -> #REF! | AY26: =VLOOKUP(H26,#REF!,23,0) -> #REF! | AZ26: =VLOOKUP(H26,#REF!,24,0) -> #REF! | BA26: =VLOOKUP(H26,#REF!,25,0) -> #REF! | BB26: =VLOOKUP(H26,#REF!,26,0) -> #REF! | BC26: =VLOOKUP(H26,#REF!,27,0) -> #REF! | BD26: =VLOOKUP(H26,#REF!,29,0) -> #REF! | BE26: =VLOOKUP(H26,#REF!,30,0) -> #REF! | BF26: =VLOOKUP(H26,#REF!,31,0) -> #REF! | BG26: =VLOOKUP(H26,#REF!,32,0) -> #REF! | BH26: =VLOOKUP(H26,#REF!,33,0) -> #REF! | BI26: =VLOOKUP(H26,#REF!,34,0) -> #REF! | BJ26: =VLOOKUP(H26,#REF!,36,0) -> #REF! | BK26: =VLOOKUP(H26,#REF!,37,0) -> #REF! | BL26: =VLOOKUP(H26,#REF!,44,0) -> #REF! | BM26: =VLOOKUP(H26,#REF!,45,0) -> #REF! | BN26: =VLOOKUP(H26,#REF!,46,0) -> #REF! | BO26: =VLOOKUP(H26,#REF!,47,0) -> #REF! | BP26: =VLOOKUP(H26,#REF!,48,0) -> #REF!
A27: Gobierno nacional | B27: OCA | C27: E | D27: 19 | E27: CONTRALORIA GENERAL | F27: 19 | G27: CONTRALORIA GENERAL | H27: 196 | I27: CONTRALORIA GENERAL | J27: 15 | K27: LIMA | L27: 1 | M27: LIMA | N27: 13 | O27: JESUS MARIA | Q27: S | R27: S | V27: OCA | W27: =IFERROR(VLOOKUP(H27,'IT PEI'!$X$2:$X$5647,1,0),"...") -> 196 | X27: =_xlfn.XLOOKUP(H27,'IT PEI'!X$2:X$5647,'IT PEI'!E$2:E$5647,"...",2,-1) -> 2025-2030 | Y27: =_xlfn.XLOOKUP(H27,'IT PEI'!X$2:X$5647,'IT PEI'!G$2:G$5647,"...",2,-1) -> FORMULADO | Z27: =_xlfn.XLOOKUP(H27,'IT PEI'!X$2:X$5647,'IT PEI'!F$2:F$5647,"...",2,-1) -> SI | AA27: =_xlfn.XLOOKUP(H27,'IT PEI'!X$2:X$5647,'IT PEI'!H$2:H$5647,"...",2,-1) -> EMITIDO | AB27: =_xlfn.XLOOKUP(H27,'IT PEI'!X$2:X$5647,'IT PEI'!O$2:O$5647,"...",2,-1) -> 2025-0001450 | AC27: =_xlfn.XLOOKUP(H27,'IT PEI'!X$2:X$5647,'IT PEI'!P$2:P$5647,"...",2,-1) -> 45832 | AD27: =_xlfn.XLOOKUP(H27,'IT PEI'!X$2:X$5647,'IT PEI'!Q$2:Q$5647,"...",2,-1) -> 000241-2025-CEPLAN-DNCPPEI | AE27: =IF(COUNTIF(X27, "*" & "2030" & "*")>0, "SI", "No" ) -> SI | AF27: =IF(COUNTIF(X27, "*" & "2030" & "*")>0, 1, 0 ) -> 1 | AG27: =IF(COUNTIF(X27, "*" & "2030" & "*")>0, 0, 1 ) -> 0 | AH27: =IF(AND(AA27="En Proceso",AE27="Si"),1,0) -> 0 | AI27: ACTIVO | AJ27: Addy López Peña | AK27: alopez@ceplan.gob.pe | AL27: =IFERROR(VLOOKUP(tbl_ues[[#This Row],[Id_UE]],'[1]Directorio v.02'!$H$3:$U$3089,11,FALSE),"") -> Cedilia Victoria Akemi Kuroiwa Pérez | AM27: =IFERROR(VLOOKUP(tbl_ues[[#This Row],[Id_UE]],'[1]Directorio v.02'!$H$3:$U$3089,12,FALSE),"") -> Gerente de Modernización y Planeamiento (e) | AN27: =IFERROR(VLOOKUP(tbl_ues[[#This Row],[Id_UE]],'[1]Directorio v.02'!$H$3:$U$3089,13,FALSE),"") -> (01) 330 3000 / Anexo 2506 | AO27: =IFERROR(VLOOKUP(tbl_ues[[#This Row],[Id_UE]],'[1]Directorio v.02'!$H$3:$U$3089,14,FALSE),"") -> ckuroiwa@contraloria.gob.pe | AP27: =VLOOKUP(H27,#REF!,7,0) -> #REF! | AQ27: =VLOOKUP(H27,#REF!,9,0) -> #REF! | AR27: =VLOOKUP(H27,#REF!,15,0) -> #REF! | AS27: =VLOOKUP(H27,#REF!,16,0) -> #REF! | AT27: =VLOOKUP(H27,#REF!,17,0) -> #REF! | AU27: =VLOOKUP(H27,#REF!,18,0) -> #REF! | AV27: =VLOOKUP(H27,#REF!,19,0) -> #REF! | AW27: =VLOOKUP(H27,#REF!,20,0) -> #REF! | AX27: =VLOOKUP(H27,#REF!,22,0) -> #REF! | AY27: =VLOOKUP(H27,#REF!,23,0) -> #REF! | AZ27: =VLOOKUP(H27,#REF!,24,0) -> #REF! | BA27: =VLOOKUP(H27,#REF!,25,0) -> #REF! | BB27: =VLOOKUP(H27,#REF!,26,0) -> #REF! | BC27: =VLOOKUP(H27,#REF!,27,0) -> #REF! | BD27: =VLOOKUP(H27,#REF!,29,0) -> #REF! | BE27: =VLOOKUP(H27,#REF!,30,0) -> #REF! | BF27: =VLOOKUP(H27,#REF!,31,0) -> #REF! | BG27: =VLOOKUP(H27,#REF!,32,0) -> #REF! | BH27: =VLOOKUP(H27,#REF!,33,0) -> #REF! | BI27: =VLOOKUP(H27,#REF!,34,0) -> #REF! | BJ27: =VLOOKUP(H27,#REF!,36,0) -> #REF! | BK27: =VLOOKUP(H27,#REF!,37,0) -> #REF! | BL27: =VLOOKUP(H27,#REF!,44,0) -> #REF! | BM27: =VLOOKUP(H27,#REF!,45,0) -> #REF! | BN27: =VLOOKUP(H27,#REF!,46,0) -> #REF! | BO27: =VLOOKUP(H27,#REF!,47,0) -> #REF! | BP27: =VLOOKUP(H27,#REF!,48,0) -> #REF!
A28: Gobierno nacional | B28: OCA | C28: E | D28: 19 | E28: CONTRALORIA GENERAL | F28: 19 | G28: CONTRALORIA GENERAL | H28: 1698 | I28: CONTRALORIA GENERAL - GESTION DE PROYECTOS Y FORTALECIMIENTO DE CAPACIDADES | J28: 15 | K28: LIMA | L28: 1 | M28: LIMA | N28: 13 | O28: JESUS MARIA | R28: S | V28: OCA | W28: =IFERROR(VLOOKUP(H28,'IT PEI'!$X$2:$X$5647,1,0),"...") -> ... | X28: =_xlfn.XLOOKUP(H28,'IT PEI'!X$2:X$5647,'IT PEI'!E$2:E$5647,"...",2,-1) -> ... | Y28: =_xlfn.XLOOKUP(H28,'IT PEI'!X$2:X$5647,'IT PEI'!G$2:G$5647,"...",2,-1) -> ... | Z28: =_xlfn.XLOOKUP(H28,'IT PEI'!X$2:X$5647,'IT PEI'!F$2:F$5647,"...",2,-1) -> ... | AA28: =_xlfn.XLOOKUP(H28,'IT PEI'!X$2:X$5647,'IT PEI'!H$2:H$5647,"...",2,-1) -> ... | AB28: =_xlfn.XLOOKUP(H28,'IT PEI'!X$2:X$5647,'IT PEI'!O$2:O$5647,"...",2,-1) -> ... | AC28: =_xlfn.XLOOKUP(H28,'IT PEI'!X$2:X$5647,'IT PEI'!P$2:P$5647,"...",2,-1) -> ... | AD28: =_xlfn.XLOOKUP(H28,'IT PEI'!X$2:X$5647,'IT PEI'!Q$2:Q$5647,"...",2,-1) -> ... | AE28: =IF(COUNTIF(X28, "*" & "2030" & "*")>0, "SI", "No" ) -> No | AF28: =IF(COUNTIF(X28, "*" & "2030" & "*")>0, 1, 0 ) -> 0 | AG28: =IF(COUNTIF(X28, "*" & "2030" & "*")>0, 0, 1 ) -> 1 | AH28: =IF(AND(AA28="En Proceso",AE28="Si"),1,0) -> 0 | AI28: ACTIVO | AJ28: Addy López Peña | AK28: alopez@ceplan.gob.pe | AL28: =IFERROR(VLOOKUP(tbl_ues[[#This Row],[Id_UE]],'[1]Directorio v.02'!$H$3:$U$3089,11,FALSE),"") -> Cedilia Victoria Akemi Kuroiwa Pérez | AM28: =IFERROR(VLOOKUP(tbl_ues[[#This Row],[Id_UE]],'[1]Directorio v.02'!$H$3:$U$3089,12,FALSE),"") -> Gerente de Modernización y Planeamiento (e) | AN28: =IFERROR(VLOOKUP(tbl_ues[[#This Row],[Id_UE]],'[1]Directorio v.02'!$H$3:$U$3089,13,FALSE),"") -> (01) 330 3000 / Anexo 2506 | AO28: =IFERROR(VLOOKUP(tbl_ues[[#This Row],[Id_UE]],'[1]Directorio v.02'!$H$3:$U$3089,14,FALSE),"") -> ckuroiwa@contraloria.gob.pe | AP28: =VLOOKUP(H28,#REF!,7,0) -> #REF! | AQ28: =VLOOKUP(H28,#REF!,9,0) -> #REF! | AR28: =VLOOKUP(H28,#REF!,15,0) -> #REF! | AS28: =VLOOKUP(H28,#REF!,16,0) -> #REF! | AT28: =VLOOKUP(H28,#REF!,17,0) -> #REF! | AU28: =VLOOKUP(H28,#REF!,18,0) -> #REF! | AV28: =VLOOKUP(H28,#REF!,19,0) -> #REF! | AW28: =VLOOKUP(H28,#REF!,20,0) -> #REF! | AX28: =VLOOKUP(H28,#REF!,22,0) -> #REF! | AY28: =VLOOKUP(H28,#REF!,23,0) -> #REF! | AZ28: =VLOOKUP(H28,#REF!,24,0) -> #REF! | BA28: =VLOOKUP(H28,#REF!,25,0) -> #REF! | BB28: =VLOOKUP(H28,#REF!,26,0) -> #REF! | BC28: =VLOOKUP(H28,#REF!,27,0) -> #REF! | BD28: =VLOOKUP(H28,#REF!,29,0) -> #REF! | BE28: =VLOOKUP(H28,#REF!,30,0) -> #REF! | BF28: =VLOOKUP(H28,#REF!,31,0) -> #REF! | BG28: =VLOOKUP(H28,#REF!,32,0) -> #REF! | BH28: =VLOOKUP(H28,#REF!,33,0) -> #REF! | BI28: =VLOOKUP(H28,#REF!,34,0) -> #REF! | BJ28: =VLOOKUP(H28,#REF!,36,0) -> #REF! | BK28: =VLOOKUP(H28,#REF!,37,0) -> #REF! | BL28: =VLOOKUP(H28,#REF!,44,0) -> #REF! | BM28: =VLOOKUP(H28,#REF!,45,0) -> #REF! | BN28: =VLOOKUP(H28,#REF!,46,0) -> #REF! | BO28: =VLOOKUP(H28,#REF!,47,0) -> #REF! | BP28: =VLOOKUP(H28,#REF!,48,0) -> #REF!
A29: Gobierno nacional | B29: OCA | C29: E | D29: 20 | E29: DEFENSORIA DEL PUEBLO | F29: 20 | G29: DEFENSORIA DEL PUEBLO | H29: 197 | I29: DEFENSORIA DEL PUEBLO | J29: 15 | K29: LIMA | L29: 1 | M29: LIMA | N29: 1 | O29: LIMA | Q29: S | R29: S | V29: OCA | W29: =IFERROR(VLOOKUP(H29,'IT PEI'!$X$2:$X$5647,1,0),"...") -> 197 | X29: =_xlfn.XLOOKUP(H29,'IT PEI'!X$2:X$5647,'IT PEI'!E$2:E$5647,"...",2,-1) -> 2025-2030 | Y29: =_xlfn.XLOOKUP(H29,'IT PEI'!X$2:X$5647,'IT PEI'!G$2:G$5647,"...",2,-1) -> FORMULADO | Z29: =_xlfn.XLOOKUP(H29,'IT PEI'!X$2:X$5647,'IT PEI'!F$2:F$5647,"...",2,-1) -> SI | AA29: =_xlfn.XLOOKUP(H29,'IT PEI'!X$2:X$5647,'IT PEI'!H$2:H$5647,"...",2,-1) -> EMITIDO | AB29: =_xlfn.XLOOKUP(H29,'IT PEI'!X$2:X$5647,'IT PEI'!O$2:O$5647,"...",2,-1) -> 2024-0004004 | AC29: =_xlfn.XLOOKUP(H29,'IT PEI'!X$2:X$5647,'IT PEI'!P$2:P$5647,"...",2,-1) -> 45657 | AD29: =_xlfn.XLOOKUP(H29,'IT PEI'!X$2:X$5647,'IT PEI'!Q$2:Q$5647,"...",2,-1) -> 000492-2024-CEPLAN-DNCPPEI | AE29: =IF(COUNTIF(X29, "*" & "2030" & "*")>0, "SI", "No" ) -> SI | AF29: =IF(COUNTIF(X29, "*" & "2030" & "*")>0, 1, 0 ) -> 1 | AG29: =IF(COUNTIF(X29, "*" & "2030" & "*")>0, 0, 1 ) -> 0 | AH29: =IF(AND(AA29="En Proceso",AE29="Si"),1,0) -> 0 | AI29: ACTIVO | AJ29: Addy López Peña | AK29: alopez@ceplan.gob.pe | AL29: =IFERROR(VLOOKUP(tbl_ues[[#This Row],[Id_UE]],'[1]Directorio v.02'!$H$3:$U$3089,11,FALSE),"") -> Quispe Seijas, Maria Isabel | AM29: =IFERROR(VLOOKUP(tbl_ues[[#This Row],[Id_UE]],'[1]Directorio v.02'!$H$3:$U$3089,12,FALSE),"") -> Oficina de gobierno digital, proyectos y tecnologías de la información | AN29: =IFERROR(VLOOKUP(tbl_ues[[#This Row],[Id_UE]],'[1]Directorio v.02'!$H$3:$U$3089,13,FALSE),"") -> 3110300 anexo 1166 | AO29: =IFERROR(VLOOKUP(tbl_ues[[#This Row],[Id_UE]],'[1]Directorio v.02'!$H$3:$U$3089,14,FALSE),"") -> mquispes@defensoria.gob.pe | AP29: =VLOOKUP(H29,#REF!,7,0) -> #REF! | AQ29: =VLOOKUP(H29,#REF!,9,0) -> #REF! | AR29: =VLOOKUP(H29,#REF!,15,0) -> #REF! | AS29: =VLOOKUP(H29,#REF!,16,0) -> #REF! | AT29: =VLOOKUP(H29,#REF!,17,0) -> #REF! | AU29: =VLOOKUP(H29,#REF!,18,0) -> #REF! | AV29: =VLOOKUP(H29,#REF!,19,0) -> #REF! | AW29: =VLOOKUP(H29,#REF!,20,0) -> #REF! | AX29: =VLOOKUP(H29,#REF!,22,0) -> #REF! | AY29: =VLOOKUP(H29,#REF!,23,0) -> #REF! | AZ29: =VLOOKUP(H29,#REF!,24,0) -> #REF! | BA29: =VLOOKUP(H29,#REF!,25,0) -> #REF! | BB29: =VLOOKUP(H29,#REF!,26,0) -> #REF! | BC29: =VLOOKUP(H29,#REF!,27,0) -> #REF! | BD29: =VLOOKUP(H29,#REF!,29,0) -> #REF! | BE29: =VLOOKUP(H29,#REF!,30,0) -> #REF! | BF29: =VLOOKUP(H29,#REF!,31,0) -> #REF! | BG29: =VLOOKUP(H29,#REF!,32,0) -> #REF! | BH29: =VLOOKUP(H29,#REF!,33,0) -> #REF! | BI29: =VLOOKUP(H29,#REF!,34,0) -> #REF! | BJ29: =VLOOKUP(H29,#REF!,36,0) -> #REF! | BK29: =VLOOKUP(H29,#REF!,37,0) -> #REF! | BL29: =VLOOKUP(H29,#REF!,44,0) -> #REF! | BM29: =VLOOKUP(H29,#REF!,45,0) -> #REF! | BN29: =VLOOKUP(H29,#REF!,46,0) -> #REF! | BO29: =VLOOKUP(H29,#REF!,47,0) -> #REF! | BP29: =VLOOKUP(H29,#REF!,48,0) -> #REF!
A30: Gobierno nacional | B30: Poder Ejecutivo | C30: E | D30: 1 | E30: PRESIDENCIA CONSEJO MINISTROS | F30: 11 | G30: DESPACHO PRESIDENCIAL | H30: 1061 | I30: DESPACHO PRESIDENCIAL | J30: 15 | K30: LIMA | L30: 1 | M30: LIMA | N30: 1 | O30: LIMA | Q30: S | R30: S | W30: =IFERROR(VLOOKUP(H30,'IT PEI'!$X$2:$X$5647,1,0),"...") -> 1061 | X30: =_xlfn.XLOOKUP(H30,'IT PEI'!X$2:X$5647,'IT PEI'!E$2:E$5647,"...",2,-1) -> 2025-2030 | Y30: =_xlfn.XLOOKUP(H30,'IT PEI'!X$2:X$5647,'IT PEI'!G$2:G$5647,"...",2,-1) -> FORMULADO | Z30: =_xlfn.XLOOKUP(H30,'IT PEI'!X$2:X$5647,'IT PEI'!F$2:F$5647,"...",2,-1) -> SI | AA30: =_xlfn.XLOOKUP(H30,'IT PEI'!X$2:X$5647,'IT PEI'!H$2:H$5647,"...",2,-1) -> EMITIDO | AB30: =_xlfn.XLOOKUP(H30,'IT PEI'!X$2:X$5647,'IT PEI'!O$2:O$5647,"...",2,-1) -> 2025-0000320 | AC30: =_xlfn.XLOOKUP(H30,'IT PEI'!X$2:X$5647,'IT PEI'!P$2:P$5647,"...",2,-1) -> 45686 | AD30: =_xlfn.XLOOKUP(H30,'IT PEI'!X$2:X$5647,'IT PEI'!Q$2:Q$5647,"...",2,-1) -> 000025-2025-CEPLAN-DNCPPEI | AE30: =IF(COUNTIF(X30, "*" & "2030" & "*")>0, "SI", "No" ) -> SI | AF30: =IF(COUNTIF(X30, "*" & "2030" & "*")>0, 1, 0 ) -> 1 | AG30: =IF(COUNTIF(X30, "*" & "2030" & "*")>0, 0, 1 ) -> 0 | AH30: =IF(AND(AA30="En Proceso",AE30="Si"),1,0) -> 0 | AI30: ACTIVO | AJ30: Claudia Melendez Mauricio | AK30: claudia.melendez.ceplan@gmail.com | AL30: =IFERROR(VLOOKUP(tbl_ues[[#This Row],[Id_UE]],'[1]Directorio v.02'!$H$3:$U$3089,11,FALSE),"") -> Eco. Antonio Mirril Ramos Bernaola | AM30: =IFERROR(VLOOKUP(tbl_ues[[#This Row],[Id_UE]],'[1]Directorio v.02'!$H$3:$U$3089,12,FALSE),"") -> Director General de la Oficina General de Planeamiento, Presupuesto y Modernización (OGPM) | AN30: =IFERROR(VLOOKUP(tbl_ues[[#This Row],[Id_UE]],'[1]Directorio v.02'!$H$3:$U$3089,13,FALSE),"") -> 959 526 300 / 958 967 034 | AO30: =IFERROR(VLOOKUP(tbl_ues[[#This Row],[Id_UE]],'[1]Directorio v.02'!$H$3:$U$3089,14,FALSE),"") -> aramosb@presidencia.gob.pe | AP30: =VLOOKUP(H30,#REF!,7,0) -> #REF! | AQ30: =VLOOKUP(H30,#REF!,9,0) -> #REF! | AR30: =VLOOKUP(H30,#REF!,15,0) -> #REF! | AS30: =VLOOKUP(H30,#REF!,16,0) -> #REF! | AT30: =VLOOKUP(H30,#REF!,17,0) -> #REF! | AU30: =VLOOKUP(H30,#REF!,18,0) -> #REF! | AV30: =VLOOKUP(H30,#REF!,19,0) -> #REF! | AW30: =VLOOKUP(H30,#REF!,20,0) -> #REF! | AX30: =VLOOKUP(H30,#REF!,22,0) -> #REF! | AY30: =VLOOKUP(H30,#REF!,23,0) -> #REF! | AZ30: =VLOOKUP(H30,#REF!,24,0) -> #REF! | BA30: =VLOOKUP(H30,#REF!,25,0) -> #REF! | BB30: =VLOOKUP(H30,#REF!,26,0) -> #REF! | BC30: =VLOOKUP(H30,#REF!,27,0) -> #REF! | BD30: =VLOOKUP(H30,#REF!,29,0) -> #REF! | BE30: =VLOOKUP(H30,#REF!,30,0) -> #REF! | BF30: =VLOOKUP(H30,#REF!,31,0) -> #REF! | BG30: =VLOOKUP(H30,#REF!,32,0) -> #REF! | BH30: =VLOOKUP(H30,#REF!,33,0) -> #REF! | BI30: =VLOOKUP(H30,#REF!,34,0) -> #REF! | BJ30: =VLOOKUP(H30,#REF!,36,0) -> #REF! | BK30: =VLOOKUP(H30,#REF!,37,0) -> #REF! | BL30: =VLOOKUP(H30,#REF!,44,0) -> #REF! | BM30: =VLOOKUP(H30,#REF!,45,0) -> #REF! | BN30: =VLOOKUP(H30,#REF!,46,0) -> #REF! | BO30: =VLOOKUP(H30,#REF!,47,0) -> #REF! | BP30: =VLOOKUP(H30,#REF!,48,0) -> #REF!
A31: Gobierno nacional | B31: Poder Ejecutivo | C31: E | D31: 1 | E31: PRESIDENCIA CONSEJO MINISTROS | F31: 10 | G31: DIRECCION NACIONAL DE INTELIGENCIA | H31: 1032 | I31: DIRECCION NACIONAL DE INTELIGENCIA- DINI | J31: 15 | K31: LIMA | L31: 1 | M31: LIMA | N31: 4 | O31: BARRANCO | Q31: S | R31: S | W31: =IFERROR(VLOOKUP(H31,'IT PEI'!$X$2:$X$5647,1,0),"...") -> 1032 | X31: =_xlfn.XLOOKUP(H31,'IT PEI'!X$2:X$5647,'IT PEI'!E$2:E$5647,"...",2,-1) -> 2026-2030 | Y31: =_xlfn.XLOOKUP(H31,'IT PEI'!X$2:X$5647,'IT PEI'!G$2:G$5647,"...",2,-1) -> FORMULADO | Z31: =_xlfn.XLOOKUP(H31,'IT PEI'!X$2:X$5647,'IT PEI'!F$2:F$5647,"...",2,-1) -> SI | AA31: =_xlfn.XLOOKUP(H31,'IT PEI'!X$2:X$5647,'IT PEI'!H$2:H$5647,"...",2,-1) -> EMITIDO | AB31: =_xlfn.XLOOKUP(H31,'IT PEI'!X$2:X$5647,'IT PEI'!O$2:O$5647,"...",2,-1) -> 2025-000329 | AC31: =_xlfn.XLOOKUP(H31,'IT PEI'!X$2:X$5647,'IT PEI'!P$2:P$5647,"...",2,-1) -> 45940 | AD31: =_xlfn.XLOOKUP(H31,'IT PEI'!X$2:X$5647,'IT PEI'!Q$2:Q$5647,"...",2,-1) -> 000394-2025-CEPLAN-DNCPPEI | AE31: =IF(COUNTIF(X31, "*" & "2030" & "*")>0, "SI", "No" ) -> SI | AF31: =IF(COUNTIF(X31, "*" & "2030" & "*")>0, 1, 0 ) -> 1 | AG31: =IF(COUNTIF(X31, "*" & "2030" & "*")>0, 0, 1 ) -> 0 | AH31: =IF(AND(AA31="En Proceso",AE31="Si"),1,0) -> 0 | AI31: ACTIVO | AJ31: Claudia Melendez Mauricio | AK31: claudia.melendez.ceplan@gmail.com | AL31: =IFERROR(VLOOKUP(tbl_ues[[#This Row],[Id_UE]],'[1]Directorio v.02'!$H$3:$U$3089,11,FALSE),"") -> Cesi Llatas | AM31: =IFERROR(VLOOKUP(tbl_ues[[#This Row],[Id_UE]],'[1]Directorio v.02'!$H$3:$U$3089,12,FALSE),"") -> Jefe de Planificación y presupuesto | AN31: =IFERROR(VLOOKUP(tbl_ues[[#This Row],[Id_UE]],'[1]Directorio v.02'!$H$3:$U$3089,13,FALSE),"") -> 6175414 | AO31: =IFERROR(VLOOKUP(tbl_ues[[#This Row],[Id_UE]],'[1]Directorio v.02'!$H$3:$U$3089,14,FALSE),"") -> of674@dini.gob.pe | AP31: =VLOOKUP(H31,#REF!,7,0) -> #REF! | AQ31: =VLOOKUP(H31,#REF!,9,0) -> #REF! | AR31: =VLOOKUP(H31,#REF!,15,0) -> #REF! | AS31: =VLOOKUP(H31,#REF!,16,0) -> #REF! | AT31: =VLOOKUP(H31,#REF!,17,0) -> #REF! | AU31: =VLOOKUP(H31,#REF!,18,0) -> #REF! | AV31: =VLOOKUP(H31,#REF!,19,0) -> #REF! | AW31: =VLOOKUP(H31,#REF!,20,0) -> #REF! | AX31: =VLOOKUP(H31,#REF!,22,0) -> #REF! | AY31: =VLOOKUP(H31,#REF!,23,0) -> #REF! | AZ31: =VLOOKUP(H31,#REF!,24,0) -> #REF! | BA31: =VLOOKUP(H31,#REF!,25,0) -> #REF! | BB31: =VLOOKUP(H31,#REF!,26,0) -> #REF! | BC31: =VLOOKUP(H31,#REF!,27,0) -> #REF! | BD31: =VLOOKUP(H31,#REF!,29,0) -> #REF! | BE31: =VLOOKUP(H31,#REF!,30,0) -> #REF! | BF31: =VLOOKUP(H31,#REF!,31,0) -> #REF! | BG31: =VLOOKUP(H31,#REF!,32,0) -> #REF! | BH31: =VLOOKUP(H31,#REF!,33,0) -> #REF! | BI31: =VLOOKUP(H31,#REF!,34,0) -> #REF! | BJ31: =VLOOKUP(H31,#REF!,36,0) -> #REF! | BK31: =VLOOKUP(H31,#REF!,37,0) -> #REF! | BL31: =VLOOKUP(H31,#REF!,44,0) -> #REF! | BM31: =VLOOKUP(H31,#REF!,45,0) -> #REF! | BN31: =VLOOKUP(H31,#REF!,46,0) -> #REF! | BO31: =VLOOKUP(H31,#REF!,47,0) -> #REF! | BP31: =VLOOKUP(H31,#REF!,48,0) -> #REF!
A32: Mancomunidad | B32: Mancomunidad | C32: N | D32: 0 | E32: FICTICIO | F32: 350051 | G32: MANCOMUNIDAD MUNICIPAL Q'ANCHI DE LA PROVINCIA DE CANCHIS | H32: 350051 | I32: MANCOMUNIDAD MUNICIPAL Q'ANCHI DE LA PROVINCIA DE CANCHIS | J32: 08 | K32: CUSCO | L32: 6 | M32: CANCHIS | N32: 1 | O32: SICUANI | Q32: S | R32: S | W32: =IFERROR(VLOOKUP(H32,'IT PEI'!$X$2:$X$5647,1,0),"...") -> ... | X32: =_xlfn.XLOOKUP(H32,'IT PEI'!X$2:X$5647,'IT PEI'!E$2:E$5647,"...",2,-1) -> ... | Y32: =_xlfn.XLOOKUP(H32,'IT PEI'!X$2:X$5647,'IT PEI'!G$2:G$5647,"...",2,-1) -> ... | Z32: =_xlfn.XLOOKUP(H32,'IT PEI'!X$2:X$5647,'IT PEI'!F$2:F$5647,"...",2,-1) -> ... | AA32: =_xlfn.XLOOKUP(H32,'IT PEI'!X$2:X$5647,'IT PEI'!H$2:H$5647,"...",2,-1) -> ... | AB32: =_xlfn.XLOOKUP(H32,'IT PEI'!X$2:X$5647,'IT PEI'!O$2:O$5647,"...",2,-1) -> ... | AC32: =_xlfn.XLOOKUP(H32,'IT PEI'!X$2:X$5647,'IT PEI'!P$2:P$5647,"...",2,-1) -> ... | AD32: =_xlfn.XLOOKUP(H32,'IT PEI'!X$2:X$5647,'IT PEI'!Q$2:Q$5647,"...",2,-1) -> ... | AE32: =IF(COUNTIF(X32, "*" & "2030" & "*")>0, "SI", "No" ) -> No | AF32: =IF(COUNTIF(X32, "*" & "2030" & "*")>0, 1, 0 ) -> 0 | AG32: =IF(COUNTIF(X32, "*" & "2030" & "*")>0, 0, 1 ) -> 1 | AH32: =IF(AND(AA32="En Proceso",AE32="Si"),1,0) -> 0 | AI32: INACTIVO | AL32: =IFERROR(VLOOKUP(tbl_ues[[#This Row],[Id_UE]],'[1]Directorio v.02'!$H$3:$U$3089,11,FALSE),"") | AM32: =IFERROR(VLOOKUP(tbl_ues[[#This Row],[Id_UE]],'[1]Directorio v.02'!$H$3:$U$3089,12,FALSE),"") | AN32: =IFERROR(VLOOKUP(tbl_ues[[#This Row],[Id_UE]],'[1]Directorio v.02'!$H$3:$U$3089,13,FALSE),"") | AO32: =IFERROR(VLOOKUP(tbl_ues[[#This Row],[Id_UE]],'[1]Directorio v.02'!$H$3:$U$3089,14,FALSE),"") | AP32: =VLOOKUP(H32,#REF!,7,0) -> #REF! | AQ32: =VLOOKUP(H32,#REF!,9,0) -> #REF! | AR32: =VLOOKUP(H32,#REF!,15,0) -> #REF! | AS32: =VLOOKUP(H32,#REF!,16,0) -> #REF! | AT32: =VLOOKUP(H32,#REF!,17,0) -> #REF! | AU32: =VLOOKUP(H32,#REF!,18,0) -> #REF! | AV32: =VLOOKUP(H32,#REF!,19,0) -> #REF! | AW32: =VLOOKUP(H32,#REF!,20,0) -> #REF! | AX32: =VLOOKUP(H32,#REF!,22,0) -> #REF! | AY32: =VLOOKUP(H32,#REF!,23,0) -> #REF! | AZ32: =VLOOKUP(H32,#REF!,24,0) -> #REF! | BA32: =VLOOKUP(H32,#REF!,25,0) -> #REF! | BB32: =VLOOKUP(H32,#REF!,26,0) -> #REF! | BC32: =VLOOKUP(H32,#REF!,27,0) -> #REF! | BD32: =VLOOKUP(H32,#REF!,29,0) -> #REF! | BE32: =VLOOKUP(H32,#REF!,30,0) -> #REF! | BF32: =VLOOKUP(H32,#REF!,31,0) -> #REF! | BG32: =VLOOKUP(H32,#REF!,32,0) -> #REF! | BH32: =VLOOKUP(H32,#REF!,33,0) -> #REF! | BI32: =VLOOKUP(H32,#REF!,34,0) -> #REF! | BJ32: =VLOOKUP(H32,#REF!,36,0) -> #REF! | BK32: =VLOOKUP(H32,#REF!,37,0) -> #REF! | BL32: =VLOOKUP(H32,#REF!,44,0) -> #REF! | BM32: =VLOOKUP(H32,#REF!,45,0) -> #REF! | BN32: =VLOOKUP(H32,#REF!,46,0) -> #REF! | BO32: =VLOOKUP(H32,#REF!,47,0) -> #REF! | BP32: =VLOOKUP(H32,#REF!,48,0) -> #REF!
A33: Mancomunidad | B33: Mancomunidad | C33: N | D33: 0 | E33: FICTICIO | F33: 350050 | G33: MANCOMUNIDAD MUNICIPAL DE LAS CUENCAS DEL CHOTANO - CONCHANO "MANUEL JOSÉ BECERRA SILVA" | H33: 350050 | I33: MANCOMUNIDAD MUNICIPAL DE LAS CUENCAS DEL CHOTANO - CONCHANO "MANUEL JOSÉ BECERRA SILVA" | J33: 06 | K33: CAJAMARCA | L33: 4 | M33: CHOTA | N33: 1 | O33: CHOTA | Q33: S | R33: S | W33: =IFERROR(VLOOKUP(H33,'IT PEI'!$X$2:$X$5647,1,0),"...") -> ... | X33: =_xlfn.XLOOKUP(H33,'IT PEI'!X$2:X$5647,'IT PEI'!E$2:E$5647,"...",2,-1) -> ... | Y33: =_xlfn.XLOOKUP(H33,'IT PEI'!X$2:X$5647,'IT PEI'!G$2:G$5647,"...",2,-1) -> ... | Z33: =_xlfn.XLOOKUP(H33,'IT PEI'!X$2:X$5647,'IT PEI'!F$2:F$5647,"...",2,-1) -> ... | AA33: =_xlfn.XLOOKUP(H33,'IT PEI'!X$2:X$5647,'IT PEI'!H$2:H$5647,"...",2,-1) -> ... | AB33: =_xlfn.XLOOKUP(H33,'IT PEI'!X$2:X$5647,'IT PEI'!O$2:O$5647,"...",2,-1) -> ... | AC33: =_xlfn.XLOOKUP(H33,'IT PEI'!X$2:X$5647,'IT PEI'!P$2:P$5647,"...",2,-1) -> ... | AD33: =_xlfn.XLOOKUP(H33,'IT PEI'!X$2:X$5647,'IT PEI'!Q$2:Q$5647,"...",2,-1) -> ... | AE33: =IF(COUNTIF(X33, "*" & "2030" & "*")>0, "SI", "No" ) -> No | AF33: =IF(COUNTIF(X33, "*" & "2030" & "*")>0, 1, 0 ) -> 0 | AG33: =IF(COUNTIF(X33, "*" & "2030" & "*")>0, 0, 1 ) -> 1 | AH33: =IF(AND(AA33="En Proceso",AE33="Si"),1,0) -> 0 | AI33: INACTIVO | AL33: =IFERROR(VLOOKUP(tbl_ues[[#This Row],[Id_UE]],'[1]Directorio v.02'!$H$3:$U$3089,11,FALSE),"") | AM33: =IFERROR(VLOOKUP(tbl_ues[[#This Row],[Id_UE]],'[1]Directorio v.02'!$H$3:$U$3089,12,FALSE),"") | AN33: =IFERROR(VLOOKUP(tbl_ues[[#This Row],[Id_UE]],'[1]Directorio v.02'!$H$3:$U$3089,13,FALSE),"") | AO33: =IFERROR(VLOOKUP(tbl_ues[[#This Row],[Id_UE]],'[1]Directorio v.02'!$H$3:$U$3089,14,FALSE),"") | AP33: =VLOOKUP(H33,#REF!,7,0) -> #REF! | AQ33: =VLOOKUP(H33,#REF!,9,0) -> #REF! | AR33: =VLOOKUP(H33,#REF!,15,0) -> #REF! | AS33: =VLOOKUP(H33,#REF!,16,0) -> #REF! | AT33: =VLOOKUP(H33,#REF!,17,0) -> #REF! | AU33: =VLOOKUP(H33,#REF!,18,0) -> #REF! | AV33: =VLOOKUP(H33,#REF!,19,0) -> #REF! | AW33: =VLOOKUP(H33,#REF!,20,0) -> #REF! | AX33: =VLOOKUP(H33,#REF!,22,0) -> #REF! | AY33: =VLOOKUP(H33,#REF!,23,0) -> #REF! | AZ33: =VLOOKUP(H33,#REF!,24,0) -> #REF! | BA33: =VLOOKUP(H33,#REF!,25,0) -> #REF! | BB33: =VLOOKUP(H33,#REF!,26,0) -> #REF! | BC33: =VLOOKUP(H33,#REF!,27,0) -> #REF! | BD33: =VLOOKUP(H33,#REF!,29,0) -> #REF! | BE33: =VLOOKUP(H33,#REF!,30,0) -> #REF! | BF33: =VLOOKUP(H33,#REF!,31,0) -> #REF! | BG33: =VLOOKUP(H33,#REF!,32,0) -> #REF! | BH33: =VLOOKUP(H33,#REF!,33,0) -> #REF! | BI33: =VLOOKUP(H33,#REF!,34,0) -> #REF! | BJ33: =VLOOKUP(H33,#REF!,36,0) -> #REF! | BK33: =VLOOKUP(H33,#REF!,37,0) -> #REF! | BL33: =VLOOKUP(H33,#REF!,44,0) -> #REF! | BM33: =VLOOKUP(H33,#REF!,45,0) -> #REF! | BN33: =VLOOKUP(H33,#REF!,46,0) -> #REF! | BO33: =VLOOKUP(H33,#REF!,47,0) -> #REF! | BP33: =VLOOKUP(H33,#REF!,48,0) -> #REF!
A34: Mancomunidad | B34: Mancomunidad | C34: N | D34: 0 | E34: FICTICIO | F34: 350049 | G34: MANCOMUNIDAD MUNICIPAL LIMA SUR | H34: 350049 | I34: MANCOMUNIDAD MUNICIPAL LIMA SUR | J34: 15 | K34: LIMA | L34: 1 | M34: LIMA | N34: 43 | O34: VILLA MARIA DEL TRIUNFO | Q34: S | R34: S | W34: =IFERROR(VLOOKUP(H34,'IT PEI'!$X$2:$X$5647,1,0),"...") -> ... | X34: =_xlfn.XLOOKUP(H34,'IT PEI'!X$2:X$5647,'IT PEI'!E$2:E$5647,"...",2,-1) -> ... | Y34: =_xlfn.XLOOKUP(H34,'IT PEI'!X$2:X$5647,'IT PEI'!G$2:G$5647,"...",2,-1) -> ... | Z34: =_xlfn.XLOOKUP(H34,'IT PEI'!X$2:X$5647,'IT PEI'!F$2:F$5647,"...",2,-1) -> ... | AA34: =_xlfn.XLOOKUP(H34,'IT PEI'!X$2:X$5647,'IT PEI'!H$2:H$5647,"...",2,-1) -> ... | AB34: =_xlfn.XLOOKUP(H34,'IT PEI'!X$2:X$5647,'IT PEI'!O$2:O$5647,"...",2,-1) -> ... | AC34: =_xlfn.XLOOKUP(H34,'IT PEI'!X$2:X$5647,'IT PEI'!P$2:P$5647,"...",2,-1) -> ... | AD34: =_xlfn.XLOOKUP(H34,'IT PEI'!X$2:X$5647,'IT PEI'!Q$2:Q$5647,"...",2,-1) -> ... | AE34: =IF(COUNTIF(X34, "*" & "2030" & "*")>0, "SI", "No" ) -> No | AF34: =IF(COUNTIF(X34, "*" & "2030" & "*")>0, 1, 0 ) -> 0 | AG34: =IF(COUNTIF(X34, "*" & "2030" & "*")>0, 0, 1 ) -> 1 | AH34: =IF(AND(AA34="En Proceso",AE34="Si"),1,0) -> 0 | AI34: INACTIVO | AL34: =IFERROR(VLOOKUP(tbl_ues[[#This Row],[Id_UE]],'[1]Directorio v.02'!$H$3:$U$3089,11,FALSE),"") | AM34: =IFERROR(VLOOKUP(tbl_ues[[#This Row],[Id_UE]],'[1]Directorio v.02'!$H$3:$U$3089,12,FALSE),"") | AN34: =IFERROR(VLOOKUP(tbl_ues[[#This Row],[Id_UE]],'[1]Directorio v.02'!$H$3:$U$3089,13,FALSE),"") | AO34: =IFERROR(VLOOKUP(tbl_ues[[#This Row],[Id_UE]],'[1]Directorio v.02'!$H$3:$U$3089,14,FALSE),"") | AP34: =VLOOKUP(H34,#REF!,7,0) -> #REF! | AQ34: =VLOOKUP(H34,#REF!,9,0) -> #REF! | AR34: =VLOOKUP(H34,#REF!,15,0) -> #REF! | AS34: =VLOOKUP(H34,#REF!,16,0) -> #REF! | AT34: =VLOOKUP(H34,#REF!,17,0) -> #REF! | AU34: =VLOOKUP(H34,#REF!,18,0) -> #REF! | AV34: =VLOOKUP(H34,#REF!,19,0) -> #REF! | AW34: =VLOOKUP(H34,#REF!,20,0) -> #REF! | AX34: =VLOOKUP(H34,#REF!,22,0) -> #REF! | AY34: =VLOOKUP(H34,#REF!,23,0) -> #REF! | AZ34: =VLOOKUP(H34,#REF!,24,0) -> #REF! | BA34: =VLOOKUP(H34,#REF!,25,0) -> #REF! | BB34: =VLOOKUP(H34,#REF!,26,0) -> #REF! | BC34: =VLOOKUP(H34,#REF!,27,0) -> #REF! | BD34: =VLOOKUP(H34,#REF!,29,0) -> #REF! | BE34: =VLOOKUP(H34,#REF!,30,0) -> #REF! | BF34: =VLOOKUP(H34,#REF!,31,0) -> #REF! | BG34: =VLOOKUP(H34,#REF!,32,0) -> #REF! | BH34: =VLOOKUP(H34,#REF!,33,0) -> #REF! | BI34: =VLOOKUP(H34,#REF!,34,0) -> #REF! | BJ34: =VLOOKUP(H34,#REF!,36,0) -> #REF! | BK34: =VLOOKUP(H34,#REF!,37,0) -> #REF! | BL34: =VLOOKUP(H34,#REF!,44,0) -> #REF! | BM34: =VLOOKUP(H34,#REF!,45,0) -> #REF! | BN34: =VLOOKUP(H34,#REF!,46,0) -> #REF! | BO34: =VLOOKUP(H34,#REF!,47,0) -> #REF! | BP34: =VLOOKUP(H34,#REF!,48,0) -> #REF!
A35: Mancomunidad | B35: Mancomunidad | C35: N | D35: 0 | E35: FICTICIO | F35: 350048 | G35: MANCOMUNIDAD MUNICIPAL FORESTACION SIN FRONTERAS | H35: 350048 | I35: MANCOMUNIDAD MUNICIPAL FORESTACION SIN FRONTERAS | J35: 11 | K35: ICA | L35: 2 | M35: CHINCHA | N35: 7 | O35: PUEBLO NUEVO | Q35: S | R35: S | W35: =IFERROR(VLOOKUP(H35,'IT PEI'!$X$2:$X$5647,1,0),"...") -> ... | X35: =_xlfn.XLOOKUP(H35,'IT PEI'!X$2:X$5647,'IT PEI'!E$2:E$5647,"...",2,-1) -> ... | Y35: =_xlfn.XLOOKUP(H35,'IT PEI'!X$2:X$5647,'IT PEI'!G$2:G$5647,"...",2,-1) -> ... | Z35: =_xlfn.XLOOKUP(H35,'IT PEI'!X$2:X$5647,'IT PEI'!F$2:F$5647,"...",2,-1) -> ... | AA35: =_xlfn.XLOOKUP(H35,'IT PEI'!X$2:X$5647,'IT PEI'!H$2:H$5647,"...",2,-1) -> ... | AB35: =_xlfn.XLOOKUP(H35,'IT PEI'!X$2:X$5647,'IT PEI'!O$2:O$5647,"...",2,-1) -> ... | AC35: =_xlfn.XLOOKUP(H35,'IT PEI'!X$2:X$5647,'IT PEI'!P$2:P$5647,"...",2,-1) -> ... | AD35: =_xlfn.XLOOKUP(H35,'IT PEI'!X$2:X$5647,'IT PEI'!Q$2:Q$5647,"...",2,-1) -> ... | AE35: =IF(COUNTIF(X35, "*" & "2030" & "*")>0, "SI", "No" ) -> No | AF35: =IF(COUNTIF(X35, "*" & "2030" & "*")>0, 1, 0 ) -> 0 | AG35: =IF(COUNTIF(X35, "*" & "2030" & "*")>0, 0, 1 ) -> 1 | AH35: =IF(AND(AA35="En Proceso",AE35="Si"),1,0) -> 0 | AI35: INACTIVO | AL35: =IFERROR(VLOOKUP(tbl_ues[[#This Row],[Id_UE]],'[1]Directorio v.02'!$H$3:$U$3089,11,FALSE),"") | AM35: =IFERROR(VLOOKUP(tbl_ues[[#This Row],[Id_UE]],'[1]Directorio v.02'!$H$3:$U$3089,12,FALSE),"") | AN35: =IFERROR(VLOOKUP(tbl_ues[[#This Row],[Id_UE]],'[1]Directorio v.02'!$H$3:$U$3089,13,FALSE),"") | AO35: =IFERROR(VLOOKUP(tbl_ues[[#This Row],[Id_UE]],'[1]Directorio v.02'!$H$3:$U$3089,14,FALSE),"") | AP35: =VLOOKUP(H35,#REF!,7,0) -> #REF! | AQ35: =VLOOKUP(H35,#REF!,9,0) -> #REF! | AR35: =VLOOKUP(H35,#REF!,15,0) -> #REF! | AS35: =VLOOKUP(H35,#REF!,16,0) -> #REF! | AT35: =VLOOKUP(H35,#REF!,17,0) -> #REF! | AU35: =VLOOKUP(H35,#REF!,18,0) -> #REF! | AV35: =VLOOKUP(H35,#REF!,19,0) -> #REF! | AW35: =VLOOKUP(H35,#REF!,20,0) -> #REF! | AX35: =VLOOKUP(H35,#REF!,22,0) -> #REF! | AY35: =VLOOKUP(H35,#REF!,23,0) -> #REF! | AZ35: =VLOOKUP(H35,#REF!,24,0) -> #REF! | BA35: =VLOOKUP(H35,#REF!,25,0) -> #REF! | BB35: =VLOOKUP(H35,#REF!,26,0) -> #REF! | BC35: =VLOOKUP(H35,#REF!,27,0) -> #REF! | BD35: =VLOOKUP(H35,#REF!,29,0) -> #REF! | BE35: =VLOOKUP(H35,#REF!,30,0) -> #REF! | BF35: =VLOOKUP(H35,#REF!,31,0) -> #REF! | BG35: =VLOOKUP(H35,#REF!,32,0) -> #REF! | BH35: =VLOOKUP(H35,#REF!,33,0) -> #REF! | BI35: =VLOOKUP(H35,#REF!,34,0) -> #REF! | BJ35: =VLOOKUP(H35,#REF!,36,0) -> #REF! | BK35: =VLOOKUP(H35,#REF!,37,0) -> #REF! | BL35: =VLOOKUP(H35,#REF!,44,0) -> #REF! | BM35: =VLOOKUP(H35,#REF!,45,0) -> #REF! | BN35: =VLOOKUP(H35,#REF!,46,0) -> #REF! | BO35: =VLOOKUP(H35,#REF!,47,0) -> #REF! | BP35: =VLOOKUP(H35,#REF!,48,0) -> #REF!
A36: Mancomunidad | B36: Mancomunidad | C36: N | D36: 0 | E36: FICTICIO | F36: 350047 | G36: MANCOMUNIDAD MUNICIPAL DE LOS DISTRITOS DE OXAPAMPA | H36: 350047 | I36: MANCOMUNIDAD MUNICIPAL DE LOS DISTRITOS DE OXAPAMPA | J36: 19 | K36: PASCO | L36: 3 | M36: OXAPAMPA | N36: 7 | O36: VILLA RICA | Q36: S | R36: S | W36: =IFERROR(VLOOKUP(H36,'IT PEI'!$X$2:$X$5647,1,0),"...") -> ... | X36: =_xlfn.XLOOKUP(H36,'IT PEI'!X$2:X$5647,'IT PEI'!E$2:E$5647,"...",2,-1) -> ... | Y36: =_xlfn.XLOOKUP(H36,'IT PEI'!X$2:X$5647,'IT PEI'!G$2:G$5647,"...",2,-1) -> ... | Z36: =_xlfn.XLOOKUP(H36,'IT PEI'!X$2:X$5647,'IT PEI'!F$2:F$5647,"...",2,-1) -> ... | AA36: =_xlfn.XLOOKUP(H36,'IT PEI'!X$2:X$5647,'IT PEI'!H$2:H$5647,"...",2,-1) -> ... | AB36: =_xlfn.XLOOKUP(H36,'IT PEI'!X$2:X$5647,'IT PEI'!O$2:O$5647,"...",2,-1) -> ... | AC36: =_xlfn.XLOOKUP(H36,'IT PEI'!X$2:X$5647,'IT PEI'!P$2:P$5647,"...",2,-1) -> ... | AD36: =_xlfn.XLOOKUP(H36,'IT PEI'!X$2:X$5647,'IT PEI'!Q$2:Q$5647,"...",2,-1) -> ... | AE36: =IF(COUNTIF(X36, "*" & "2030" & "*")>0, "SI", "No" ) -> No | AF36: =IF(COUNTIF(X36, "*" & "2030" & "*")>0, 1, 0 ) -> 0 | AG36: =IF(COUNTIF(X36, "*" & "2030" & "*")>0, 0, 1 ) -> 1 | AH36: =IF(AND(AA36="En Proceso",AE36="Si"),1,0) -> 0 | AI36: INACTIVO | AL36: =IFERROR(VLOOKUP(tbl_ues[[#This Row],[Id_UE]],'[1]Directorio v.02'!$H$3:$U$3089,11,FALSE),"") | AM36: =IFERROR(VLOOKUP(tbl_ues[[#This Row],[Id_UE]],'[1]Directorio v.02'!$H$3:$U$3089,12,FALSE),"") | AN36: =IFERROR(VLOOKUP(tbl_ues[[#This Row],[Id_UE]],'[1]Directorio v.02'!$H$3:$U$3089,13,FALSE),"") | AO36: =IFERROR(VLOOKUP(tbl_ues[[#This Row],[Id_UE]],'[1]Directorio v.02'!$H$3:$U$3089,14,FALSE),"") | AP36: =VLOOKUP(H36,#REF!,7,0) -> #REF! | AQ36: =VLOOKUP(H36,#REF!,9,0) -> #REF! | AR36: =VLOOKUP(H36,#REF!,15,0) -> #REF! | AS36: =VLOOKUP(H36,#REF!,16,0) -> #REF! | AT36: =VLOOKUP(H36,#REF!,17,0) -> #REF! | AU36: =VLOOKUP(H36,#REF!,18,0) -> #REF! | AV36: =VLOOKUP(H36,#REF!,19,0) -> #REF! | AW36: =VLOOKUP(H36,#REF!,20,0) -> #REF! | AX36: =VLOOKUP(H36,#REF!,22,0) -> #REF! | AY36: =VLOOKUP(H36,#REF!,23,0) -> #REF! | AZ36: =VLOOKUP(H36,#REF!,24,0) -> #REF! | BA36: =VLOOKUP(H36,#REF!,25,0) -> #REF! | BB36: =VLOOKUP(H36,#REF!,26,0) -> #REF! | BC36: =VLOOKUP(H36,#REF!,27,0) -> #REF! | BD36: =VLOOKUP(H36,#REF!,29,0) -> #REF! | BE36: =VLOOKUP(H36,#REF!,30,0) -> #REF! | BF36: =VLOOKUP(H36,#REF!,31,0) -> #REF! | BG36: =VLOOKUP(H36,#REF!,32,0) -> #REF! | BH36: =VLOOKUP(H36,#REF!,33,0) -> #REF! | BI36: =VLOOKUP(H36,#REF!,34,0) -> #REF! | BJ36: =VLOOKUP(H36,#REF!,36,0) -> #REF! | BK36: =VLOOKUP(H36,#REF!,37,0) -> #REF! | BL36: =VLOOKUP(H36,#REF!,44,0) -> #REF! | BM36: =VLOOKUP(H36,#REF!,45,0) -> #REF! | BN36: =VLOOKUP(H36,#REF!,46,0) -> #REF! | BO36: =VLOOKUP(H36,#REF!,47,0) -> #REF! | BP36: =VLOOKUP(H36,#REF!,48,0) -> #REF!
A37: Mancomunidad | B37: Mancomunidad | C37: N | D37: 0 | E37: FICTICIO | F37: 350046 | G37: MANCOMUNIDAD MUNICIPAL CIRCUITO MOCHICA | H37: 350046 | I37: MANCOMUNIDAD MUNICIPAL CIRCUITO MOCHICA | J37: 14 | K37: LAMBAYEQUE | L37: 1 | M37: CHICLAYO | N37: 1 | O37: CHICLAYO | Q37: S | R37: S | W37: =IFERROR(VLOOKUP(H37,'IT PEI'!$X$2:$X$5647,1,0),"...") -> ... | X37: =_xlfn.XLOOKUP(H37,'IT PEI'!X$2:X$5647,'IT PEI'!E$2:E$5647,"...",2,-1) -> ... | Y37: =_xlfn.XLOOKUP(H37,'IT PEI'!X$2:X$5647,'IT PEI'!G$2:G$5647,"...",2,-1) -> ... | Z37: =_xlfn.XLOOKUP(H37,'IT PEI'!X$2:X$5647,'IT PEI'!F$2:F$5647,"...",2,-1) -> ... | AA37: =_xlfn.XLOOKUP(H37,'IT PEI'!X$2:X$5647,'IT PEI'!H$2:H$5647,"...",2,-1) -> ... | AB37: =_xlfn.XLOOKUP(H37,'IT PEI'!X$2:X$5647,'IT PEI'!O$2:O$5647,"...",2,-1) -> ... | AC37: =_xlfn.XLOOKUP(H37,'IT PEI'!X$2:X$5647,'IT PEI'!P$2:P$5647,"...",2,-1) -> ... | AD37: =_xlfn.XLOOKUP(H37,'IT PEI'!X$2:X$5647,'IT PEI'!Q$2:Q$5647,"...",2,-1) -> ... | AE37: =IF(COUNTIF(X37, "*" & "2030" & "*")>0, "SI", "No" ) -> No | AF37: =IF(COUNTIF(X37, "*" & "2030" & "*")>0, 1, 0 ) -> 0 | AG37: =IF(COUNTIF(X37, "*" & "2030" & "*")>0, 0, 1 ) -> 1 | AH37: =IF(AND(AA37="En Proceso",AE37="Si"),1,0) -> 0 | AI37: INACTIVO | AL37: =IFERROR(VLOOKUP(tbl_ues[[#This Row],[Id_UE]],'[1]Directorio v.02'!$H$3:$U$3089,11,FALSE),"") | AM37: =IFERROR(VLOOKUP(tbl_ues[[#This Row],[Id_UE]],'[1]Directorio v.02'!$H$3:$U$3089,12,FALSE),"") | AN37: =IFERROR(VLOOKUP(tbl_ues[[#This Row],[Id_UE]],'[1]Directorio v.02'!$H$3:$U$3089,13,FALSE),"") | AO37: =IFERROR(VLOOKUP(tbl_ues[[#This Row],[Id_UE]],'[1]Directorio v.02'!$H$3:$U$3089,14,FALSE),"") | AP37: =VLOOKUP(H37,#REF!,7,0) -> #REF! | AQ37: =VLOOKUP(H37,#REF!,9,0) -> #REF! | AR37: =VLOOKUP(H37,#REF!,15,0) -> #REF! | AS37: =VLOOKUP(H37,#REF!,16,0) -> #REF! | AT37: =VLOOKUP(H37,#REF!,17,0) -> #REF! | AU37: =VLOOKUP(H37,#REF!,18,0) -> #REF! | AV37: =VLOOKUP(H37,#REF!,19,0) -> #REF! | AW37: =VLOOKUP(H37,#REF!,20,0) -> #REF! | AX37: =VLOOKUP(H37,#REF!,22,0) -> #REF! | AY37: =VLOOKUP(H37,#REF!,23,0) -> #REF! | AZ37: =VLOOKUP(H37,#REF!,24,0) -> #REF! | BA37: =VLOOKUP(H37,#REF!,25,0) -> #REF! | BB37: =VLOOKUP(H37,#REF!,26,0) -> #REF! | BC37: =VLOOKUP(H37,#REF!,27,0) -> #REF! | BD37: =VLOOKUP(H37,#REF!,29,0) -> #REF! | BE37: =VLOOKUP(H37,#REF!,30,0) -> #REF! | BF37: =VLOOKUP(H37,#REF!,31,0) -> #REF! | BG37: =VLOOKUP(H37,#REF!,32,0) -> #REF! | BH37: =VLOOKUP(H37,#REF!,33,0) -> #REF! | BI37: =VLOOKUP(H37,#REF!,34,0) -> #REF! | BJ37: =VLOOKUP(H37,#REF!,36,0) -> #REF! | BK37: =VLOOKUP(H37,#REF!,37,0) -> #REF! | BL37: =VLOOKUP(H37,#REF!,44,0) -> #REF! | BM37: =VLOOKUP(H37,#REF!,45,0) -> #REF! | BN37: =VLOOKUP(H37,#REF!,46,0) -> #REF! | BO37: =VLOOKUP(H37,#REF!,47,0) -> #REF! | BP37: =VLOOKUP(H37,#REF!,48,0) -> #REF!
A38: Mancomunidad | B38: Mancomunidad | C38: N | D38: 0 | E38: FICTICIO | F38: 350045 | G38: MANCOMUNIDAD MUNICIPAL TRES CUENCAS: SANTA- FORTALEZA - PATIVILCA | H38: 350045 | I38: MANCOMUNIDAD MUNICIPAL TRES CUENCAS: SANTA- FORTALEZA - PATIVILCA | J38: 02 | K38: ANCASH | L38: 5 | M38: BOLOGNESI | N38: 1 | O38: CHIQUIAN | Q38: S | R38: S | W38: =IFERROR(VLOOKUP(H38,'IT PEI'!$X$2:$X$5647,1,0),"...") -> ... | X38: =_xlfn.XLOOKUP(H38,'IT PEI'!X$2:X$5647,'IT PEI'!E$2:E$5647,"...",2,-1) -> ... | Y38: =_xlfn.XLOOKUP(H38,'IT PEI'!X$2:X$5647,'IT PEI'!G$2:G$5647,"...",2,-1) -> ... | Z38: =_xlfn.XLOOKUP(H38,'IT PEI'!X$2:X$5647,'IT PEI'!F$2:F$5647,"...",2,-1) -> ... | AA38: =_xlfn.XLOOKUP(H38,'IT PEI'!X$2:X$5647,'IT PEI'!H$2:H$5647,"...",2,-1) -> ... | AB38: =_xlfn.XLOOKUP(H38,'IT PEI'!X$2:X$5647,'IT PEI'!O$2:O$5647,"...",2,-1) -> ... | AC38: =_xlfn.XLOOKUP(H38,'IT PEI'!X$2:X$5647,'IT PEI'!P$2:P$5647,"...",2,-1) -> ... | AD38: =_xlfn.XLOOKUP(H38,'IT PEI'!X$2:X$5647,'IT PEI'!Q$2:Q$5647,"...",2,-1) -> ... | AE38: =IF(COUNTIF(X38, "*" & "2030" & "*")>0, "SI", "No" ) -> No | AF38: =IF(COUNTIF(X38, "*" & "2030" & "*")>0, 1, 0 ) -> 0 | AG38: =IF(COUNTIF(X38, "*" & "2030" & "*")>0, 0, 1 ) -> 1 | AH38: =IF(AND(AA38="En Proceso",AE38="Si"),1,0) -> 0 | AI38: INACTIVO | AL38: =IFERROR(VLOOKUP(tbl_ues[[#This Row],[Id_UE]],'[1]Directorio v.02'!$H$3:$U$3089,11,FALSE),"") | AM38: =IFERROR(VLOOKUP(tbl_ues[[#This Row],[Id_UE]],'[1]Directorio v.02'!$H$3:$U$3089,12,FALSE),"") | AN38: =IFERROR(VLOOKUP(tbl_ues[[#This Row],[Id_UE]],'[1]Directorio v.02'!$H$3:$U$3089,13,FALSE),"") | AO38: =IFERROR(VLOOKUP(tbl_ues[[#This Row],[Id_UE]],'[1]Directorio v.02'!$H$3:$U$3089,14,FALSE),"") | AP38: =VLOOKUP(H38,#REF!,7,0) -> #REF! | AQ38: =VLOOKUP(H38,#REF!,9,0) -> #REF! | AR38: =VLOOKUP(H38,#REF!,15,0) -> #REF! | AS38: =VLOOKUP(H38,#REF!,16,0) -> #REF! | AT38: =VLOOKUP(H38,#REF!,17,0) -> #REF! | AU38: =VLOOKUP(H38,#REF!,18,0) -> #REF! | AV38: =VLOOKUP(H38,#REF!,19,0) -> #REF! | AW38: =VLOOKUP(H38,#REF!,20,0) -> #REF! | AX38: =VLOOKUP(H38,#REF!,22,0) -> #REF! | AY38: =VLOOKUP(H38,#REF!,23,0) -> #REF! | AZ38: =VLOOKUP(H38,#REF!,24,0) -> #REF! | BA38: =VLOOKUP(H38,#REF!,25,0) -> #REF! | BB38: =VLOOKUP(H38,#REF!,26,0) -> #REF! | BC38: =VLOOKUP(H38,#REF!,27,0) -> #REF! | BD38: =VLOOKUP(H38,#REF!,29,0) -> #REF! | BE38: =VLOOKUP(H38,#REF!,30,0) -> #REF! | BF38: =VLOOKUP(H38,#REF!,31,0) -> #REF! | BG38: =VLOOKUP(H38,#REF!,32,0) -> #REF! | BH38: =VLOOKUP(H38,#REF!,33,0) -> #REF! | BI38: =VLOOKUP(H38,#REF!,34,0) -> #REF! | BJ38: =VLOOKUP(H38,#REF!,36,0) -> #REF! | BK38: =VLOOKUP(H38,#REF!,37,0) -> #REF! | BL38: =VLOOKUP(H38,#REF!,44,0) -> #REF! | BM38: =VLOOKUP(H38,#REF!,45,0) -> #REF! | BN38: =VLOOKUP(H38,#REF!,46,0) -> #REF! | BO38: =VLOOKUP(H38,#REF!,47,0) -> #REF! | BP38: =VLOOKUP(H38,#REF!,48,0) -> #REF!
A39: Mancomunidad | B39: Mancomunidad | C39: N | D39: 0 | E39: FICTICIO | F39: 350044 | G39: MANCOMUNIDAD MUNICIPAL DEL VALLE DE YANAMARCA | H39: 350044 | I39: MANCOMUNIDAD MUNICIPAL DEL VALLE DE YANAMARCA | J39: 12 | K39: JUNIN | L39: 4 | M39: JAUJA | N39: 2 | O39: ACOLLA | Q39: S | R39: S | W39: =IFERROR(VLOOKUP(H39,'IT PEI'!$X$2:$X$5647,1,0),"...") -> ... | X39: =_xlfn.XLOOKUP(H39,'IT PEI'!X$2:X$5647,'IT PEI'!E$2:E$5647,"...",2,-1) -> ... | Y39: =_xlfn.XLOOKUP(H39,'IT PEI'!X$2:X$5647,'IT PEI'!G$2:G$5647,"...",2,-1) -> ... | Z39: =_xlfn.XLOOKUP(H39,'IT PEI'!X$2:X$5647,'IT PEI'!F$2:F$5647,"...",2,-1) -> ... | AA39: =_xlfn.XLOOKUP(H39,'IT PEI'!X$2:X$5647,'IT PEI'!H$2:H$5647,"...",2,-1) -> ... | AB39: =_xlfn.XLOOKUP(H39,'IT PEI'!X$2:X$5647,'IT PEI'!O$2:O$5647,"...",2,-1) -> ... | AC39: =_xlfn.XLOOKUP(H39,'IT PEI'!X$2:X$5647,'IT PEI'!P$2:P$5647,"...",2,-1) -> ... | AD39: =_xlfn.XLOOKUP(H39,'IT PEI'!X$2:X$5647,'IT PEI'!Q$2:Q$5647,"...",2,-1) -> ... | AE39: =IF(COUNTIF(X39, "*" & "2030" & "*")>0, "SI", "No" ) -> No | AF39: =IF(COUNTIF(X39, "*" & "2030" & "*")>0, 1, 0 ) -> 0 | AG39: =IF(COUNTIF(X39, "*" & "2030" & "*")>0, 0, 1 ) -> 1 | AH39: =IF(AND(AA39="En Proceso",AE39="Si"),1,0) -> 0 | AI39: INACTIVO | AL39: =IFERROR(VLOOKUP(tbl_ues[[#This Row],[Id_UE]],'[1]Directorio v.02'!$H$3:$U$3089,11,FALSE),"") | AM39: =IFERROR(VLOOKUP(tbl_ues[[#This Row],[Id_UE]],'[1]Directorio v.02'!$H$3:$U$3089,12,FALSE),"") | AN39: =IFERROR(VLOOKUP(tbl_ues[[#This Row],[Id_UE]],'[1]Directorio v.02'!$H$3:$U$3089,13,FALSE),"") | AO39: =IFERROR(VLOOKUP(tbl_ues[[#This Row],[Id_UE]],'[1]Directorio v.02'!$H$3:$U$3089,14,FALSE),"") | AP39: =VLOOKUP(H39,#REF!,7,0) -> #REF! | AQ39: =VLOOKUP(H39,#REF!,9,0) -> #REF! | AR39: =VLOOKUP(H39,#REF!,15,0) -> #REF! | AS39: =VLOOKUP(H39,#REF!,16,0) -> #REF! | AT39: =VLOOKUP(H39,#REF!,17,0) -> #REF! | AU39: =VLOOKUP(H39,#REF!,18,0) -> #REF! | AV39: =VLOOKUP(H39,#REF!,19,0) -> #REF! | AW39: =VLOOKUP(H39,#REF!,20,0) -> #REF! | AX39: =VLOOKUP(H39,#REF!,22,0) -> #REF! | AY39: =VLOOKUP(H39,#REF!,23,0) -> #REF! | AZ39: =VLOOKUP(H39,#REF!,24,0) -> #REF! | BA39: =VLOOKUP(H39,#REF!,25,0) -> #REF! | BB39: =VLOOKUP(H39,#REF!,26,0) -> #REF! | BC39: =VLOOKUP(H39,#REF!,27,0) -> #REF! | BD39: =VLOOKUP(H39,#REF!,29,0) -> #REF! | BE39: =VLOOKUP(H39,#REF!,30,0) -> #REF! | BF39: =VLOOKUP(H39,#REF!,31,0) -> #REF! | BG39: =VLOOKUP(H39,#REF!,32,0) -> #REF! | BH39: =VLOOKUP(H39,#REF!,33,0) -> #REF! | BI39: =VLOOKUP(H39,#REF!,34,0) -> #REF! | BJ39: =VLOOKUP(H39,#REF!,36,0) -> #REF! | BK39: =VLOOKUP(H39,#REF!,37,0) -> #REF! | BL39: =VLOOKUP(H39,#REF!,44,0) -> #REF! | BM39: =VLOOKUP(H39,#REF!,45,0) -> #REF! | BN39: =VLOOKUP(H39,#REF!,46,0) -> #REF! | BO39: =VLOOKUP(H39,#REF!,47,0) -> #REF! | BP39: =VLOOKUP(H39,#REF!,48,0) -> #REF!
A40: Mancomunidad | B40: Mancomunidad | C40: N | D40: 0 | E40: FICTICIO | F40: 350043 | G40: MANCOMUNIDAD MUNICIPAL CUENCA DEL RIO CUMBAZA | H40: 350043 | I40: MANCOMUNIDAD MUNICIPAL CUENCA DEL RIO CUMBAZA | J40: 22 | K40: SAN MARTIN | L40: 9 | M40: SAN MARTIN | N40: 1 | O40: TARAPOTO | Q40: S | R40: S | W40: =IFERROR(VLOOKUP(H40,'IT PEI'!$X$2:$X$5647,1,0),"...") -> ... | X40: =_xlfn.XLOOKUP(H40,'IT PEI'!X$2:X$5647,'IT PEI'!E$2:E$5647,"...",2,-1) -> ... | Y40: =_xlfn.XLOOKUP(H40,'IT PEI'!X$2:X$5647,'IT PEI'!G$2:G$5647,"...",2,-1) -> ... | Z40: =_xlfn.XLOOKUP(H40,'IT PEI'!X$2:X$5647,'IT PEI'!F$2:F$5647,"...",2,-1) -> ... | AA40: =_xlfn.XLOOKUP(H40,'IT PEI'!X$2:X$5647,'IT PEI'!H$2:H$5647,"...",2,-1) -> ... | AB40: =_xlfn.XLOOKUP(H40,'IT PEI'!X$2:X$5647,'IT PEI'!O$2:O$5647,"...",2,-1) -> ... | AC40: =_xlfn.XLOOKUP(H40,'IT PEI'!X$2:X$5647,'IT PEI'!P$2:P$5647,"...",2,-1) -> ... | AD40: =_xlfn.XLOOKUP(H40,'IT PEI'!X$2:X$5647,'IT PEI'!Q$2:Q$5647,"...",2,-1) -> ... | AE40: =IF(COUNTIF(X40, "*" & "2030" & "*")>0, "SI", "No" ) -> No | AF40: =IF(COUNTIF(X40, "*" & "2030" & "*")>0, 1, 0 ) -> 0 | AG40: =IF(COUNTIF(X40, "*" & "2030" & "*")>0, 0, 1 ) -> 1 | AH40: =IF(AND(AA40="En Proceso",AE40="Si"),1,0) -> 0 | AI40: INACTIVO | AL40: =IFERROR(VLOOKUP(tbl_ues[[#This Row],[Id_UE]],'[1]Directorio v.02'!$H$3:$U$3089,11,FALSE),"") | AM40: =IFERROR(VLOOKUP(tbl_ues[[#This Row],[Id_UE]],'[1]Directorio v.02'!$H$3:$U$3089,12,FALSE),"") | AN40: =IFERROR(VLOOKUP(tbl_ues[[#This Row],[Id_UE]],'[1]Directorio v.02'!$H$3:$U$3089,13,FALSE),"") | AO40: =IFERROR(VLOOKUP(tbl_ues[[#This Row],[Id_UE]],'[1]Directorio v.02'!$H$3:$U$3089,14,FALSE),"") | AP40: =VLOOKUP(H40,#REF!,7,0) -> #REF! | AQ40: =VLOOKUP(H40,#REF!,9,0) -> #REF! | AR40: =VLOOKUP(H40,#REF!,15,0) -> #REF! | AS40: =VLOOKUP(H40,#REF!,16,0) -> #REF! | AT40: =VLOOKUP(H40,#REF!,17,0) -> #REF! | AU40: =VLOOKUP(H40,#REF!,18,0) -> #REF! | AV40: =VLOOKUP(H40,#REF!,19,0) -> #REF! | AW40: =VLOOKUP(H40,#REF!,20,0) -> #REF! | AX40: =VLOOKUP(H40,#REF!,22,0) -> #REF! | AY40: =VLOOKUP(H40,#REF!,23,0) -> #REF! | AZ40: =VLOOKUP(H40,#REF!,24,0) -> #REF! | BA40: =VLOOKUP(H40,#REF!,25,0) -> #REF! | BB40: =VLOOKUP(H40,#REF!,26,0) -> #REF! | BC40: =VLOOKUP(H40,#REF!,27,0) -> #REF! | BD40: =VLOOKUP(H40,#REF!,29,0) -> #REF! | BE40: =VLOOKUP(H40,#REF!,30,0) -> #REF! | BF40: =VLOOKUP(H40,#REF!,31,0) -> #REF! | BG40: =VLOOKUP(H40,#REF!,32,0) -> #REF! | BH40: =VLOOKUP(H40,#REF!,33,0) -> #REF! | BI40: =VLOOKUP(H40,#REF!,34,0) -> #REF! | BJ40: =VLOOKUP(H40,#REF!,36,0) -> #REF! | BK40: =VLOOKUP(H40,#REF!,37,0) -> #REF! | BL40: =VLOOKUP(H40,#REF!,44,0) -> #REF! | BM40: =VLOOKUP(H40,#REF!,45,0) -> #REF! | BN40: =VLOOKUP(H40,#REF!,46,0) -> #REF! | BO40: =VLOOKUP(H40,#REF!,47,0) -> #REF! | BP40: =VLOOKUP(H40,#REF!,48,0) -> #REF!
A41: Mancomunidad | B41: Mancomunidad | C41: N | D41: 0 | E41: FICTICIO | F41: 350042 | G41: MANCOMUNIDAD MUNICIPAL WARAQ | H41: 350042 | I41: MANCOMUNIDAD MUNICIPAL WARAQ | J41: 02 | K41: ANCASH | L41: 1 | M41: HUARAZ | N41: 5 | O41: INDEPENDENCIA | Q41: S | R41: S | W41: =IFERROR(VLOOKUP(H41,'IT PEI'!$X$2:$X$5647,1,0),"...") -> ... | X41: =_xlfn.XLOOKUP(H41,'IT PEI'!X$2:X$5647,'IT PEI'!E$2:E$5647,"...",2,-1) -> ... | Y41: =_xlfn.XLOOKUP(H41,'IT PEI'!X$2:X$5647,'IT PEI'!G$2:G$5647,"...",2,-1) -> ... | Z41: =_xlfn.XLOOKUP(H41,'IT PEI'!X$2:X$5647,'IT PEI'!F$2:F$5647,"...",2,-1) -> ... | AA41: =_xlfn.XLOOKUP(H41,'IT PEI'!X$2:X$5647,'IT PEI'!H$2:H$5647,"...",2,-1) -> ... | AB41: =_xlfn.XLOOKUP(H41,'IT PEI'!X$2:X$5647,'IT PEI'!O$2:O$5647,"...",2,-1) -> ... | AC41: =_xlfn.XLOOKUP(H41,'IT PEI'!X$2:X$5647,'IT PEI'!P$2:P$5647,"...",2,-1) -> ... | AD41: =_xlfn.XLOOKUP(H41,'IT PEI'!X$2:X$5647,'IT PEI'!Q$2:Q$5647,"...",2,-1) -> ... | AE41: =IF(COUNTIF(X41, "*" & "2030" & "*")>0, "SI", "No" ) -> No | AF41: =IF(COUNTIF(X41, "*" & "2030" & "*")>0, 1, 0 ) -> 0 | AG41: =IF(COUNTIF(X41, "*" & "2030" & "*")>0, 0, 1 ) -> 1 | AH41: =IF(AND(AA41="En Proceso",AE41="Si"),1,0) -> 0 | AI41: INACTIVO | AL41: =IFERROR(VLOOKUP(tbl_ues[[#This Row],[Id_UE]],'[1]Directorio v.02'!$H$3:$U$3089,11,FALSE),"") | AM41: =IFERROR(VLOOKUP(tbl_ues[[#This Row],[Id_UE]],'[1]Directorio v.02'!$H$3:$U$3089,12,FALSE),"") | AN41: =IFERROR(VLOOKUP(tbl_ues[[#This Row],[Id_UE]],'[1]Directorio v.02'!$H$3:$U$3089,13,FALSE),"") | AO41: =IFERROR(VLOOKUP(tbl_ues[[#This Row],[Id_UE]],'[1]Directorio v.02'!$H$3:$U$3089,14,FALSE),"") | AP41: =VLOOKUP(H41,#REF!,7,0) -> #REF! | AQ41: =VLOOKUP(H41,#REF!,9,0) -> #REF! | AR41: =VLOOKUP(H41,#REF!,15,0) -> #REF! | AS41: =VLOOKUP(H41,#REF!,16,0) -> #REF! | AT41: =VLOOKUP(H41,#REF!,17,0) -> #REF! | AU41: =VLOOKUP(H41,#REF!,18,0) -> #REF! | AV41: =VLOOKUP(H41,#REF!,19,0) -> #REF! | AW41: =VLOOKUP(H41,#REF!,20,0) -> #REF! | AX41: =VLOOKUP(H41,#REF!,22,0) -> #REF! | AY41: =VLOOKUP(H41,#REF!,23,0) -> #REF! | AZ41: =VLOOKUP(H41,#REF!,24,0) -> #REF! | BA41: =VLOOKUP(H41,#REF!,25,0) -> #REF! | BB41: =VLOOKUP(H41,#REF!,26,0) -> #REF! | BC41: =VLOOKUP(H41,#REF!,27,0) -> #REF! | BD41: =VLOOKUP(H41,#REF!,29,0) -> #REF! | BE41: =VLOOKUP(H41,#REF!,30,0) -> #REF! | BF41: =VLOOKUP(H41,#REF!,31,0) -> #REF! | BG41: =VLOOKUP(H41,#REF!,32,0) -> #REF! | BH41: =VLOOKUP(H41,#REF!,33,0) -> #REF! | BI41: =VLOOKUP(H41,#REF!,34,0) -> #REF! | BJ41: =VLOOKUP(H41,#REF!,36,0) -> #REF! | BK41: =VLOOKUP(H41,#REF!,37,0) -> #REF! | BL41: =VLOOKUP(H41,#REF!,44,0) -> #REF! | BM41: =VLOOKUP(H41,#REF!,45,0) -> #REF! | BN41: =VLOOKUP(H41,#REF!,46,0) -> #REF! | BO41: =VLOOKUP(H41,#REF!,47,0) -> #REF! | BP41: =VLOOKUP(H41,#REF!,48,0) -> #REF!
A42: Mancomunidad | B42: Mancomunidad | C42: N | D42: 0 | E42: FICTICIO | F42: 350041 | G42: MANCOMUNIDAD MUNICIPAL DEL YACUS | H42: 350041 | I42: MANCOMUNIDAD MUNICIPAL DEL YACUS | J42: 12 | K42: JUNIN | L42: 4 | M42: JAUJA | N42: 22 | O42: PACA | Q42: S | R42: S | W42: =IFERROR(VLOOKUP(H42,'IT PEI'!$X$2:$X$5647,1,0),"...") -> ... | X42: =_xlfn.XLOOKUP(H42,'IT PEI'!X$2:X$5647,'IT PEI'!E$2:E$5647,"...",2,-1) -> ... | Y42: =_xlfn.XLOOKUP(H42,'IT PEI'!X$2:X$5647,'IT PEI'!G$2:G$5647,"...",2,-1) -> ... | Z42: =_xlfn.XLOOKUP(H42,'IT PEI'!X$2:X$5647,'IT PEI'!F$2:F$5647,"...",2,-1) -> ... | AA42: =_xlfn.XLOOKUP(H42,'IT PEI'!X$2:X$5647,'IT PEI'!H$2:H$5647,"...",2,-1) -> ... | AB42: =_xlfn.XLOOKUP(H42,'IT PEI'!X$2:X$5647,'IT PEI'!O$2:O$5647,"...",2,-1) -> ... | AC42: =_xlfn.XLOOKUP(H42,'IT PEI'!X$2:X$5647,'IT PEI'!P$2:P$5647,"...",2,-1) -> ... | AD42: =_xlfn.XLOOKUP(H42,'IT PEI'!X$2:X$5647,'IT PEI'!Q$2:Q$5647,"...",2,-1) -> ... | AE42: =IF(COUNTIF(X42, "*" & "2030" & "*")>0, "SI", "No" ) -> No | AF42: =IF(COUNTIF(X42, "*" & "2030" & "*")>0, 1, 0 ) -> 0 | AG42: =IF(COUNTIF(X42, "*" & "2030" & "*")>0, 0, 1 ) -> 1 | AH42: =IF(AND(AA42="En Proceso",AE42="Si"),1,0) -> 0 | AI42: INACTIVO | AL42: =IFERROR(VLOOKUP(tbl_ues[[#This Row],[Id_UE]],'[1]Directorio v.02'!$H$3:$U$3089,11,FALSE),"") | AM42: =IFERROR(VLOOKUP(tbl_ues[[#This Row],[Id_UE]],'[1]Directorio v.02'!$H$3:$U$3089,12,FALSE),"") | AN42: =IFERROR(VLOOKUP(tbl_ues[[#This Row],[Id_UE]],'[1]Directorio v.02'!$H$3:$U$3089,13,FALSE),"") | AO42: =IFERROR(VLOOKUP(tbl_ues[[#This Row],[Id_UE]],'[1]Directorio v.02'!$H$3:$U$3089,14,FALSE),"") | AP42: =VLOOKUP(H42,#REF!,7,0) -> #REF! | AQ42: =VLOOKUP(H42,#REF!,9,0) -> #REF! | AR42: =VLOOKUP(H42,#REF!,15,0) -> #REF! | AS42: =VLOOKUP(H42,#REF!,16,0) -> #REF! | AT42: =VLOOKUP(H42,#REF!,17,0) -> #REF! | AU42: =VLOOKUP(H42,#REF!,18,0) -> #REF! | AV42: =VLOOKUP(H42,#REF!,19,0) -> #REF! | AW42: =VLOOKUP(H42,#REF!,20,0) -> #REF! | AX42: =VLOOKUP(H42,#REF!,22,0) -> #REF! | AY42: =VLOOKUP(H42,#REF!,23,0) -> #REF! | AZ42: =VLOOKUP(H42,#REF!,24,0) -> #REF! | BA42: =VLOOKUP(H42,#REF!,25,0) -> #REF! | BB42: =VLOOKUP(H42,#REF!,26,0) -> #REF! | BC42: =VLOOKUP(H42,#REF!,27,0) -> #REF! | BD42: =VLOOKUP(H42,#REF!,29,0) -> #REF! | BE42: =VLOOKUP(H42,#REF!,30,0) -> #REF! | BF42: =VLOOKUP(H42,#REF!,31,0) -> #REF! | BG42: =VLOOKUP(H42,#REF!,32,0) -> #REF! | BH42: =VLOOKUP(H42,#REF!,33,0) -> #REF! | BI42: =VLOOKUP(H42,#REF!,34,0) -> #REF! | BJ42: =VLOOKUP(H42,#REF!,36,0) -> #REF! | BK42: =VLOOKUP(H42,#REF!,37,0) -> #REF! | BL42: =VLOOKUP(H42,#REF!,44,0) -> #REF! | BM42: =VLOOKUP(H42,#REF!,45,0) -> #REF! | BN42: =VLOOKUP(H42,#REF!,46,0) -> #REF! | BO42: =VLOOKUP(H42,#REF!,47,0) -> #REF! | BP42: =VLOOKUP(H42,#REF!,48,0) -> #REF!
A43: Mancomunidad | B43: Mancomunidad | C43: N | D43: 0 | E43: FICTICIO | F43: 350040 | G43: MANCOMUNIDAD MUNICIPAL SEÑOR CAUTIVO DE AYABACA | H43: 350040 | I43: MANCOMUNIDAD MUNICIPAL SEÑOR CAUTIVO DE AYABACA | J43: 20 | K43: PIURA | L43: 2 | M43: AYABACA | N43: 5 | O43: MONTERO | Q43: S | R43: S | W43: =IFERROR(VLOOKUP(H43,'IT PEI'!$X$2:$X$5647,1,0),"...") -> ... | X43: =_xlfn.XLOOKUP(H43,'IT PEI'!X$2:X$5647,'IT PEI'!E$2:E$5647,"...",2,-1) -> ... | Y43: =_xlfn.XLOOKUP(H43,'IT PEI'!X$2:X$5647,'IT PEI'!G$2:G$5647,"...",2,-1) -> ... | Z43: =_xlfn.XLOOKUP(H43,'IT PEI'!X$2:X$5647,'IT PEI'!F$2:F$5647,"...",2,-1) -> ... | AA43: =_xlfn.XLOOKUP(H43,'IT PEI'!X$2:X$5647,'IT PEI'!H$2:H$5647,"...",2,-1) -> ... | AB43: =_xlfn.XLOOKUP(H43,'IT PEI'!X$2:X$5647,'IT PEI'!O$2:O$5647,"...",2,-1) -> ... | AC43: =_xlfn.XLOOKUP(H43,'IT PEI'!X$2:X$5647,'IT PEI'!P$2:P$5647,"...",2,-1) -> ... | AD43: =_xlfn.XLOOKUP(H43,'IT PEI'!X$2:X$5647,'IT PEI'!Q$2:Q$5647,"...",2,-1) -> ... | AE43: =IF(COUNTIF(X43, "*" & "2030" & "*")>0, "SI", "No" ) -> No | AF43: =IF(COUNTIF(X43, "*" & "2030" & "*")>0, 1, 0 ) -> 0 | AG43: =IF(COUNTIF(X43, "*" & "2030" & "*")>0, 0, 1 ) -> 1 | AH43: =IF(AND(AA43="En Proceso",AE43="Si"),1,0) -> 0 | AI43: INACTIVO | AL43: =IFERROR(VLOOKUP(tbl_ues[[#This Row],[Id_UE]],'[1]Directorio v.02'!$H$3:$U$3089,11,FALSE),"") | AM43: =IFERROR(VLOOKUP(tbl_ues[[#This Row],[Id_UE]],'[1]Directorio v.02'!$H$3:$U$3089,12,FALSE),"") | AN43: =IFERROR(VLOOKUP(tbl_ues[[#This Row],[Id_UE]],'[1]Directorio v.02'!$H$3:$U$3089,13,FALSE),"") | AO43: =IFERROR(VLOOKUP(tbl_ues[[#This Row],[Id_UE]],'[1]Directorio v.02'!$H$3:$U$3089,14,FALSE),"") | AP43: =VLOOKUP(H43,#REF!,7,0) -> #REF! | AQ43: =VLOOKUP(H43,#REF!,9,0) -> #REF! | AR43: =VLOOKUP(H43,#REF!,15,0) -> #REF! | AS43: =VLOOKUP(H43,#REF!,16,0) -> #REF! | AT43: =VLOOKUP(H43,#REF!,17,0) -> #REF! | AU43: =VLOOKUP(H43,#REF!,18,0) -> #REF! | AV43: =VLOOKUP(H43,#REF!,19,0) -> #REF! | AW43: =VLOOKUP(H43,#REF!,20,0) -> #REF! | AX43: =VLOOKUP(H43,#REF!,22,0) -> #REF! | AY43: =VLOOKUP(H43,#REF!,23,0) -> #REF! | AZ43: =VLOOKUP(H43,#REF!,24,0) -> #REF! | BA43: =VLOOKUP(H43,#REF!,25,0) -> #REF! | BB43: =VLOOKUP(H43,#REF!,26,0) -> #REF! | BC43: =VLOOKUP(H43,#REF!,27,0) -> #REF! | BD43: =VLOOKUP(H43,#REF!,29,0) -> #REF! | BE43: =VLOOKUP(H43,#REF!,30,0) -> #REF! | BF43: =VLOOKUP(H43,#REF!,31,0) -> #REF! | BG43: =VLOOKUP(H43,#REF!,32,0) -> #REF! | BH43: =VLOOKUP(H43,#REF!,33,0) -> #REF! | BI43: =VLOOKUP(H43,#REF!,34,0) -> #REF! | BJ43: =VLOOKUP(H43,#REF!,36,0) -> #REF! | BK43: =VLOOKUP(H43,#REF!,37,0) -> #REF! | BL43: =VLOOKUP(H43,#REF!,44,0) -> #REF! | BM43: =VLOOKUP(H43,#REF!,45,0) -> #REF! | BN43: =VLOOKUP(H43,#REF!,46,0) -> #REF! | BO43: =VLOOKUP(H43,#REF!,47,0) -> #REF! | BP43: =VLOOKUP(H43,#REF!,48,0) -> #REF!
A44: Mancomunidad | B44: Mancomunidad | C44: N | D44: 0 | E44: FICTICIO | F44: 350039 | G44: MANCOMUNIDAD MUNICIPAL DE LAS CABEZADAS DEL SUR DE LUCANAS - AYACUCHO - MANSURLA | H44: 350039 | I44: MANCOMUNIDAD MUNICIPAL DE LAS CABEZADAS DEL SUR DE LUCANAS - AYACUCHO - MANSURLA | J44: 11 | K44: ICA | L44: 1 | M44: ICA | N44: 1 | O44: ICA | Q44: S | R44: S | W44: =IFERROR(VLOOKUP(H44,'IT PEI'!$X$2:$X$5647,1,0),"...") -> ... | X44: =_xlfn.XLOOKUP(H44,'IT PEI'!X$2:X$5647,'IT PEI'!E$2:E$5647,"...",2,-1) -> ... | Y44: =_xlfn.XLOOKUP(H44,'IT PEI'!X$2:X$5647,'IT PEI'!G$2:G$5647,"...",2,-1) -> ... | Z44: =_xlfn.XLOOKUP(H44,'IT PEI'!X$2:X$5647,'IT PEI'!F$2:F$5647,"...",2,-1) -> ... | AA44: =_xlfn.XLOOKUP(H44,'IT PEI'!X$2:X$5647,'IT PEI'!H$2:H$5647,"...",2,-1) -> ... | AB44: =_xlfn.XLOOKUP(H44,'IT PEI'!X$2:X$5647,'IT PEI'!O$2:O$5647,"...",2,-1) -> ... | AC44: =_xlfn.XLOOKUP(H44,'IT PEI'!X$2:X$5647,'IT PEI'!P$2:P$5647,"...",2,-1) -> ... | AD44: =_xlfn.XLOOKUP(H44,'IT PEI'!X$2:X$5647,'IT PEI'!Q$2:Q$5647,"...",2,-1) -> ... | AE44: =IF(COUNTIF(X44, "*" & "2030" & "*")>0, "SI", "No" ) -> No | AF44: =IF(COUNTIF(X44, "*" & "2030" & "*")>0, 1, 0 ) -> 0 | AG44: =IF(COUNTIF(X44, "*" & "2030" & "*")>0, 0, 1 ) -> 1 | AH44: =IF(AND(AA44="En Proceso",AE44="Si"),1,0) -> 0 | AI44: INACTIVO | AL44: =IFERROR(VLOOKUP(tbl_ues[[#This Row],[Id_UE]],'[1]Directorio v.02'!$H$3:$U$3089,11,FALSE),"") | AM44: =IFERROR(VLOOKUP(tbl_ues[[#This Row],[Id_UE]],'[1]Directorio v.02'!$H$3:$U$3089,12,FALSE),"") | AN44: =IFERROR(VLOOKUP(tbl_ues[[#This Row],[Id_UE]],'[1]Directorio v.02'!$H$3:$U$3089,13,FALSE),"") | AO44: =IFERROR(VLOOKUP(tbl_ues[[#This Row],[Id_UE]],'[1]Directorio v.02'!$H$3:$U$3089,14,FALSE),"") | AP44: =VLOOKUP(H44,#REF!,7,0) -> #REF! | AQ44: =VLOOKUP(H44,#REF!,9,0) -> #REF! | AR44: =VLOOKUP(H44,#REF!,15,0) -> #REF! | AS44: =VLOOKUP(H44,#REF!,16,0) -> #REF! | AT44: =VLOOKUP(H44,#REF!,17,0) -> #REF! | AU44: =VLOOKUP(H44,#REF!,18,0) -> #REF! | AV44: =VLOOKUP(H44,#REF!,19,0) -> #REF! | AW44: =VLOOKUP(H44,#REF!,20,0) -> #REF! | AX44: =VLOOKUP(H44,#REF!,22,0) -> #REF! | AY44: =VLOOKUP(H44,#REF!,23,0) -> #REF! | AZ44: =VLOOKUP(H44,#REF!,24,0) -> #REF! | BA44: =VLOOKUP(H44,#REF!,25,0) -> #REF! | BB44: =VLOOKUP(H44,#REF!,26,0) -> #REF! | BC44: =VLOOKUP(H44,#REF!,27,0) -> #REF! | BD44: =VLOOKUP(H44,#REF!,29,0) -> #REF! | BE44: =VLOOKUP(H44,#REF!,30,0) -> #REF! | BF44: =VLOOKUP(H44,#REF!,31,0) -> #REF! | BG44: =VLOOKUP(H44,#REF!,32,0) -> #REF! | BH44: =VLOOKUP(H44,#REF!,33,0) -> #REF! | BI44: =VLOOKUP(H44,#REF!,34,0) -> #REF! | BJ44: =VLOOKUP(H44,#REF!,36,0) -> #REF! | BK44: =VLOOKUP(H44,#REF!,37,0) -> #REF! | BL44: =VLOOKUP(H44,#REF!,44,0) -> #REF! | BM44: =VLOOKUP(H44,#REF!,45,0) -> #REF! | BN44: =VLOOKUP(H44,#REF!,46,0) -> #REF! | BO44: =VLOOKUP(H44,#REF!,47,0) -> #REF! | BP44: =VLOOKUP(H44,#REF!,48,0) -> #REF!
A45: Mancomunidad | B45: Mancomunidad | C45: N | D45: 0 | E45: FICTICIO | F45: 350037 | G45: MANCOMUNIDAD MUNICIPAL DEL VALLE FORTALEZA Y DEL SANTA | H45: 350037 | I45: MANCOMUNIDAD MUNICIPAL DEL VALLE FORTALEZA Y DEL SANTA | J45: 15 | K45: LIMA | L45: 1 | M45: LIMA | N45: 15 | O45: LA VICTORIA | Q45: S | R45: S | W45: =IFERROR(VLOOKUP(H45,'IT PEI'!$X$2:$X$5647,1,0),"...") -> ... | X45: =_xlfn.XLOOKUP(H45,'IT PEI'!X$2:X$5647,'IT PEI'!E$2:E$5647,"...",2,-1) -> ... | Y45: =_xlfn.XLOOKUP(H45,'IT PEI'!X$2:X$5647,'IT PEI'!G$2:G$5647,"...",2,-1) -> ... | Z45: =_xlfn.XLOOKUP(H45,'IT PEI'!X$2:X$5647,'IT PEI'!F$2:F$5647,"...",2,-1) -> ... | AA45: =_xlfn.XLOOKUP(H45,'IT PEI'!X$2:X$5647,'IT PEI'!H$2:H$5647,"...",2,-1) -> ... | AB45: =_xlfn.XLOOKUP(H45,'IT PEI'!X$2:X$5647,'IT PEI'!O$2:O$5647,"...",2,-1) -> ... | AC45: =_xlfn.XLOOKUP(H45,'IT PEI'!X$2:X$5647,'IT PEI'!P$2:P$5647,"...",2,-1) -> ... | AD45: =_xlfn.XLOOKUP(H45,'IT PEI'!X$2:X$5647,'IT PEI'!Q$2:Q$5647,"...",2,-1) -> ... | AE45: =IF(COUNTIF(X45, "*" & "2030" & "*")>0, "SI", "No" ) -> No | AF45: =IF(COUNTIF(X45, "*" & "2030" & "*")>0, 1, 0 ) -> 0 | AG45: =IF(COUNTIF(X45, "*" & "2030" & "*")>0, 0, 1 ) -> 1 | AH45: =IF(AND(AA45="En Proceso",AE45="Si"),1,0) -> 0 | AI45: INACTIVO | AL45: =IFERROR(VLOOKUP(tbl_ues[[#This Row],[Id_UE]],'[1]Directorio v.02'!$H$3:$U$3089,11,FALSE),"") | AM45: =IFERROR(VLOOKUP(tbl_ues[[#This Row],[Id_UE]],'[1]Directorio v.02'!$H$3:$U$3089,12,FALSE),"") | AN45: =IFERROR(VLOOKUP(tbl_ues[[#This Row],[Id_UE]],'[1]Directorio v.02'!$H$3:$U$3089,13,FALSE),"") | AO45: =IFERROR(VLOOKUP(tbl_ues[[#This Row],[Id_UE]],'[1]Directorio v.02'!$H$3:$U$3089,14,FALSE),"") | AP45: =VLOOKUP(H45,#REF!,7,0) -> #REF! | AQ45: =VLOOKUP(H45,#REF!,9,0) -> #REF! | AR45: =VLOOKUP(H45,#REF!,15,0) -> #REF! | AS45: =VLOOKUP(H45,#REF!,16,0) -> #REF! | AT45: =VLOOKUP(H45,#REF!,17,0) -> #REF! | AU45: =VLOOKUP(H45,#REF!,18,0) -> #REF! | AV45: =VLOOKUP(H45,#REF!,19,0) -> #REF! | AW45: =VLOOKUP(H45,#REF!,20,0) -> #REF! | AX45: =VLOOKUP(H45,#REF!,22,0) -> #REF! | AY45: =VLOOKUP(H45,#REF!,23,0) -> #REF! | AZ45: =VLOOKUP(H45,#REF!,24,0) -> #REF! | BA45: =VLOOKUP(H45,#REF!,25,0) -> #REF! | BB45: =VLOOKUP(H45,#REF!,26,0) -> #REF! | BC45: =VLOOKUP(H45,#REF!,27,0) -> #REF! | BD45: =VLOOKUP(H45,#REF!,29,0) -> #REF! | BE45: =VLOOKUP(H45,#REF!,30,0) -> #REF! | BF45: =VLOOKUP(H45,#REF!,31,0) -> #REF! | BG45: =VLOOKUP(H45,#REF!,32,0) -> #REF! | BH45: =VLOOKUP(H45,#REF!,33,0) -> #REF! | BI45: =VLOOKUP(H45,#REF!,34,0) -> #REF! | BJ45: =VLOOKUP(H45,#REF!,36,0) -> #REF! | BK45: =VLOOKUP(H45,#REF!,37,0) -> #REF! | BL45: =VLOOKUP(H45,#REF!,44,0) -> #REF! | BM45: =VLOOKUP(H45,#REF!,45,0) -> #REF! | BN45: =VLOOKUP(H45,#REF!,46,0) -> #REF! | BO45: =VLOOKUP(H45,#REF!,47,0) -> #REF! | BP45: =VLOOKUP(H45,#REF!,48,0) -> #REF!
A46: Mancomunidad | B46: Mancomunidad | C46: N | D46: 0 | E46: FICTICIO | F46: 350036 | G46: MANCOMUNIDAD MUNICIPAL DEL VALLE SANTA EULALIA | H46: 350036 | I46: MANCOMUNIDAD MUNICIPAL DEL VALLE SANTA EULALIA | J46: 15 | K46: LIMA | L46: 1 | M46: LIMA | N46: 18 | O46: LURIGANCHO | Q46: S | R46: S | W46: =IFERROR(VLOOKUP(H46,'IT PEI'!$X$2:$X$5647,1,0),"...") -> ... | X46: =_xlfn.XLOOKUP(H46,'IT PEI'!X$2:X$5647,'IT PEI'!E$2:E$5647,"...",2,-1) -> ... | Y46: =_xlfn.XLOOKUP(H46,'IT PEI'!X$2:X$5647,'IT PEI'!G$2:G$5647,"...",2,-1) -> ... | Z46: =_xlfn.XLOOKUP(H46,'IT PEI'!X$2:X$5647,'IT PEI'!F$2:F$5647,"...",2,-1) -> ... | AA46: =_xlfn.XLOOKUP(H46,'IT PEI'!X$2:X$5647,'IT PEI'!H$2:H$5647,"...",2,-1) -> ... | AB46: =_xlfn.XLOOKUP(H46,'IT PEI'!X$2:X$5647,'IT PEI'!O$2:O$5647,"...",2,-1) -> ... | AC46: =_xlfn.XLOOKUP(H46,'IT PEI'!X$2:X$5647,'IT PEI'!P$2:P$5647,"...",2,-1) -> ... | AD46: =_xlfn.XLOOKUP(H46,'IT PEI'!X$2:X$5647,'IT PEI'!Q$2:Q$5647,"...",2,-1) -> ... | AE46: =IF(COUNTIF(X46, "*" & "2030" & "*")>0, "SI", "No" ) -> No | AF46: =IF(COUNTIF(X46, "*" & "2030" & "*")>0, 1, 0 ) -> 0 | AG46: =IF(COUNTIF(X46, "*" & "2030" & "*")>0, 0, 1 ) -> 1 | AH46: =IF(AND(AA46="En Proceso",AE46="Si"),1,0) -> 0 | AI46: INACTIVO | AL46: =IFERROR(VLOOKUP(tbl_ues[[#This Row],[Id_UE]],'[1]Directorio v.02'!$H$3:$U$3089,11,FALSE),"") | AM46: =IFERROR(VLOOKUP(tbl_ues[[#This Row],[Id_UE]],'[1]Directorio v.02'!$H$3:$U$3089,12,FALSE),"") | AN46: =IFERROR(VLOOKUP(tbl_ues[[#This Row],[Id_UE]],'[1]Directorio v.02'!$H$3:$U$3089,13,FALSE),"") | AO46: =IFERROR(VLOOKUP(tbl_ues[[#This Row],[Id_UE]],'[1]Directorio v.02'!$H$3:$U$3089,14,FALSE),"") | AP46: =VLOOKUP(H46,#REF!,7,0) -> #REF! | AQ46: =VLOOKUP(H46,#REF!,9,0) -> #REF! | AR46: =VLOOKUP(H46,#REF!,15,0) -> #REF! | AS46: =VLOOKUP(H46,#REF!,16,0) -> #REF! | AT46: =VLOOKUP(H46,#REF!,17,0) -> #REF! | AU46: =VLOOKUP(H46,#REF!,18,0) -> #REF! | AV46: =VLOOKUP(H46,#REF!,19,0) -> #REF! | AW46: =VLOOKUP(H46,#REF!,20,0) -> #REF! | AX46: =VLOOKUP(H46,#REF!,22,0) -> #REF! | AY46: =VLOOKUP(H46,#REF!,23,0) -> #REF! | AZ46: =VLOOKUP(H46,#REF!,24,0) -> #REF! | BA46: =VLOOKUP(H46,#REF!,25,0) -> #REF! | BB46: =VLOOKUP(H46,#REF!,26,0) -> #REF! | BC46: =VLOOKUP(H46,#REF!,27,0) -> #REF! | BD46: =VLOOKUP(H46,#REF!,29,0) -> #REF! | BE46: =VLOOKUP(H46,#REF!,30,0) -> #REF! | BF46: =VLOOKUP(H46,#REF!,31,0) -> #REF! | BG46: =VLOOKUP(H46,#REF!,32,0) -> #REF! | BH46: =VLOOKUP(H46,#REF!,33,0) -> #REF! | BI46: =VLOOKUP(H46,#REF!,34,0) -> #REF! | BJ46: =VLOOKUP(H46,#REF!,36,0) -> #REF! | BK46: =VLOOKUP(H46,#REF!,37,0) -> #REF! | BL46: =VLOOKUP(H46,#REF!,44,0) -> #REF! | BM46: =VLOOKUP(H46,#REF!,45,0) -> #REF! | BN46: =VLOOKUP(H46,#REF!,46,0) -> #REF! | BO46: =VLOOKUP(H46,#REF!,47,0) -> #REF! | BP46: =VLOOKUP(H46,#REF!,48,0) -> #REF!
A47: Mancomunidad | B47: Mancomunidad | C47: N | D47: 0 | E47: FICTICIO | F47: 350035 | G47: MANCOMUNIDAD MUNICIPAL LIMA NORTE | H47: 350035 | I47: MANCOMUNIDAD MUNICIPAL LIMA NORTE | J47: 15 | K47: LIMA | L47: 1 | M47: LIMA | N47: 10 | O47: COMAS | Q47: S | R47: S | W47: =IFERROR(VLOOKUP(H47,'IT PEI'!$X$2:$X$5647,1,0),"...") -> ... | X47: =_xlfn.XLOOKUP(H47,'IT PEI'!X$2:X$5647,'IT PEI'!E$2:E$5647,"...",2,-1) -> ... | Y47: =_xlfn.XLOOKUP(H47,'IT PEI'!X$2:X$5647,'IT PEI'!G$2:G$5647,"...",2,-1) -> ... | Z47: =_xlfn.XLOOKUP(H47,'IT PEI'!X$2:X$5647,'IT PEI'!F$2:F$5647,"...",2,-1) -> ... | AA47: =_xlfn.XLOOKUP(H47,'IT PEI'!X$2:X$5647,'IT PEI'!H$2:H$5647,"...",2,-1) -> ... | AB47: =_xlfn.XLOOKUP(H47,'IT PEI'!X$2:X$5647,'IT PEI'!O$2:O$5647,"...",2,-1) -> ... | AC47: =_xlfn.XLOOKUP(H47,'IT PEI'!X$2:X$5647,'IT PEI'!P$2:P$5647,"...",2,-1) -> ... | AD47: =_xlfn.XLOOKUP(H47,'IT PEI'!X$2:X$5647,'IT PEI'!Q$2:Q$5647,"...",2,-1) -> ... | AE47: =IF(COUNTIF(X47, "*" & "2030" & "*")>0, "SI", "No" ) -> No | AF47: =IF(COUNTIF(X47, "*" & "2030" & "*")>0, 1, 0 ) -> 0 | AG47: =IF(COUNTIF(X47, "*" & "2030" & "*")>0, 0, 1 ) -> 1 | AH47: =IF(AND(AA47="En Proceso",AE47="Si"),1,0) -> 0 | AI47: INACTIVO | AL47: =IFERROR(VLOOKUP(tbl_ues[[#This Row],[Id_UE]],'[1]Directorio v.02'!$H$3:$U$3089,11,FALSE),"") | AM47: =IFERROR(VLOOKUP(tbl_ues[[#This Row],[Id_UE]],'[1]Directorio v.02'!$H$3:$U$3089,12,FALSE),"") | AN47: =IFERROR(VLOOKUP(tbl_ues[[#This Row],[Id_UE]],'[1]Directorio v.02'!$H$3:$U$3089,13,FALSE),"") | AO47: =IFERROR(VLOOKUP(tbl_ues[[#This Row],[Id_UE]],'[1]Directorio v.02'!$H$3:$U$3089,14,FALSE),"") | AP47: =VLOOKUP(H47,#REF!,7,0) -> #REF! | AQ47: =VLOOKUP(H47,#REF!,9,0) -> #REF! | AR47: =VLOOKUP(H47,#REF!,15,0) -> #REF! | AS47: =VLOOKUP(H47,#REF!,16,0) -> #REF! | AT47: =VLOOKUP(H47,#REF!,17,0) -> #REF! | AU47: =VLOOKUP(H47,#REF!,18,0) -> #REF! | AV47: =VLOOKUP(H47,#REF!,19,0) -> #REF! | AW47: =VLOOKUP(H47,#REF!,20,0) -> #REF! | AX47: =VLOOKUP(H47,#REF!,22,0) -> #REF! | AY47: =VLOOKUP(H47,#REF!,23,0) -> #REF! | AZ47: =VLOOKUP(H47,#REF!,24,0) -> #REF! | BA47: =VLOOKUP(H47,#REF!,25,0) -> #REF! | BB47: =VLOOKUP(H47,#REF!,26,0) -> #REF! | BC47: =VLOOKUP(H47,#REF!,27,0) -> #REF! | BD47: =VLOOKUP(H47,#REF!,29,0) -> #REF! | BE47: =VLOOKUP(H47,#REF!,30,0) -> #REF! | BF47: =VLOOKUP(H47,#REF!,31,0) -> #REF! | BG47: =VLOOKUP(H47,#REF!,32,0) -> #REF! | BH47: =VLOOKUP(H47,#REF!,33,0) -> #REF! | BI47: =VLOOKUP(H47,#REF!,34,0) -> #REF! | BJ47: =VLOOKUP(H47,#REF!,36,0) -> #REF! | BK47: =VLOOKUP(H47,#REF!,37,0) -> #REF! | BL47: =VLOOKUP(H47,#REF!,44,0) -> #REF! | BM47: =VLOOKUP(H47,#REF!,45,0) -> #REF! | BN47: =VLOOKUP(H47,#REF!,46,0) -> #REF! | BO47: =VLOOKUP(H47,#REF!,47,0) -> #REF! | BP47: =VLOOKUP(H47,#REF!,48,0) -> #REF!
A48: Mancomunidad | B48: Mancomunidad | C48: N | D48: 0 | E48: FICTICIO | F48: 350034 | G48: MANCOMUNIDAD MUNICIPAL QHAPAQ QOLLA | H48: 350034 | I48: MANCOMUNIDAD MUNICIPAL QHAPAQ QOLLA | J48: 21 | K48: PUNO | L48: 1 | M48: PUNO | N48: 1 | O48: PUNO | Q48: S | R48: S | W48: =IFERROR(VLOOKUP(H48,'IT PEI'!$X$2:$X$5647,1,0),"...") -> ... | X48: =_xlfn.XLOOKUP(H48,'IT PEI'!X$2:X$5647,'IT PEI'!E$2:E$5647,"...",2,-1) -> ... | Y48: =_xlfn.XLOOKUP(H48,'IT PEI'!X$2:X$5647,'IT PEI'!G$2:G$5647,"...",2,-1) -> ... | Z48: =_xlfn.XLOOKUP(H48,'IT PEI'!X$2:X$5647,'IT PEI'!F$2:F$5647,"...",2,-1) -> ... | AA48: =_xlfn.XLOOKUP(H48,'IT PEI'!X$2:X$5647,'IT PEI'!H$2:H$5647,"...",2,-1) -> ... | AB48: =_xlfn.XLOOKUP(H48,'IT PEI'!X$2:X$5647,'IT PEI'!O$2:O$5647,"...",2,-1) -> ... | AC48: =_xlfn.XLOOKUP(H48,'IT PEI'!X$2:X$5647,'IT PEI'!P$2:P$5647,"...",2,-1) -> ... | AD48: =_xlfn.XLOOKUP(H48,'IT PEI'!X$2:X$5647,'IT PEI'!Q$2:Q$5647,"...",2,-1) -> ... | AE48: =IF(COUNTIF(X48, "*" & "2030" & "*")>0, "SI", "No" ) -> No | AF48: =IF(COUNTIF(X48, "*" & "2030" & "*")>0, 1, 0 ) -> 0 | AG48: =IF(COUNTIF(X48, "*" & "2030" & "*")>0, 0, 1 ) -> 1 | AH48: =IF(AND(AA48="En Proceso",AE48="Si"),1,0) -> 0 | AI48: INACTIVO | AL48: =IFERROR(VLOOKUP(tbl_ues[[#This Row],[Id_UE]],'[1]Directorio v.02'!$H$3:$U$3089,11,FALSE),"") | AM48: =IFERROR(VLOOKUP(tbl_ues[[#This Row],[Id_UE]],'[1]Directorio v.02'!$H$3:$U$3089,12,FALSE),"") | AN48: =IFERROR(VLOOKUP(tbl_ues[[#This Row],[Id_UE]],'[1]Directorio v.02'!$H$3:$U$3089,13,FALSE),"") | AO48: =IFERROR(VLOOKUP(tbl_ues[[#This Row],[Id_UE]],'[1]Directorio v.02'!$H$3:$U$3089,14,FALSE),"") | AP48: =VLOOKUP(H48,#REF!,7,0) -> #REF! | AQ48: =VLOOKUP(H48,#REF!,9,0) -> #REF! | AR48: =VLOOKUP(H48,#REF!,15,0) -> #REF! | AS48: =VLOOKUP(H48,#REF!,16,0) -> #REF! | AT48: =VLOOKUP(H48,#REF!,17,0) -> #REF! | AU48: =VLOOKUP(H48,#REF!,18,0) -> #REF! | AV48: =VLOOKUP(H48,#REF!,19,0) -> #REF! | AW48: =VLOOKUP(H48,#REF!,20,0) -> #REF! | AX48: =VLOOKUP(H48,#REF!,22,0) -> #REF! | AY48: =VLOOKUP(H48,#REF!,23,0) -> #REF! | AZ48: =VLOOKUP(H48,#REF!,24,0) -> #REF! | BA48: =VLOOKUP(H48,#REF!,25,0) -> #REF! | BB48: =VLOOKUP(H48,#REF!,26,0) -> #REF! | BC48: =VLOOKUP(H48,#REF!,27,0) -> #REF! | BD48: =VLOOKUP(H48,#REF!,29,0) -> #REF! | BE48: =VLOOKUP(H48,#REF!,30,0) -> #REF! | BF48: =VLOOKUP(H48,#REF!,31,0) -> #REF! | BG48: =VLOOKUP(H48,#REF!,32,0) -> #REF! | BH48: =VLOOKUP(H48,#REF!,33,0) -> #REF! | BI48: =VLOOKUP(H48,#REF!,34,0) -> #REF! | BJ48: =VLOOKUP(H48,#REF!,36,0) -> #REF! | BK48: =VLOOKUP(H48,#REF!,37,0) -> #REF! | BL48: =VLOOKUP(H48,#REF!,44,0) -> #REF! | BM48: =VLOOKUP(H48,#REF!,45,0) -> #REF! | BN48: =VLOOKUP(H48,#REF!,46,0) -> #REF! | BO48: =VLOOKUP(H48,#REF!,47,0) -> #REF! | BP48: =VLOOKUP(H48,#REF!,48,0) -> #REF!
A49: Mancomunidad | B49: Mancomunidad | C49: N | D49: 0 | E49: FICTICIO | F49: 350032 | G49: MANCOMUNIDAD MUNICIPAL DE LA CUENCA DEL RIO SANTO TOMAS | H49: 350032 | I49: MANCOMUNIDAD MUNICIPAL DE LA CUENCA DEL RIO SANTO TOMAS | J49: 08 | K49: CUSCO | L49: 7 | M49: CHUMBIVILCAS | N49: 1 | O49: SANTO TOMAS | Q49: S | R49: S | W49: =IFERROR(VLOOKUP(H49,'IT PEI'!$X$2:$X$5647,1,0),"...") -> ... | X49: =_xlfn.XLOOKUP(H49,'IT PEI'!X$2:X$5647,'IT PEI'!E$2:E$5647,"...",2,-1) -> ... | Y49: =_xlfn.XLOOKUP(H49,'IT PEI'!X$2:X$5647,'IT PEI'!G$2:G$5647,"...",2,-1) -> ... | Z49: =_xlfn.XLOOKUP(H49,'IT PEI'!X$2:X$5647,'IT PEI'!F$2:F$5647,"...",2,-1) -> ... | AA49: =_xlfn.XLOOKUP(H49,'IT PEI'!X$2:X$5647,'IT PEI'!H$2:H$5647,"...",2,-1) -> ... | AB49: =_xlfn.XLOOKUP(H49,'IT PEI'!X$2:X$5647,'IT PEI'!O$2:O$5647,"...",2,-1) -> ... | AC49: =_xlfn.XLOOKUP(H49,'IT PEI'!X$2:X$5647,'IT PEI'!P$2:P$5647,"...",2,-1) -> ... | AD49: =_xlfn.XLOOKUP(H49,'IT PEI'!X$2:X$5647,'IT PEI'!Q$2:Q$5647,"...",2,-1) -> ... | AE49: =IF(COUNTIF(X49, "*" & "2030" & "*")>0, "SI", "No" ) -> No | AF49: =IF(COUNTIF(X49, "*" & "2030" & "*")>0, 1, 0 ) -> 0 | AG49: =IF(COUNTIF(X49, "*" & "2030" & "*")>0, 0, 1 ) -> 1 | AH49: =IF(AND(AA49="En Proceso",AE49="Si"),1,0) -> 0 | AI49: INACTIVO | AL49: =IFERROR(VLOOKUP(tbl_ues[[#This Row],[Id_UE]],'[1]Directorio v.02'!$H$3:$U$3089,11,FALSE),"") | AM49: =IFERROR(VLOOKUP(tbl_ues[[#This Row],[Id_UE]],'[1]Directorio v.02'!$H$3:$U$3089,12,FALSE),"") | AN49: =IFERROR(VLOOKUP(tbl_ues[[#This Row],[Id_UE]],'[1]Directorio v.02'!$H$3:$U$3089,13,FALSE),"") | AO49: =IFERROR(VLOOKUP(tbl_ues[[#This Row],[Id_UE]],'[1]Directorio v.02'!$H$3:$U$3089,14,FALSE),"") | AP49: =VLOOKUP(H49,#REF!,7,0) -> #REF! | AQ49: =VLOOKUP(H49,#REF!,9,0) -> #REF! | AR49: =VLOOKUP(H49,#REF!,15,0) -> #REF! | AS49: =VLOOKUP(H49,#REF!,16,0) -> #REF! | AT49: =VLOOKUP(H49,#REF!,17,0) -> #REF! | AU49: =VLOOKUP(H49,#REF!,18,0) -> #REF! | AV49: =VLOOKUP(H49,#REF!,19,0) -> #REF! | AW49: =VLOOKUP(H49,#REF!,20,0) -> #REF! | AX49: =VLOOKUP(H49,#REF!,22,0) -> #REF! | AY49: =VLOOKUP(H49,#REF!,23,0) -> #REF! | AZ49: =VLOOKUP(H49,#REF!,24,0) -> #REF! | BA49: =VLOOKUP(H49,#REF!,25,0) -> #REF! | BB49: =VLOOKUP(H49,#REF!,26,0) -> #REF! | BC49: =VLOOKUP(H49,#REF!,27,0) -> #REF! | BD49: =VLOOKUP(H49,#REF!,29,0) -> #REF! | BE49: =VLOOKUP(H49,#REF!,30,0) -> #REF! | BF49: =VLOOKUP(H49,#REF!,31,0) -> #REF! | BG49: =VLOOKUP(H49,#REF!,32,0) -> #REF! | BH49: =VLOOKUP(H49,#REF!,33,0) -> #REF! | BI49: =VLOOKUP(H49,#REF!,34,0) -> #REF! | BJ49: =VLOOKUP(H49,#REF!,36,0) -> #REF! | BK49: =VLOOKUP(H49,#REF!,37,0) -> #REF! | BL49: =VLOOKUP(H49,#REF!,44,0) -> #REF! | BM49: =VLOOKUP(H49,#REF!,45,0) -> #REF! | BN49: =VLOOKUP(H49,#REF!,46,0) -> #REF! | BO49: =VLOOKUP(H49,#REF!,47,0) -> #REF! | BP49: =VLOOKUP(H49,#REF!,48,0) -> #REF!
A50: Mancomunidad | B50: Mancomunidad | C50: N | D50: 0 | E50: FICTICIO | F50: 350031 | G50: MANCOMUNIDAD MUNICIPAL LIMA CENTRO | H50: 350031 | I50: MANCOMUNIDAD MUNICIPAL LIMA CENTRO | J50: 15 | K50: LIMA | L50: 1 | M50: LIMA | N50: 15 | O50: LA VICTORIA | Q50: S | R50: S | W50: =IFERROR(VLOOKUP(H50,'IT PEI'!$X$2:$X$5647,1,0),"...") -> ... | X50: =_xlfn.XLOOKUP(H50,'IT PEI'!X$2:X$5647,'IT PEI'!E$2:E$5647,"...",2,-1) -> ... | Y50: =_xlfn.XLOOKUP(H50,'IT PEI'!X$2:X$5647,'IT PEI'!G$2:G$5647,"...",2,-1) -> ... | Z50: =_xlfn.XLOOKUP(H50,'IT PEI'!X$2:X$5647,'IT PEI'!F$2:F$5647,"...",2,-1) -> ... | AA50: =_xlfn.XLOOKUP(H50,'IT PEI'!X$2:X$5647,'IT PEI'!H$2:H$5647,"...",2,-1) -> ... | AB50: =_xlfn.XLOOKUP(H50,'IT PEI'!X$2:X$5647,'IT PEI'!O$2:O$5647,"...",2,-1) -> ... | AC50: =_xlfn.XLOOKUP(H50,'IT PEI'!X$2:X$5647,'IT PEI'!P$2:P$5647,"...",2,-1) -> ... | AD50: =_xlfn.XLOOKUP(H50,'IT PEI'!X$2:X$5647,'IT PEI'!Q$2:Q$5647,"...",2,-1) -> ... | AE50: =IF(COUNTIF(X50, "*" & "2030" & "*")>0, "SI", "No" ) -> No | AF50: =IF(COUNTIF(X50, "*" & "2030" & "*")>0, 1, 0 ) -> 0 | AG50: =IF(COUNTIF(X50, "*" & "2030" & "*")>0, 0, 1 ) -> 1 | AH50: =IF(AND(AA50="En Proceso",AE50="Si"),1,0) -> 0 | AI50: INACTIVO | AL50: =IFERROR(VLOOKUP(tbl_ues[[#This Row],[Id_UE]],'[1]Directorio v.02'!$H$3:$U$3089,11,FALSE),"") | AM50: =IFERROR(VLOOKUP(tbl_ues[[#This Row],[Id_UE]],'[1]Directorio v.02'!$H$3:$U$3089,12,FALSE),"") | AN50: =IFERROR(VLOOKUP(tbl_ues[[#This Row],[Id_UE]],'[1]Directorio v.02'!$H$3:$U$3089,13,FALSE),"") | AO50: =IFERROR(VLOOKUP(tbl_ues[[#This Row],[Id_UE]],'[1]Directorio v.02'!$H$3:$U$3089,14,FALSE),"") | AP50: =VLOOKUP(H50,#REF!,7,0) -> #REF! | AQ50: =VLOOKUP(H50,#REF!,9,0) -> #REF! | AR50: =VLOOKUP(H50,#REF!,15,0) -> #REF! | AS50: =VLOOKUP(H50,#REF!,16,0) -> #REF! | AT50: =VLOOKUP(H50,#REF!,17,0) -> #REF! | AU50: =VLOOKUP(H50,#REF!,18,0) -> #REF! | AV50: =VLOOKUP(H50,#REF!,19,0) -> #REF! | AW50: =VLOOKUP(H50,#REF!,20,0) -> #REF! | AX50: =VLOOKUP(H50,#REF!,22,0) -> #REF! | AY50: =VLOOKUP(H50,#REF!,23,0) -> #REF! | AZ50: =VLOOKUP(H50,#REF!,24,0) -> #REF! | BA50: =VLOOKUP(H50,#REF!,25,0) -> #REF! | BB50: =VLOOKUP(H50,#REF!,26,0) -> #REF! | BC50: =VLOOKUP(H50,#REF!,27,0) -> #REF! | BD50: =VLOOKUP(H50,#REF!,29,0) -> #REF! | BE50: =VLOOKUP(H50,#REF!,30,0) -> #REF! | BF50: =VLOOKUP(H50,#REF!,31,0) -> #REF! | BG50: =VLOOKUP(H50,#REF!,32,0) -> #REF! | BH50: =VLOOKUP(H50,#REF!,33,0) -> #REF! | BI50: =VLOOKUP(H50,#REF!,34,0) -> #REF! | BJ50: =VLOOKUP(H50,#REF!,36,0) -> #REF! | BK50: =VLOOKUP(H50,#REF!,37,0) -> #REF! | BL50: =VLOOKUP(H50,#REF!,44,0) -> #REF! | BM50: =VLOOKUP(H50,#REF!,45,0) -> #REF! | BN50: =VLOOKUP(H50,#REF!,46,0) -> #REF! | BO50: =VLOOKUP(H50,#REF!,47,0) -> #REF! | BP50: =VLOOKUP(H50,#REF!,48,0) -> #REF!
A51: Mancomunidad | B51: Mancomunidad | C51: N | D51: 0 | E51: FICTICIO | F51: 350030 | G51: MANCOMUNIDAD MUNICIPAL ANGARAES SUR- MANUAS | H51: 350030 | I51: MANCOMUNIDAD MUNICIPAL ANGARAES SUR- MANUAS | J51: 09 | K51: HUANCAVELICA | L51: 3 | M51: ANGARAES | N51: 9 | O51: JULCAMARCA | Q51: S | R51: S | W51: =IFERROR(VLOOKUP(H51,'IT PEI'!$X$2:$X$5647,1,0),"...") -> ... | X51: =_xlfn.XLOOKUP(H51,'IT PEI'!X$2:X$5647,'IT PEI'!E$2:E$5647,"...",2,-1) -> ... | Y51: =_xlfn.XLOOKUP(H51,'IT PEI'!X$2:X$5647,'IT PEI'!G$2:G$5647,"...",2,-1) -> ... | Z51: =_xlfn.XLOOKUP(H51,'IT PEI'!X$2:X$5647,'IT PEI'!F$2:F$5647,"...",2,-1) -> ... | AA51: =_xlfn.XLOOKUP(H51,'IT PEI'!X$2:X$5647,'IT PEI'!H$2:H$5647,"...",2,-1) -> ... | AB51: =_xlfn.XLOOKUP(H51,'IT PEI'!X$2:X$5647,'IT PEI'!O$2:O$5647,"...",2,-1) -> ... | AC51: =_xlfn.XLOOKUP(H51,'IT PEI'!X$2:X$5647,'IT PEI'!P$2:P$5647,"...",2,-1) -> ... | AD51: =_xlfn.XLOOKUP(H51,'IT PEI'!X$2:X$5647,'IT PEI'!Q$2:Q$5647,"...",2,-1) -> ... | AE51: =IF(COUNTIF(X51, "*" & "2030" & "*")>0, "SI", "No" ) -> No | AF51: =IF(COUNTIF(X51, "*" & "2030" & "*")>0, 1, 0 ) -> 0 | AG51: =IF(COUNTIF(X51, "*" & "2030" & "*")>0, 0, 1 ) -> 1 | AH51: =IF(AND(AA51="En Proceso",AE51="Si"),1,0) -> 0 | AI51: INACTIVO | AL51: =IFERROR(VLOOKUP(tbl_ues[[#This Row],[Id_UE]],'[1]Directorio v.02'!$H$3:$U$3089,11,FALSE),"") | AM51: =IFERROR(VLOOKUP(tbl_ues[[#This Row],[Id_UE]],'[1]Directorio v.02'!$H$3:$U$3089,12,FALSE),"") | AN51: =IFERROR(VLOOKUP(tbl_ues[[#This Row],[Id_UE]],'[1]Directorio v.02'!$H$3:$U$3089,13,FALSE),"") | AO51: =IFERROR(VLOOKUP(tbl_ues[[#This Row],[Id_UE]],'[1]Directorio v.02'!$H$3:$U$3089,14,FALSE),"") | AP51: =VLOOKUP(H51,#REF!,7,0) -> #REF! | AQ51: =VLOOKUP(H51,#REF!,9,0) -> #REF! | AR51: =VLOOKUP(H51,#REF!,15,0) -> #REF! | AS51: =VLOOKUP(H51,#REF!,16,0) -> #REF! | AT51: =VLOOKUP(H51,#REF!,17,0) -> #REF! | AU51: =VLOOKUP(H51,#REF!,18,0) -> #REF! | AV51: =VLOOKUP(H51,#REF!,19,0) -> #REF! | AW51: =VLOOKUP(H51,#REF!,20,0) -> #REF! | AX51: =VLOOKUP(H51,#REF!,22,0) -> #REF! | AY51: =VLOOKUP(H51,#REF!,23,0) -> #REF! | AZ51: =VLOOKUP(H51,#REF!,24,0) -> #REF! | BA51: =VLOOKUP(H51,#REF!,25,0) -> #REF! | BB51: =VLOOKUP(H51,#REF!,26,0) -> #REF! | BC51: =VLOOKUP(H51,#REF!,27,0) -> #REF! | BD51: =VLOOKUP(H51,#REF!,29,0) -> #REF! | BE51: =VLOOKUP(H51,#REF!,30,0) -> #REF! | BF51: =VLOOKUP(H51,#REF!,31,0) -> #REF! | BG51: =VLOOKUP(H51,#REF!,32,0) -> #REF! | BH51: =VLOOKUP(H51,#REF!,33,0) -> #REF! | BI51: =VLOOKUP(H51,#REF!,34,0) -> #REF! | BJ51: =VLOOKUP(H51,#REF!,36,0) -> #REF! | BK51: =VLOOKUP(H51,#REF!,37,0) -> #REF! | BL51: =VLOOKUP(H51,#REF!,44,0) -> #REF! | BM51: =VLOOKUP(H51,#REF!,45,0) -> #REF! | BN51: =VLOOKUP(H51,#REF!,46,0) -> #REF! | BO51: =VLOOKUP(H51,#REF!,47,0) -> #REF! | BP51: =VLOOKUP(H51,#REF!,48,0) -> #REF!
A52: Mancomunidad | B52: Mancomunidad | C52: N | D52: 0 | E52: FICTICIO | F52: 350029 | G52: MANCOMUNIDAD MUNICIPAL CUENCA CACHI | H52: 350029 | I52: MANCOMUNIDAD MUNICIPAL CUENCA CACHI | J52: 05 | K52: AYACUCHO | L52: 2 | M52: CANGALLO | N52: 3 | O52: LOS MOROCHUCOS | Q52: S | R52: S | W52: =IFERROR(VLOOKUP(H52,'IT PEI'!$X$2:$X$5647,1,0),"...") -> ... | X52: =_xlfn.XLOOKUP(H52,'IT PEI'!X$2:X$5647,'IT PEI'!E$2:E$5647,"...",2,-1) -> ... | Y52: =_xlfn.XLOOKUP(H52,'IT PEI'!X$2:X$5647,'IT PEI'!G$2:G$5647,"...",2,-1) -> ... | Z52: =_xlfn.XLOOKUP(H52,'IT PEI'!X$2:X$5647,'IT PEI'!F$2:F$5647,"...",2,-1) -> ... | AA52: =_xlfn.XLOOKUP(H52,'IT PEI'!X$2:X$5647,'IT PEI'!H$2:H$5647,"...",2,-1) -> ... | AB52: =_xlfn.XLOOKUP(H52,'IT PEI'!X$2:X$5647,'IT PEI'!O$2:O$5647,"...",2,-1) -> ... | AC52: =_xlfn.XLOOKUP(H52,'IT PEI'!X$2:X$5647,'IT PEI'!P$2:P$5647,"...",2,-1) -> ... | AD52: =_xlfn.XLOOKUP(H52,'IT PEI'!X$2:X$5647,'IT PEI'!Q$2:Q$5647,"...",2,-1) -> ... | AE52: =IF(COUNTIF(X52, "*" & "2030" & "*")>0, "SI", "No" ) -> No | AF52: =IF(COUNTIF(X52, "*" & "2030" & "*")>0, 1, 0 ) -> 0 | AG52: =IF(COUNTIF(X52, "*" & "2030" & "*")>0, 0, 1 ) -> 1 | AH52: =IF(AND(AA52="En Proceso",AE52="Si"),1,0) -> 0 | AI52: INACTIVO | AL52: =IFERROR(VLOOKUP(tbl_ues[[#This Row],[Id_UE]],'[1]Directorio v.02'!$H$3:$U$3089,11,FALSE),"") | AM52: =IFERROR(VLOOKUP(tbl_ues[[#This Row],[Id_UE]],'[1]Directorio v.02'!$H$3:$U$3089,12,FALSE),"") | AN52: =IFERROR(VLOOKUP(tbl_ues[[#This Row],[Id_UE]],'[1]Directorio v.02'!$H$3:$U$3089,13,FALSE),"") | AO52: =IFERROR(VLOOKUP(tbl_ues[[#This Row],[Id_UE]],'[1]Directorio v.02'!$H$3:$U$3089,14,FALSE),"") | AP52: =VLOOKUP(H52,#REF!,7,0) -> #REF! | AQ52: =VLOOKUP(H52,#REF!,9,0) -> #REF! | AR52: =VLOOKUP(H52,#REF!,15,0) -> #REF! | AS52: =VLOOKUP(H52,#REF!,16,0) -> #REF! | AT52: =VLOOKUP(H52,#REF!,17,0) -> #REF! | AU52: =VLOOKUP(H52,#REF!,18,0) -> #REF! | AV52: =VLOOKUP(H52,#REF!,19,0) -> #REF! | AW52: =VLOOKUP(H52,#REF!,20,0) -> #REF! | AX52: =VLOOKUP(H52,#REF!,22,0) -> #REF! | AY52: =VLOOKUP(H52,#REF!,23,0) -> #REF! | AZ52: =VLOOKUP(H52,#REF!,24,0) -> #REF! | BA52: =VLOOKUP(H52,#REF!,25,0) -> #REF! | BB52: =VLOOKUP(H52,#REF!,26,0) -> #REF! | BC52: =VLOOKUP(H52,#REF!,27,0) -> #REF! | BD52: =VLOOKUP(H52,#REF!,29,0) -> #REF! | BE52: =VLOOKUP(H52,#REF!,30,0) -> #REF! | BF52: =VLOOKUP(H52,#REF!,31,0) -> #REF! | BG52: =VLOOKUP(H52,#REF!,32,0) -> #REF! | BH52: =VLOOKUP(H52,#REF!,33,0) -> #REF! | BI52: =VLOOKUP(H52,#REF!,34,0) -> #REF! | BJ52: =VLOOKUP(H52,#REF!,36,0) -> #REF! | BK52: =VLOOKUP(H52,#REF!,37,0) -> #REF! | BL52: =VLOOKUP(H52,#REF!,44,0) -> #REF! | BM52: =VLOOKUP(H52,#REF!,45,0) -> #REF! | BN52: =VLOOKUP(H52,#REF!,46,0) -> #REF! | BO52: =VLOOKUP(H52,#REF!,47,0) -> #REF! | BP52: =VLOOKUP(H52,#REF!,48,0) -> #REF!
A53: Mancomunidad | B53: Mancomunidad | C53: N | D53: 0 | E53: FICTICIO | F53: 350028 | G53: MANCOMUNIDAD MUNICIPAL DE HATUN HUAYLAS | H53: 350028 | I53: MANCOMUNIDAD MUNICIPAL DE HATUN HUAYLAS | J53: 02 | K53: ANCASH | L53: 20 | M53: YUNGAY | N53: 1 | O53: YUNGAY | Q53: S | R53: S | W53: =IFERROR(VLOOKUP(H53,'IT PEI'!$X$2:$X$5647,1,0),"...") -> ... | X53: =_xlfn.XLOOKUP(H53,'IT PEI'!X$2:X$5647,'IT PEI'!E$2:E$5647,"...",2,-1) -> ... | Y53: =_xlfn.XLOOKUP(H53,'IT PEI'!X$2:X$5647,'IT PEI'!G$2:G$5647,"...",2,-1) -> ... | Z53: =_xlfn.XLOOKUP(H53,'IT PEI'!X$2:X$5647,'IT PEI'!F$2:F$5647,"...",2,-1) -> ... | AA53: =_xlfn.XLOOKUP(H53,'IT PEI'!X$2:X$5647,'IT PEI'!H$2:H$5647,"...",2,-1) -> ... | AB53: =_xlfn.XLOOKUP(H53,'IT PEI'!X$2:X$5647,'IT PEI'!O$2:O$5647,"...",2,-1) -> ... | AC53: =_xlfn.XLOOKUP(H53,'IT PEI'!X$2:X$5647,'IT PEI'!P$2:P$5647,"...",2,-1) -> ... | AD53: =_xlfn.XLOOKUP(H53,'IT PEI'!X$2:X$5647,'IT PEI'!Q$2:Q$5647,"...",2,-1) -> ... | AE53: =IF(COUNTIF(X53, "*" & "2030" & "*")>0, "SI", "No" ) -> No | AF53: =IF(COUNTIF(X53, "*" & "2030" & "*")>0, 1, 0 ) -> 0 | AG53: =IF(COUNTIF(X53, "*" & "2030" & "*")>0, 0, 1 ) -> 1 | AH53: =IF(AND(AA53="En Proceso",AE53="Si"),1,0) -> 0 | AI53: INACTIVO | AL53: =IFERROR(VLOOKUP(tbl_ues[[#This Row],[Id_UE]],'[1]Directorio v.02'!$H$3:$U$3089,11,FALSE),"") | AM53: =IFERROR(VLOOKUP(tbl_ues[[#This Row],[Id_UE]],'[1]Directorio v.02'!$H$3:$U$3089,12,FALSE),"") | AN53: =IFERROR(VLOOKUP(tbl_ues[[#This Row],[Id_UE]],'[1]Directorio v.02'!$H$3:$U$3089,13,FALSE),"") | AO53: =IFERROR(VLOOKUP(tbl_ues[[#This Row],[Id_UE]],'[1]Directorio v.02'!$H$3:$U$3089,14,FALSE),"") | AP53: =VLOOKUP(H53,#REF!,7,0) -> #REF! | AQ53: =VLOOKUP(H53,#REF!,9,0) -> #REF! | AR53: =VLOOKUP(H53,#REF!,15,0) -> #REF! | AS53: =VLOOKUP(H53,#REF!,16,0) -> #REF! | AT53: =VLOOKUP(H53,#REF!,17,0) -> #REF! | AU53: =VLOOKUP(H53,#REF!,18,0) -> #REF! | AV53: =VLOOKUP(H53,#REF!,19,0) -> #REF! | AW53: =VLOOKUP(H53,#REF!,20,0) -> #REF! | AX53: =VLOOKUP(H53,#REF!,22,0) -> #REF! | AY53: =VLOOKUP(H53,#REF!,23,0) -> #REF! | AZ53: =VLOOKUP(H53,#REF!,24,0) -> #REF! | BA53: =VLOOKUP(H53,#REF!,25,0) -> #REF! | BB53: =VLOOKUP(H53,#REF!,26,0) -> #REF! | BC53: =VLOOKUP(H53,#REF!,27,0) -> #REF! | BD53: =VLOOKUP(H53,#REF!,29,0) -> #REF! | BE53: =VLOOKUP(H53,#REF!,30,0) -> #REF! | BF53: =VLOOKUP(H53,#REF!,31,0) -> #REF! | BG53: =VLOOKUP(H53,#REF!,32,0) -> #REF! | BH53: =VLOOKUP(H53,#REF!,33,0) -> #REF! | BI53: =VLOOKUP(H53,#REF!,34,0) -> #REF! | BJ53: =VLOOKUP(H53,#REF!,36,0) -> #REF! | BK53: =VLOOKUP(H53,#REF!,37,0) -> #REF! | BL53: =VLOOKUP(H53,#REF!,44,0) -> #REF! | BM53: =VLOOKUP(H53,#REF!,45,0) -> #REF! | BN53: =VLOOKUP(H53,#REF!,46,0) -> #REF! | BO53: =VLOOKUP(H53,#REF!,47,0) -> #REF! | BP53: =VLOOKUP(H53,#REF!,48,0) -> #REF!
A54: Mancomunidad | B54: Mancomunidad | C54: N | D54: 0 | E54: FICTICIO | F54: 350027 | G54: MANCOMUNIDAD MUNICIPAL DEL CORREDOR MANTARO | H54: 350027 | I54: MANCOMUNIDAD MUNICIPAL DEL CORREDOR MANTARO | J54: 12 | K54: JUNIN | L54: 1 | M54: HUANCAYO | N54: 1 | O54: HUANCAYO | Q54: S | R54: S | W54: =IFERROR(VLOOKUP(H54,'IT PEI'!$X$2:$X$5647,1,0),"...") -> ... | X54: =_xlfn.XLOOKUP(H54,'IT PEI'!X$2:X$5647,'IT PEI'!E$2:E$5647,"...",2,-1) -> ... | Y54: =_xlfn.XLOOKUP(H54,'IT PEI'!X$2:X$5647,'IT PEI'!G$2:G$5647,"...",2,-1) -> ... | Z54: =_xlfn.XLOOKUP(H54,'IT PEI'!X$2:X$5647,'IT PEI'!F$2:F$5647,"...",2,-1) -> ... | AA54: =_xlfn.XLOOKUP(H54,'IT PEI'!X$2:X$5647,'IT PEI'!H$2:H$5647,"...",2,-1) -> ... | AB54: =_xlfn.XLOOKUP(H54,'IT PEI'!X$2:X$5647,'IT PEI'!O$2:O$5647,"...",2,-1) -> ... | AC54: =_xlfn.XLOOKUP(H54,'IT PEI'!X$2:X$5647,'IT PEI'!P$2:P$5647,"...",2,-1) -> ... | AD54: =_xlfn.XLOOKUP(H54,'IT PEI'!X$2:X$5647,'IT PEI'!Q$2:Q$5647,"...",2,-1) -> ... | AE54: =IF(COUNTIF(X54, "*" & "2030" & "*")>0, "SI", "No" ) -> No | AF54: =IF(COUNTIF(X54, "*" & "2030" & "*")>0, 1, 0 ) -> 0 | AG54: =IF(COUNTIF(X54, "*" & "2030" & "*")>0, 0, 1 ) -> 1 | AH54: =IF(AND(AA54="En Proceso",AE54="Si"),1,0) -> 0 | AI54: INACTIVO | AL54: =IFERROR(VLOOKUP(tbl_ues[[#This Row],[Id_UE]],'[1]Directorio v.02'!$H$3:$U$3089,11,FALSE),"") | AM54: =IFERROR(VLOOKUP(tbl_ues[[#This Row],[Id_UE]],'[1]Directorio v.02'!$H$3:$U$3089,12,FALSE),"") | AN54: =IFERROR(VLOOKUP(tbl_ues[[#This Row],[Id_UE]],'[1]Directorio v.02'!$H$3:$U$3089,13,FALSE),"") | AO54: =IFERROR(VLOOKUP(tbl_ues[[#This Row],[Id_UE]],'[1]Directorio v.02'!$H$3:$U$3089,14,FALSE),"") | AP54: =VLOOKUP(H54,#REF!,7,0) -> #REF! | AQ54: =VLOOKUP(H54,#REF!,9,0) -> #REF! | AR54: =VLOOKUP(H54,#REF!,15,0) -> #REF! | AS54: =VLOOKUP(H54,#REF!,16,0) -> #REF! | AT54: =VLOOKUP(H54,#REF!,17,0) -> #REF! | AU54: =VLOOKUP(H54,#REF!,18,0) -> #REF! | AV54: =VLOOKUP(H54,#REF!,19,0) -> #REF! | AW54: =VLOOKUP(H54,#REF!,20,0) -> #REF! | AX54: =VLOOKUP(H54,#REF!,22,0) -> #REF! | AY54: =VLOOKUP(H54,#REF!,23,0) -> #REF! | AZ54: =VLOOKUP(H54,#REF!,24,0) -> #REF! | BA54: =VLOOKUP(H54,#REF!,25,0) -> #REF! | BB54: =VLOOKUP(H54,#REF!,26,0) -> #REF! | BC54: =VLOOKUP(H54,#REF!,27,0) -> #REF! | BD54: =VLOOKUP(H54,#REF!,29,0) -> #REF! | BE54: =VLOOKUP(H54,#REF!,30,0) -> #REF! | BF54: =VLOOKUP(H54,#REF!,31,0) -> #REF! | BG54: =VLOOKUP(H54,#REF!,32,0) -> #REF! | BH54: =VLOOKUP(H54,#REF!,33,0) -> #REF! | BI54: =VLOOKUP(H54,#REF!,34,0) -> #REF! | BJ54: =VLOOKUP(H54,#REF!,36,0) -> #REF! | BK54: =VLOOKUP(H54,#REF!,37,0) -> #REF! | BL54: =VLOOKUP(H54,#REF!,44,0) -> #REF! | BM54: =VLOOKUP(H54,#REF!,45,0) -> #REF! | BN54: =VLOOKUP(H54,#REF!,46,0) -> #REF! | BO54: =VLOOKUP(H54,#REF!,47,0) -> #REF! | BP54: =VLOOKUP(H54,#REF!,48,0) -> #REF!
A55: Mancomunidad | B55: Mancomunidad | C55: N | D55: 0 | E55: FICTICIO | F55: 350026 | G55: MANCOMUNIDAD MUNICIPAL DE LA CUENCA VALLE DE LURIN | H55: 350026 | I55: MANCOMUNIDAD MUNICIPAL DE LA CUENCA VALLE DE LURIN | J55: 15 | K55: LIMA | L55: 7 | M55: HUAROCHIRI | N55: 15 | O55: SAN ANDRES DE TUPICOCHA | Q55: S | R55: S | W55: =IFERROR(VLOOKUP(H55,'IT PEI'!$X$2:$X$5647,1,0),"...") -> ... | X55: =_xlfn.XLOOKUP(H55,'IT PEI'!X$2:X$5647,'IT PEI'!E$2:E$5647,"...",2,-1) -> ... | Y55: =_xlfn.XLOOKUP(H55,'IT PEI'!X$2:X$5647,'IT PEI'!G$2:G$5647,"...",2,-1) -> ... | Z55: =_xlfn.XLOOKUP(H55,'IT PEI'!X$2:X$5647,'IT PEI'!F$2:F$5647,"...",2,-1) -> ... | AA55: =_xlfn.XLOOKUP(H55,'IT PEI'!X$2:X$5647,'IT PEI'!H$2:H$5647,"...",2,-1) -> ... | AB55: =_xlfn.XLOOKUP(H55,'IT PEI'!X$2:X$5647,'IT PEI'!O$2:O$5647,"...",2,-1) -> ... | AC55: =_xlfn.XLOOKUP(H55,'IT PEI'!X$2:X$5647,'IT PEI'!P$2:P$5647,"...",2,-1) -> ... | AD55: =_xlfn.XLOOKUP(H55,'IT PEI'!X$2:X$5647,'IT PEI'!Q$2:Q$5647,"...",2,-1) -> ... | AE55: =IF(COUNTIF(X55, "*" & "2030" & "*")>0, "SI", "No" ) -> No | AF55: =IF(COUNTIF(X55, "*" & "2030" & "*")>0, 1, 0 ) -> 0 | AG55: =IF(COUNTIF(X55, "*" & "2030" & "*")>0, 0, 1 ) -> 1 | AH55: =IF(AND(AA55="En Proceso",AE55="Si"),1,0) -> 0 | AI55: INACTIVO | AL55: =IFERROR(VLOOKUP(tbl_ues[[#This Row],[Id_UE]],'[1]Directorio v.02'!$H$3:$U$3089,11,FALSE),"") | AM55: =IFERROR(VLOOKUP(tbl_ues[[#This Row],[Id_UE]],'[1]Directorio v.02'!$H$3:$U$3089,12,FALSE),"") | AN55: =IFERROR(VLOOKUP(tbl_ues[[#This Row],[Id_UE]],'[1]Directorio v.02'!$H$3:$U$3089,13,FALSE),"") | AO55: =IFERROR(VLOOKUP(tbl_ues[[#This Row],[Id_UE]],'[1]Directorio v.02'!$H$3:$U$3089,14,FALSE),"") | AP55: =VLOOKUP(H55,#REF!,7,0) -> #REF! | AQ55: =VLOOKUP(H55,#REF!,9,0) -> #REF! | AR55: =VLOOKUP(H55,#REF!,15,0) -> #REF! | AS55: =VLOOKUP(H55,#REF!,16,0) -> #REF! | AT55: =VLOOKUP(H55,#REF!,17,0) -> #REF! | AU55: =VLOOKUP(H55,#REF!,18,0) -> #REF! | AV55: =VLOOKUP(H55,#REF!,19,0) -> #REF! | AW55: =VLOOKUP(H55,#REF!,20,0) -> #REF! | AX55: =VLOOKUP(H55,#REF!,22,0) -> #REF! | AY55: =VLOOKUP(H55,#REF!,23,0) -> #REF! | AZ55: =VLOOKUP(H55,#REF!,24,0) -> #REF! | BA55: =VLOOKUP(H55,#REF!,25,0) -> #REF! | BB55: =VLOOKUP(H55,#REF!,26,0) -> #REF! | BC55: =VLOOKUP(H55,#REF!,27,0) -> #REF! | BD55: =VLOOKUP(H55,#REF!,29,0) -> #REF! | BE55: =VLOOKUP(H55,#REF!,30,0) -> #REF! | BF55: =VLOOKUP(H55,#REF!,31,0) -> #REF! | BG55: =VLOOKUP(H55,#REF!,32,0) -> #REF! | BH55: =VLOOKUP(H55,#REF!,33,0) -> #REF! | BI55: =VLOOKUP(H55,#REF!,34,0) -> #REF! | BJ55: =VLOOKUP(H55,#REF!,36,0) -> #REF! | BK55: =VLOOKUP(H55,#REF!,37,0) -> #REF! | BL55: =VLOOKUP(H55,#REF!,44,0) -> #REF! | BM55: =VLOOKUP(H55,#REF!,45,0) -> #REF! | BN55: =VLOOKUP(H55,#REF!,46,0) -> #REF! | BO55: =VLOOKUP(H55,#REF!,47,0) -> #REF! | BP55: =VLOOKUP(H55,#REF!,48,0) -> #REF!
